Workbook
Name AÑOS: Lists!$Q$2:$Q$31
Name lin: Lists!$A$2:$A$6
Name por.form: FORMULACIÓN!$C$8:$I$1011
Name por.pry: Lists!$K$100:$P$157
Name proyectos: Lists!$A$50:$S$59
Name rang: #REF!
Name rang2: #REF!
Name TablaBase: SEGUIMIENTO!$AI$9:$AV$216

Sheet INSTRUCTIVO
A3: INSTRUCTIVO PARA EL DILIGENCIAMIENTO DEL FORMATO
A5: Este formato está formulado sobre una matriz de búsqueda, por lo cual NO SE DEBE insertar, eliminar o combinar celdas. Las columnas resaltadas en azul no deben ser diligenciadas, ya que contienen cálculos o datos asociados.
A8: HOJA DE CÁLCULO: FORMULACIÓN
A10: Esta hoja de cálculo aplica para todas las dependencias que planifiquen un Plan de Acción. Los campos del formato están identificados por números consecutivos, a continuación se indica la manera de diligenciar cada uno de ellos:
A12: 1. DEPENDENCIA QUE LO GENERA:
B13: Seleccione de la lista desplegable la dependencia que genera el plan de acción.
A15: 2. AÑO DE INICIO:
B16: Seleccione de la lista desplegable el año de inicio del plan de acción.
A18: 3. AÑO DE FINALIZACIÓN:
B19: Seleccione de la lista desplegable el año de finalización del plan de acción.
A21: 4. PERÍODO DEL PLAN DE ACCIÓN:
B22: Celda formulada, no diligenciar.
A24: 5. LÍNEA ESTRATÉGICA:
B25: Seleccione de la lista desplegable la línea estratégica.
A27: 6. OBJETIVO:
B28: Celda formulada, se auto rellena de acuerdo con la línea estratégica seleccionada.
A30: 7. ESTRATEGIA:
B31: Seleccione de la lista desplegable la estrategia a aplicar.
A33: 8. MOTOR DE DESARROLLO:
B34: Seleccione de la lista desplegable el motor correspondiente.
A36: 9. META DE RESULTADO:
B37: Digite la meta de resultado asociada al PDI, o en su defecto la meta propuesta para la vigencia del plan de acción.
A39: 10. PROYECTO:
B40: Seleccione de la lista desplegable el proyecto vinculado al motor de desarrollo. Tenga en cuenta que los proyectos se encuentran alineados al presupuesto de la vigencia.
A42: 11. PONDERACIÓN DE LOS PROYECTOS:
B43: Establezca el peso o ponderación de cada uno de los proyectos para el plan, cuya sumatoria debe ser igual a 100%. De manera que la mayor ponderación indique mayor prioridad. Cada vez que relacione ese proyecto debe repetirse la ponderación ya definida. Es de aclarar que cada motor tiene asociados sus proyectos, pero para la ponderación debe tenerse en cuenta el total de proyectos del plan.
B44: Ejemplo: | H44: Digite en el formato de acuerdo con la ponderación asignada
C45: Asignación del peso/ponderación | H45: M1 P1 | I45: 0.2
C46: M1 P1 | D46: 0.2 | H46: M1 P1 | I46: 0.2
C47: M1 P2 | D47: 0.1 | H47: M1 P1 | I47: 0.2
C48: M2 P1 | D48: 0.3 | H48: M1 P2 | I48: 0.1
C49: M2 P2 | D49: 0.4 | H49: M1 P2 | I49: 0.1
C50: total PA | D50: =SUM(D46:D49) -> 1 | H50: M2 P1 | I50: 0.3
H51: M2 P2 | I51: 0.4
A53: 12. ACTIVIDAD DEL PROYECTO:
B54: Describa las actividades que se relacionan con el proyecto, se recomienda que inicie con un verbo en infinitivo. La celda (I7) está formulada para contar el número de actividades del PA
A56: 13. PONDERACIÓN DE LA ACTIVIDADES POR PROYECTO:
B57: Establezca el peso de la ACTIVIDAD con respecto al PROYECTO. Ejemplo: El peso de la actividad X es del 25% del valor de todo el proyecto. La sumatoria de las actividades agrupadas por proyectos debe ser igual a 100%.
A59: 14. RESPONSABLE:
B60: Seleccione de la lista desplegable el responsable de la actividad.
A62: 15. GESTIONADO EN FACULTADES:
B63: Marque con una "X" si la actividad será gestionada desde las facultades. Esta información es importante porque esta actividad con su indicador será incluida en los planes de acción de las facultades, así mismo, la meta establecida desde la vicerrectoría debe coincidir con la sumatoria de las metas de las facultades, para ello debe diligenciarse la hoja "ANEXO FORMULACIÓN FACULTADES". Es conveniente la concertación de estas metas entre la vicerrectoría y las facultades.
A66: 16. INDICADOR DE RESULTADO:
B67: 16.1 NOMBRE DEL INDICADOR:
B68: Establezca el nombre del indicador propuesto para el control y seguimiento de la actividad.
B70: 16.2 FÓRMULA DE LA MEDICIÓN:
B71: Establezca la fórmula con la cual medirá el indicador.
B73: 16.3 FRECUENCIA DE MEDICIÓN:
B74: Seleccione de la lista desplegable la frecuencia de medición del indicador.
B76: 16.4. UNIDAD DE MEDIDA:
B77: Seleccione de la lista desplegable el formato asociado para la medición del indicador.
B79: 16.5 TIPO DE MEDICIÓN:
B80: Seleccione de la lista desplegable el formato de cálculo para la evaluación del cumplimiento del indicador durante el seguimiento, de acuerdo a las siguientes consideraciones:
C81: ACUMULADO: sumatoria de valores (incluye la línea base)
C82: NUEVO GESTIONADO DURANTE LA VIGENCIA: corresponde a lo realizado durante la vigencia, parte de 0.
C83: PROMEDIO: sumatoria de ítems/número de ítems.
C84: ÚLTIMO VALOR REPORTADO: corresponde al último registro.
C85: LÍMITE: valor que no debe superarse (Evaluación dicotómica del cumplimiento)
A87: 17. META PROPUESTA:
B88: 17.1 LÍNEA BASE:
B89: Relacione de acuerdo al tipo de medición (acumulado, último valor, promedio, etc.) el valor alcanzado a corte del año anterior.
B91: 17.2 SEMESTRE 1:
B92: Describa la meta individual propuesta para el primer semestre del año, si la frecuencia de medición es semestral. O establezca de la meta anual, cuánto estima alcanzar durante el primer semestre. Tenga en cuenta el tipo de medición.
B94: 17.3 SEMESTRE 2:
B95: Describa la meta individual propuesta para el segundo semestre del año, si la frecuencia de medición es semestral. O establezca de la meta anual, cuánto estima alcanzar durante el segundo semestre. Tenga en cuenta el tipo de medición.
B97: 17.4 AÑO:
B98: Celda formulada, no diligenciar. De acuerdo al tipo de medición seleccionada, se autor rellena el valor correspondiente a la meta del año.
A100: 18. VALOR TOTAL Y FINANCIACIÓN DEL AÑO:
B101: 18.1 NIVEL CENTRAL:
B102: Si los recursos del proyecto provienen del nivel central(recursos asignados para el funcionamiento o que procesada de leyes, decretos, acuerdos, resoluciones, o cualquier otra fuentes asignada por la nación o gobernación sobre la cual la Universidad no tiene potestad para establecer valor a girársele sus cuentas) indique el valor en pesos para el proyecto. Tenga en cuenta que se está cuantificando el proyecto no las actividades.
B104: 18.2 AUTOGESTIÓN:
B105: Si los recursos del proyecto provienen de autogestión(recursos de procedan de postgrados, venta de servicios o gestión que procedan del Departamento de Extensión) indique el valor en pesos para el proyecto. Tenga en cuenta que se está cuantificando el proyecto no las actividades.
B107: 18.3 CONVENIOS:
B108: Si los recursos del proyecto provienen de convenios(recursos provenientes de Minciencias, Sistema General de Regalías, contratos o convenios gestionadas a través del Departamento de Investigación) indique el valor en pesos para el proyecto según el tipo de convenio. Tenga en cuenta que se está cuantificando el proyecto no las actividades.
B110: 18.4 TOTAL DE RECURSOS PA:
B111: Celda formulada, no diligenciar. Se autor rellena el valor correspondiente a la sumatoria de los recursos para el año.
A113: 19. PROPUESTA RECTORAL:
B114: Marque con una "X" si la actividad está articulada a la propuesta rectoral vigente.
A116: 20. PLAN DE MEJORAMIENTO INSTITUCIONAL:
B117: Marque con una "X" si la actividad está articulada al plan de mejoramiento institucional.
A119: 21. PLANES INSTITUCIONALES DECRETO 612 DE 2018:
B120: Marque con una "X" si la actividad está articulada a alguno de los siguientes planes institucionales: plan institucional de archivos de la entidad PINAR, plan anticorrupción y de atención al ciudadano, plan anual de adquisiciones, plan anual de vacantes, plan de incentivos institucionales, plan de previsión de recursos humanos, plan de seguridad y privacidad de la información, plan de trabajo anual en SST, plan de tratamiento de riesgos de seguridad y privacidad de la información, plan estratégico de talento humano, plan estratégico de tecnologías de la información y la comunicación PETIC, plan institucional de capacitación.
A122: HOJA DE CÁLCULO: SEGUIMIENTO
A124: Esta hoja de cálculo aplica para todas las dependencias que vayan a reportar seguimiento del Plan de Acción proyectado. El formato está formulado (celdas azules) para traer la información diligenciada en la hoja de Formulación, por lo tanto SÓLO debe diligenciarse las celdas sin relleno que se indican a continuación:
A126: REPORTE DE LA META
B127: SEMESTRE 1:
B128: Indique el cumplimiento del primer semestre del año, de acuerdo a la gestión realizada, no debe incluirse el valor de la LÍNEA BASE.
B130: SEMESTRE 2:
B131: Indique el cumplimiento del segundo semestre del año, de acuerdo a la gestión realizada, no debe incluirse el valor de la LÍNEA BASE ni del primer semestre.
A133: VALOR TOTAL Y FINANCIACIÓN DEL AÑO:
B134: NIVEL CENTRAL:
B135: Indique el valor ejecutado en pesos para el proyecto de acuerdo a lo planificado. Tenga en cuenta que se está cuantificando el proyecto no de las actividades.
B137: AUTOGESTIÓN:
B138: Indique el valor ejecutado en pesos para el proyecto de acuerdo a lo planificado. Tenga en cuenta que se está cuantificando el proyecto no de las actividades.
B140: CONVENIOS:
B141: Indique el valor ejecutado en pesos para el proyecto de acuerdo a lo planificado. Tenga en cuenta que se está cuantificando el proyecto no de las actividades.
A143: ESTADO DE PROYECTOS:
B144: Describa de forma concreta y resumida en las celdas LOGROS, LÍMITES, OBSERVACIÓN y ACCIONES DE FORTALECIMIENTO, las consideraciones de la gestión realizada respecto a la actividad planificada, o al cumplimiento de la meta propuesta.
A147: HOJA DE CÁLCULO: ANEXO FORMULACIÓN FACULTADES
A149: Esta hoja aplica para las vicerrectorías y/o oficinas que durante la formulación del Plan de Acción hayan identificado mediante una "X" en la columna "Gestionado en Facultades" de la hoja de Formulación, las actividades que deberían ser gestionadas desde las facultades. De manera que se deberá distribuir de la meta global, las metas de cada facultad para esa actividad del proyecto, especificando cuantitativa y cualitativamente, cómo la gestión de la facultad contribuirá a la meta global. El formato está formulado (celdas azules) para traer la información diligenciada en la hoja de Formulación, por lo tanto SÓLO debe diligenciarse las celdas sin relleno que se indican a continuación:
...

Sheet FORMULACIÓN
AK1: CÓDIGO: FOR-DE-144 | AN1: X
AK2: VERSIÓN: 3
AK3: FECHA: 26/MAR/2025
A4: FORMULACIÓN Y SEGUIMIENTO DE PLAN DE ACCIÓN
A6: Año: | D6: Semestre: | G6: 1. DEPENDENCIA QUE LO GENERA: | K6: 3. AÑO DE FINALIZACIÓN: | AK6: 4. PERÍODO DEL PLAN DE ACCIÓN: | AL6: =IF(SUM(C6,M6)=0,"",IF(AND(C6,M6)>0,CONCATENATE(C6," - ",M6)))
A8: N° | B8: AÑO | C8: 5. LÍNEA ESTRATÉGICA | D8: 6. OBJETIVO | E8: 7. ESTRATEGIA | F8: 8. MOTOR DE DESARROLLO | G8: 9. META DE RESULTADO | H8: ="10. PROYECTO" -> 10. PROYECTO | I8: 11. PONDERACIÓN DE LOS PROYECTOS | J8: ="12. ACTIVIDAD DEL PROYECTO"&CHAR(10)&"("& COUNTA(J10:J1010)&")" -> 12. ACTIVIDAD DEL PROYECTO (172) | K8: 13. PONDERACIÓN DE LA ACTIVIDADES POR PROYECTO | L8: 14. RESPONSABLE | M8: ID.INDICADOR | N8: 15. GESTIONADO EN FACULTADES | O8: 16. INDICADOR DE RESULTADO | U8: 17. META PROPUESTA | Z8: 19. Propuestas rectorales | AA8: 20. Plan de Mejoramiento Institucional | AB8: 21. PLANES INSTITUCIONALES DECRETO 612 DE 2018
O9: 16.1 NOMBRE DEL INDICADOR | P9: 16.2 FÓRMULA DE LA MEDICIÓN | Q9: 16.3 FRECUENCIA DE MEDICIÓN | R9: 16.4. UNIDAD DE MEDIDA | S9: DESCRIPCIÓN | T9: 16.5 TIPO DE MEDICIÓN | U9: 17.1 LÍNEA BASE | V9: 17.2 SEMESTRE 1 | W9: 17.3 SEMESTRE 2 | Y9: 17.4 AÑO | AB9: Plan Institucional de Archivos de la Entidad ­PINAR | AC9: Plan Anticorrupción y de Atención al Ciudadano | AD9: Plan Anual de Adquisiciones | AE9: Plan Anual de Vacantes | AF9: Plan de Incentivos Institucionales | AG9: Plan de Previsión de Recursos Humanos | AH9: Plan de Seguridad y Privacidad de la Información | AI9: Plan de Trabajo Anual en Seguridad y Salud en el Trabajo | AJ9: Plan de Tratamiento de Riesgos de Seguridad y Privacidad de la Información | AK9: Plan Estratégico de Talento Humano | AL9: Plan Estratégico de Tecnologías de la Información y las Comunicaciones ­ PETIC | AM9: Plan Institucional de Capacitación
A10: =IF(C10<>"",1,"") -> 1 | B10: 2026 | C10: L1 - Formación Académica Integral | D10: =IFERROR(VLOOKUP(FORMULACIÓN!C10,Lists!$A$2:$B$6,2,FALSE),"") -> Garantizar la formación en educación superior de manera integral e inclusiva, con calidad, pertinencia, flexibilidad, interdisciplinariedad, competencias digitales, internacionalización, multilingüismo e interculturalidad, mediante procesos de autorregulación sostenible y con perspectiva regional. | E10: 3. Fortalecer los procesos de internacionalización, movilidad, multilingüismo e interculturalidad que visibilicen la Universidad a nivel nacional e internacional, y alcanzar un posicionamiento académico. | F10: M1 - Internacionalización y multilingüismo. | G10: Lograr por lo menos el 65% de los docentes de carrera profesoral certificados en nivel suficiencia en idiomas con nivel B2 | H10: P1 - Multilingüismo e interculturalidad | I10: 0.09 | J10: Promover la formación en inglés en nuestros docentes | K10: 0.333 | L10: Vicerrector De Docencia | M10: PDI | O10: Nivel de suficiencia en idiomas B2 de los docentes de carrera profesoral | P10: N° de docentes de carrera profesoral certificados con nivel B2 en suficiencia en idiomas / total de docentes de carrera profesoral * 100 | Q10: Anual | R10: Porcentaje | S10: La meta para este año es del 6%, lo que equivale a incrementar en cinco (5) docentes adicionales para alcanzar dicho objetivo. | T10: Último valor reportado | U10: 0.04 | V10: 0 | W10: 0.06 | X10: =IFERROR(IF($T10=Lists!$S$2,SUM(FORMULACIÓN!U10:W10),IF(FORMULACIÓN!$T10=Lists!$S$3,SUM(FORMULACIÓN!V10:W10),IF(FORMULACIÓN!$T10=Lists!$S$4,AVERAGE(FORMULACIÓN!V10:W10),IF(FORMULACIÓN!$T10=Lists!$S$5,OFFSET(U10,0,COUNTA(V10:W10)),IF(FORMULACIÓN!$T10=Lists!$S$6,AVERAGE(V10:W10),""))))),"") -> 0.06 | Y10: =IF($R10=Lists!$R$3,TEXT(FORMULACIÓN!X10,"00,00%"),IF(FORMULACIÓN!X10=0,0,TEXT(FORMULACIÓN!X10,"##.###"))) -> 06,00%
A11: =IF(C11<>"",+A10+1,"") -> 2 | B11: 2026 | C11: L1 - Formación Académica Integral | D11: =IFERROR(VLOOKUP(FORMULACIÓN!C11,Lists!$A$2:$B$6,2,FALSE),"") -> Garantizar la formación en educación superior de manera integral e inclusiva, con calidad, pertinencia, flexibilidad, interdisciplinariedad, competencias digitales, internacionalización, multilingüismo e interculturalidad, mediante procesos de autorregulación sostenible y con perspectiva regional. | E11: 3. Fortalecer los procesos de internacionalización, movilidad, multilingüismo e interculturalidad que visibilicen la Universidad a nivel nacional e internacional, y alcanzar un posicionamiento académico. | F11: M1 - Internacionalización y multilingüismo. | G11: Garantizar la Política de Enseñanza aprendizaje y evaluación de Lenguas Extranjeras para que mínimo 5.324 estudiantes logren culminar los cursos de inglés establecidos, asimismo que 199 estudiantes de Licenciatura en Lenguas Extranjeras se formen mediante el Programa de Inmersión en inglés | H11: P1 - Multilingüismo e interculturalidad | I11: 0.09 | J11: Gestionar la realización de actividades institucionales con componente multilingüe e intercultural para la comunidad estudiantil | K11: 0.333 | L11: Vicerrector De Docencia | M11: PDI | O11: Estudiantes formados mediante la Política de Enseñanza aprendizaje y evaluación de Lenguas Extranjeras | P11: N° de estudiantes que culminaron los cursos de inglés establecidos en la Política de Enseñanza aprendizaje y evaluación de Lenguas Extranjeras | Q11: Anual | R11: Unidad | T11: Nuevo gestionado durante la vigencia | U11: 1727 | V11: 0 | W11: 485 | X11: =IFERROR(IF($T11=Lists!$S$2,SUM(FORMULACIÓN!U11:W11),IF(FORMULACIÓN!$T11=Lists!$S$3,SUM(FORMULACIÓN!V11:W11),IF(FORMULACIÓN!$T11=Lists!$S$4,AVERAGE(FORMULACIÓN!V11:W11),IF(FORMULACIÓN!$T11=Lists!$S$5,OFFSET(U11,0,COUNTA(V11:W11)),IF(FORMULACIÓN!$T11=Lists!$S$6,AVERAGE(V11:W11),""))))),"") -> 485 | Y11: =IF($R11=Lists!$R$3,TEXT(FORMULACIÓN!X11,"00,00%"),IF(FORMULACIÓN!X11=0,0,TEXT(FORMULACIÓN!X11,"##.###"))) -> 485
A12: =IF(C12<>"",+A11+1,"") -> 3 | B12: 2026 | C12: L1 - Formación Académica Integral | D12: =IFERROR(VLOOKUP(FORMULACIÓN!C12,Lists!$A$2:$B$6,2,FALSE),"") -> Garantizar la formación en educación superior de manera integral e inclusiva, con calidad, pertinencia, flexibilidad, interdisciplinariedad, competencias digitales, internacionalización, multilingüismo e interculturalidad, mediante procesos de autorregulación sostenible y con perspectiva regional. | E12: 4. Asegurar la sostenibilidad de la Política de Enseñanza, Aprendizaje y Evaluación de Lenguas Extranjeras de la Universidad del Atlántico. | F12: M1 - Internacionalización y multilingüismo. | G12: Garantizar la Política de Enseñanza aprendizaje y evaluación de Lenguas Extranjeras para que mínimo 5.324 estudiantes logren culminar los cursos de inglés establecidos, asimismo que 199 estudiantes de Licenciatura en Lenguas Extranjeras se formen mediante el Programa de Inmersión en inglés | H12: P1 - Multilingüismo e interculturalidad | I12: 0.09 | J12: Promover la formación en inglés en nuestros estudiantes | K12: 0.333 | L12: Jefe de Oficina de Relaciones Interinstitucionales e Internacionales | M12: PDI | O12: Estudiantes formados mediante la Política de Enseñanza aprendizaje y evaluación de Lenguas Extranjeras | P12: N° de estudiantes formados mediante el Programa de Inmersión en inglés para Estudiantes de Licenciatura en Lenguas Extranjeras | Q12: Anual | R12: Unidad | T12: Nuevo gestionado durante la vigencia | U12: 100 | V12: 0 | W12: 20 | X12: =IFERROR(IF($T12=Lists!$S$2,SUM(FORMULACIÓN!U12:W12),IF(FORMULACIÓN!$T12=Lists!$S$3,SUM(FORMULACIÓN!V12:W12),IF(FORMULACIÓN!$T12=Lists!$S$4,AVERAGE(FORMULACIÓN!V12:W12),IF(FORMULACIÓN!$T12=Lists!$S$5,OFFSET(U12,0,COUNTA(V12:W12)),IF(FORMULACIÓN!$T12=Lists!$S$6,AVERAGE(V12:W12),""))))),"") -> 20 | Y12: =IF($R12=Lists!$R$3,TEXT(FORMULACIÓN!X12,"00,00%"),IF(FORMULACIÓN!X12=0,0,TEXT(FORMULACIÓN!X12,"##.###"))) -> 20
A13: =IF(C13<>"",+A12+1,"") -> 4 | B13: 2026 | C13: L1 - Formación Académica Integral | D13: =IFERROR(VLOOKUP(FORMULACIÓN!C13,Lists!$A$2:$B$6,2,FALSE),"") -> Garantizar la formación en educación superior de manera integral e inclusiva, con calidad, pertinencia, flexibilidad, interdisciplinariedad, competencias digitales, internacionalización, multilingüismo e interculturalidad, mediante procesos de autorregulación sostenible y con perspectiva regional. | E13: 3. Fortalecer los procesos de internacionalización, movilidad, multilingüismo e interculturalidad que visibilicen la Universidad a nivel nacional e internacional, y alcanzar un posicionamiento académico. | F13: M1 - Internacionalización y multilingüismo. | G13: Propender por la movilidad de al menos 17.000 estudiantes desde y hacia la Universidad del Atlántico | H13: P2 - Movilidad académica estudiantil y docente | I13: 0.12 | J13: Impulsar la movilidad estudiantil a nivel nacional | K13: 0.15 | L13: Jefe de Oficina de Relaciones Interinstitucionales e Internacionales | M13: PDI | O13: Movilidad estudiantil nacional entrante | P13: N° de estudiantes nacionales entrantes a la Universidad del Atlántico, desde las funciones sustantivas docencia, extensión, proyección social, Bienestar Universitario e Internacionalización | Q13: Anual | R13: Unidad | T13: Nuevo gestionado durante la vigencia | U13: 850 | V13: 0 | W13: 300 | X13: =IFERROR(IF($T13=Lists!$S$2,SUM(FORMULACIÓN!U13:W13),IF(FORMULACIÓN!$T13=Lists!$S$3,SUM(FORMULACIÓN!V13:W13),IF(FORMULACIÓN!$T13=Lists!$S$4,AVERAGE(FORMULACIÓN!V13:W13),IF(FORMULACIÓN!$T13=Lists!$S$5,OFFSET(U13,0,COUNTA(V13:W13)),IF(FORMULACIÓN!$T13=Lists!$S$6,AVERAGE(V13:W13),""))))),"") -> 300 | Y13: =IF($R13=Lists!$R$3,TEXT(FORMULACIÓN!X13,"00,00%"),IF(FORMULACIÓN!X13=0,0,TEXT(FORMULACIÓN!X13,"##.###"))) -> 300
A14: =IF(C14<>"",+A13+1,"") -> 5 | B14: 2026 | C14: L1 - Formación Académica Integral | D14: =IFERROR(VLOOKUP(FORMULACIÓN!C14,Lists!$A$2:$B$6,2,FALSE),"") -> Garantizar la formación en educación superior de manera integral e inclusiva, con calidad, pertinencia, flexibilidad, interdisciplinariedad, competencias digitales, internacionalización, multilingüismo e interculturalidad, mediante procesos de autorregulación sostenible y con perspectiva regional. | E14: 3. Fortalecer los procesos de internacionalización, movilidad, multilingüismo e interculturalidad que visibilicen la Universidad a nivel nacional e internacional, y alcanzar un posicionamiento académico. | F14: M1 - Internacionalización y multilingüismo. | G14: Propender por la movilidad de al menos 17.000 estudiantes desde y hacia la Universidad del Atlántico | H14: P2 - Movilidad académica estudiantil y docente | I14: 0.12 | J14: Impulsar la movilidad estudiantil a nivel nacional | K14: 0.15 | L14: Jefe de Oficina de Relaciones Interinstitucionales e Internacionales | M14: PDI | O14: Movilidad estudiantil nacional saliente | P14: N° de estudiantes de la Universidad del Atlántico que realizaron movilidad saliente nacional, desde las funciones sustantivas docencia, extensión, proyección social, bienestar universitario e internacionalización | Q14: Anual | R14: Unidad | T14: Nuevo gestionado durante la vigencia | U14: 6961 | V14: 0 | W14: 1300 | X14: =IFERROR(IF($T14=Lists!$S$2,SUM(FORMULACIÓN!U14:W14),IF(FORMULACIÓN!$T14=Lists!$S$3,SUM(FORMULACIÓN!V14:W14),IF(FORMULACIÓN!$T14=Lists!$S$4,AVERAGE(FORMULACIÓN!V14:W14),IF(FORMULACIÓN!$T14=Lists!$S$5,OFFSET(U14,0,COUNTA(V14:W14)),IF(FORMULACIÓN!$T14=Lists!$S$6,AVERAGE(V14:W14),""))))),"") -> 1300 | Y14: =IF($R14=Lists!$R$3,TEXT(FORMULACIÓN!X14,"00,00%"),IF(FORMULACIÓN!X14=0,0,TEXT(FORMULACIÓN!X14,"##.###"))) -> 1.300
A15: =IF(C15<>"",+A14+1,"") -> 6 | B15: 2026 | C15: L1 - Formación Académica Integral | D15: =IFERROR(VLOOKUP(FORMULACIÓN!C15,Lists!$A$2:$B$6,2,FALSE),"") -> Garantizar la formación en educación superior de manera integral e inclusiva, con calidad, pertinencia, flexibilidad, interdisciplinariedad, competencias digitales, internacionalización, multilingüismo e interculturalidad, mediante procesos de autorregulación sostenible y con perspectiva regional. | E15: 3. Fortalecer los procesos de internacionalización, movilidad, multilingüismo e interculturalidad que visibilicen la Universidad a nivel nacional e internacional, y alcanzar un posicionamiento académico. | F15: M1 - Internacionalización y multilingüismo. | G15: Propender por la movilidad de al menos 17.000 estudiantes desde y hacia la Universidad del Atlántico | H15: P2 - Movilidad académica estudiantil y docente | I15: 0.12 | J15: Impulsar la movilidad estudiantil a nivel internacional | K15: 0.15 | L15: Jefe de Oficina de Relaciones Interinstitucionales e Internacionales | M15: PDI | O15: Movilidad estudiantil internacional entrante | P15: N° de estudiantes extranjeros que realizaron movilidad a la Universidad del Atlántico | Q15: Anual | R15: Unidad | T15: Nuevo gestionado durante la vigencia | U15: 110 | V15: 0 | W15: 20 | X15: =IFERROR(IF($T15=Lists!$S$2,SUM(FORMULACIÓN!U15:W15),IF(FORMULACIÓN!$T15=Lists!$S$3,SUM(FORMULACIÓN!V15:W15),IF(FORMULACIÓN!$T15=Lists!$S$4,AVERAGE(FORMULACIÓN!V15:W15),IF(FORMULACIÓN!$T15=Lists!$S$5,OFFSET(U15,0,COUNTA(V15:W15)),IF(FORMULACIÓN!$T15=Lists!$S$6,AVERAGE(V15:W15),""))))),"") -> 20 | Y15: =IF($R15=Lists!$R$3,TEXT(FORMULACIÓN!X15,"00,00%"),IF(FORMULACIÓN!X15=0,0,TEXT(FORMULACIÓN!X15,"##.###"))) -> 20
A16: =IF(C16<>"",+A15+1,"") -> 7 | B16: 2026 | C16: L1 - Formación Académica Integral | D16: =IFERROR(VLOOKUP(FORMULACIÓN!C16,Lists!$A$2:$B$6,2,FALSE),"") -> Garantizar la formación en educación superior de manera integral e inclusiva, con calidad, pertinencia, flexibilidad, interdisciplinariedad, competencias digitales, internacionalización, multilingüismo e interculturalidad, mediante procesos de autorregulación sostenible y con perspectiva regional. | E16: 3. Fortalecer los procesos de internacionalización, movilidad, multilingüismo e interculturalidad que visibilicen la Universidad a nivel nacional e internacional, y alcanzar un posicionamiento académico. | F16: M1 - Internacionalización y multilingüismo. | G16: Propender por la movilidad de al menos 17.000 estudiantes desde y hacia la Universidad del Atlántico | H16: P2 - Movilidad académica estudiantil y docente | I16: 0.12 | J16: Impulsar la movilidad estudiantil a nivel internacional | K16: 0.15 | L16: Jefe de Oficina de Relaciones Interinstitucionales e Internacionales | M16: PDI | O16: Movilidad estudiantil internacional saliente | P16: N° de estudiantes de la Universidad del Atlántico que realizaron movilidad saliente internacional, desde las funciones sustantivas docencia, extensión, proyección social, bienestar universitario e internacionalización | Q16: Anual | R16: Unidad | T16: Nuevo gestionado durante la vigencia | U16: 235 | V16: 0 | W16: 60 | X16: =IFERROR(IF($T16=Lists!$S$2,SUM(FORMULACIÓN!U16:W16),IF(FORMULACIÓN!$T16=Lists!$S$3,SUM(FORMULACIÓN!V16:W16),IF(FORMULACIÓN!$T16=Lists!$S$4,AVERAGE(FORMULACIÓN!V16:W16),IF(FORMULACIÓN!$T16=Lists!$S$5,OFFSET(U16,0,COUNTA(V16:W16)),IF(FORMULACIÓN!$T16=Lists!$S$6,AVERAGE(V16:W16),""))))),"") -> 60 | Y16: =IF($R16=Lists!$R$3,TEXT(FORMULACIÓN!X16,"00,00%"),IF(FORMULACIÓN!X16=0,0,TEXT(FORMULACIÓN!X16,"##.###"))) -> 60
A17: =IF(C17<>"",+A16+1,"") -> 8 | B17: 2026 | C17: L1 - Formación Académica Integral | D17: =IFERROR(VLOOKUP(FORMULACIÓN!C17,Lists!$A$2:$B$6,2,FALSE),"") -> Garantizar la formación en educación superior de manera integral e inclusiva, con calidad, pertinencia, flexibilidad, interdisciplinariedad, competencias digitales, internacionalización, multilingüismo e interculturalidad, mediante procesos de autorregulación sostenible y con perspectiva regional. | E17: 3. Fortalecer los procesos de internacionalización, movilidad, multilingüismo e interculturalidad que visibilicen la Universidad a nivel nacional e internacional, y alcanzar un posicionamiento académico. | F17: M1 - Internacionalización y multilingüismo. | G17: Fortalecer la movilidad docente, desde las funciones sustantivas de docencia, extensión, proyección social e internacionalización, con un mínimo de 330 registros de movilidad saliente internacional y 660 de movilidad saliente nacional | H17: P2 - Movilidad académica estudiantil y docente | I17: 0.12 | J17: Promover la movilidad docente, desde las funciones sustantivas docencia, extensión, proyección social e internacionalización | K17: 0.15 | L17: Jefe de Oficina de Relaciones Interinstitucionales e Internacionales | M17: PDI | O17: Movilidad docente internacional saliente, desde las funciones sustantivas docencia, extensión, proyección social e internacionalización | P17: N° de docentes que realizaron movilidad saliente internacional, desde las funciones sustantivas docencia, extensión, proyección social e internacionalización | Q17: Anual | R17: Unidad | T17: Nuevo gestionado durante la vigencia | U17: 149 | V17: 0 | W17: 34 | X17: =IFERROR(IF($T17=Lists!$S$2,SUM(FORMULACIÓN!U17:W17),IF(FORMULACIÓN!$T17=Lists!$S$3,SUM(FORMULACIÓN!V17:W17),IF(FORMULACIÓN!$T17=Lists!$S$4,AVERAGE(FORMULACIÓN!V17:W17),IF(FORMULACIÓN!$T17=Lists!$S$5,OFFSET(U17,0,COUNTA(V17:W17)),IF(FORMULACIÓN!$T17=Lists!$S$6,AVERAGE(V17:W17),""))))),"") -> 34 | Y17: =IF($R17=Lists!$R$3,TEXT(FORMULACIÓN!X17,"00,00%"),IF(FORMULACIÓN!X17=0,0,TEXT(FORMULACIÓN!X17,"##.###"))) -> 34
A18: =IF(C18<>"",+A17+1,"") -> 9 | B18: 2026 | C18: L1 - Formación Académica Integral | D18: =IFERROR(VLOOKUP(FORMULACIÓN!C18,Lists!$A$2:$B$6,2,FALSE),"") -> Garantizar la formación en educación superior de manera integral e inclusiva, con calidad, pertinencia, flexibilidad, interdisciplinariedad, competencias digitales, internacionalización, multilingüismo e interculturalidad, mediante procesos de autorregulación sostenible y con perspectiva regional. | E18: 3. Fortalecer los procesos de internacionalización, movilidad, multilingüismo e interculturalidad que visibilicen la Universidad a nivel nacional e internacional, y alcanzar un posicionamiento académico. | F18: M1 - Internacionalización y multilingüismo. | G18: Fortalecer la movilidad docente, desde las funciones sustantivas de docencia, extensión, proyección social e internacionalización, con un mínimo de 330 registros de movilidad saliente internacional y 660 de movilidad saliente nacional | H18: P2 - Movilidad académica estudiantil y docente | I18: 0.12 | J18: Promover la movilidad docente, desde las funciones sustantivas docencia, extensión, proyección social e internacionalización | K18: 0.15 | L18: Jefe de Oficina de Relaciones Interinstitucionales e Internacionales | M18: PDI | O18: Movilidad docente nacional saliente, desde las funciones sustantivas docencia, extensión, proyección social e internacionalización | P18: N° de docentes de la Universidad del Atlántico que realizaron movilidad saliente nacional, desde las funciones sustantivas docencia, extensión, proyección social e internacionalización | Q18: Anual | R18: Unidad | T18: Nuevo gestionado durante la vigencia | U18: 316 | V18: 0 | W18: 67 | X18: =IFERROR(IF($T18=Lists!$S$2,SUM(FORMULACIÓN!U18:W18),IF(FORMULACIÓN!$T18=Lists!$S$3,SUM(FORMULACIÓN!V18:W18),IF(FORMULACIÓN!$T18=Lists!$S$4,AVERAGE(FORMULACIÓN!V18:W18),IF(FORMULACIÓN!$T18=Lists!$S$5,OFFSET(U18,0,COUNTA(V18:W18)),IF(FORMULACIÓN!$T18=Lists!$S$6,AVERAGE(V18:W18),""))))),"") -> 67 | Y18: =IF($R18=Lists!$R$3,TEXT(FORMULACIÓN!X18,"00,00%"),IF(FORMULACIÓN!X18=0,0,TEXT(FORMULACIÓN!X18,"##.###"))) -> 67
A19: =IF(C19<>"",+A18+1,"") -> 10 | B19: 2026 | C19: L1 - Formación Académica Integral | D19: =IFERROR(VLOOKUP(FORMULACIÓN!C19,Lists!$A$2:$B$6,2,FALSE),"") -> Garantizar la formación en educación superior de manera integral e inclusiva, con calidad, pertinencia, flexibilidad, interdisciplinariedad, competencias digitales, internacionalización, multilingüismo e interculturalidad, mediante procesos de autorregulación sostenible y con perspectiva regional. | E19: 3. Fortalecer los procesos de internacionalización, movilidad, multilingüismo e interculturalidad que visibilicen la Universidad a nivel nacional e internacional, y alcanzar un posicionamiento académico. | F19: M1 - Internacionalización y multilingüismo. | G19: Fortalecer la movilidad docente entrante internacional, desde las funciones sustantivas de docencia, extensión, proyección social e internacionalización | H19: P2 - Movilidad académica estudiantil y docente | I19: 0.12 | J19: Promover la movilidad docente, desde las funciones sustantivas docencia, extensión, proyección social e internacionalización | K19: 0.1 | L19: Jefe de Oficina de Relaciones Interinstitucionales e Internacionales | M19: PA | O19: Movilidad docente internacional entrante, desde las funciones sustantivas docencia, extensión, proyección social e internacionalización | P19: N° de docentes que realizaron movilidad entrante internacional, desde las funciones sustantivas docencia, extensión, proyección social e internacionalización | Q19: Anual | R19: Unidad | T19: Nuevo gestionado durante la vigencia | U19: 253 | V19: 0 | W19: 30 | X19: =IFERROR(IF($T19=Lists!$S$2,SUM(FORMULACIÓN!U19:W19),IF(FORMULACIÓN!$T19=Lists!$S$3,SUM(FORMULACIÓN!V19:W19),IF(FORMULACIÓN!$T19=Lists!$S$4,AVERAGE(FORMULACIÓN!V19:W19),IF(FORMULACIÓN!$T19=Lists!$S$5,OFFSET(U19,0,COUNTA(V19:W19)),IF(FORMULACIÓN!$T19=Lists!$S$6,AVERAGE(V19:W19),""))))),"") -> 30 | Y19: =IF($R19=Lists!$R$3,TEXT(FORMULACIÓN!X19,"00,00%"),IF(FORMULACIÓN!X19=0,0,TEXT(FORMULACIÓN!X19,"##.###"))) -> 30
A20: =IF(C20<>"",+A19+1,"") -> 11 | B20: 2026 | C20: L1 - Formación Académica Integral | D20: =IFERROR(VLOOKUP(FORMULACIÓN!C20,Lists!$A$2:$B$6,2,FALSE),"") -> Garantizar la formación en educación superior de manera integral e inclusiva, con calidad, pertinencia, flexibilidad, interdisciplinariedad, competencias digitales, internacionalización, multilingüismo e interculturalidad, mediante procesos de autorregulación sostenible y con perspectiva regional. | E20: 8. Implementar didácticas fortalecidas por las TIC que fomenten las competencias globales, interculturales y disciplinares de docentes y estudiantes a través de metodologías innovadoras, en el marco del proyecto de internacionalización en casa y curricular | F20: M1 - Internacionalización y multilingüismo. | G20: Propender para que el 60% de los programas desarrollen actividades con componente internacional desde el aula y de manera extracurricular. | H20: P3 - Internacionalización en casa y curricular | I20: 0.06 | J20: Impulsar el desarrollo de actividades académicas con componente internacional | K20: 0.35 | L20: Jefe de Oficina de Relaciones Interinstitucionales e Internacionales | M20: PDI | O20: Porcentaje de programas académicos que desarrollan actividades con componente internacional en el aula (clases espejo, proyectos de aprendizaje colaborativo, actividades con comunidades académicas homólogas; entre otros) y extracurricular (seminarios, talleres, ferias, encuentros; entre otros). | P20: N° de programas académicos que desarrollan actividades con componente internacional en el aula de clases l / total de programas académicos *100 (clases espejo, proyectos de aprendizaje colaborativo, actividades con comunidades académicas homólogas; entre otros) | Q20: Anual | R20: Porcentaje | S20: Programas de pregrado | T20: Último valor reportado | U20: 0.24 | V20: 0 | W20: 0.34 | X20: =IFERROR(IF($T20=Lists!$S$2,SUM(FORMULACIÓN!U20:W20),IF(FORMULACIÓN!$T20=Lists!$S$3,SUM(FORMULACIÓN!V20:W20),IF(FORMULACIÓN!$T20=Lists!$S$4,AVERAGE(FORMULACIÓN!V20:W20),IF(FORMULACIÓN!$T20=Lists!$S$5,OFFSET(U20,0,COUNTA(V20:W20)),IF(FORMULACIÓN!$T20=Lists!$S$6,AVERAGE(V20:W20),""))))),"") -> 0.34 | Y20: =IF($R20=Lists!$R$3,TEXT(FORMULACIÓN!X20,"00,00%"),IF(FORMULACIÓN!X20=0,0,TEXT(FORMULACIÓN!X20,"##.###"))) -> 34,00%
A21: =IF(C21<>"",+A20+1,"") -> 12 | B21: 2026 | C21: L1 - Formación Académica Integral | D21: =IFERROR(VLOOKUP(FORMULACIÓN!C21,Lists!$A$2:$B$6,2,FALSE),"") -> Garantizar la formación en educación superior de manera integral e inclusiva, con calidad, pertinencia, flexibilidad, interdisciplinariedad, competencias digitales, internacionalización, multilingüismo e interculturalidad, mediante procesos de autorregulación sostenible y con perspectiva regional. | E21: 8. Implementar didácticas fortalecidas por las TIC que fomenten las competencias globales, interculturales y disciplinares de docentes y estudiantes a través de metodologías innovadoras, en el marco del proyecto de internacionalización en casa y curricular | F21: M1 - Internacionalización y multilingüismo. | G21: Propender para que el 60% de los programas desarrollen actividades con componente internacional desde el aula y de manera extracurricular. | H21: P3 - Internacionalización en casa y curricular | I21: 0.06 | J21: Impulsar el desarrollo de actividades académicas con componente internacional | K21: 0.35 | L21: Jefe de Oficina de Relaciones Interinstitucionales e Internacionales | M21: PDI | O21: Porcentaje de programas académicos que desarrollan actividades con componente internacional en el aula (clases espejo, proyectos de aprendizaje colaborativo, actividades con comunidades académicas homólogas; entre otros) y extracurricular (seminarios, talleres, ferias, encuentros; entre otros). | P21: N° de programas académicos que desarrollan actividades extracurriculares con componente internacional / total de programas académicos *100 (seminarios, talleres, ferias, encuentros; entre otros). | Q21: Anual | R21: Porcentaje | T21: Último valor reportado | U21: 0.46 | V21: 0 | W21: 0.13 | X21: =IFERROR(IF($T21=Lists!$S$2,SUM(FORMULACIÓN!U21:W21),IF(FORMULACIÓN!$T21=Lists!$S$3,SUM(FORMULACIÓN!V21:W21),IF(FORMULACIÓN!$T21=Lists!$S$4,AVERAGE(FORMULACIÓN!V21:W21),IF(FORMULACIÓN!$T21=Lists!$S$5,OFFSET(U21,0,COUNTA(V21:W21)),IF(FORMULACIÓN!$T21=Lists!$S$6,AVERAGE(V21:W21),""))))),"") -> 0.13 | Y21: =IF($R21=Lists!$R$3,TEXT(FORMULACIÓN!X21,"00,00%"),IF(FORMULACIÓN!X21=0,0,TEXT(FORMULACIÓN!X21,"##.###"))) -> 13,00%
A22: =IF(C22<>"",+A21+1,"") -> 13 | B22: 2026 | C22: L1 - Formación Académica Integral | D22: =IFERROR(VLOOKUP(FORMULACIÓN!C22,Lists!$A$2:$B$6,2,FALSE),"") -> Garantizar la formación en educación superior de manera integral e inclusiva, con calidad, pertinencia, flexibilidad, interdisciplinariedad, competencias digitales, internacionalización, multilingüismo e interculturalidad, mediante procesos de autorregulación sostenible y con perspectiva regional. | E22: 8. Implementar didácticas fortalecidas por las TIC que fomenten las competencias globales, interculturales y disciplinares de docentes y estudiantes a través de metodologías innovadoras, en el marco del proyecto de internacionalización en casa y curricular | F22: M1 - Internacionalización y multilingüismo. | G22: Propender para que el 60% de los programas desarrollen actividades con componente internacional desde el aula y de manera extracurricular. | H22: P3 - Internacionalización en casa y curricular | I22: 0.06 | J22: Impulsar el desarrollo de actividades académicas con componente internacional | K22: 0.3 | L22: Jefe de Oficina de Relaciones Interinstitucionales e Internacionales | M22: PDI-PA | N22: X | O22: Actividades extracurriculares con componente internacional realizadas por Facultad (seminarios, talleres, ferias, encuentros, foros, congresos, concursos; entre otros) | P22: N° de actividades extracurriculares con componente internacional realizadas por facultad (seminarios, talleres, ferias, encuentros, foros, congresos, concursos; entre otros) | Q22: Anual | R22: Unidad | S22: Arquitectura 6 Bellas Artes 3 Economicas 8 básicas 7 Humanas 7 C. de la Salud 4 Farmacia 3 Jurídica 5 Educación 10 Ingenieiría 3 | T22: Nuevo gestionado durante la vigencia | U22: 58 | V22: 0 | W22: 56 | X22: =IFERROR(IF($T22=Lists!$S$2,SUM(FORMULACIÓN!U22:W22),IF(FORMULACIÓN!$T22=Lists!$S$3,SUM(FORMULACIÓN!V22:W22),IF(FORMULACIÓN!$T22=Lists!$S$4,AVERAGE(FORMULACIÓN!V22:W22),IF(FORMULACIÓN!$T22=Lists!$S$5,OFFSET(U22,0,COUNTA(V22:W22)),IF(FORMULACIÓN!$T22=Lists!$S$6,AVERAGE(V22:W22),""))))),"") -> 56 | Y22: =IF($R22=Lists!$R$3,TEXT(FORMULACIÓN!X22,"00,00%"),IF(FORMULACIÓN!X22=0,0,TEXT(FORMULACIÓN!X22,"##.###"))) -> 56
A23: =IF(C23<>"",+A22+1,"") -> 14 | B23: 2026 | C23: L1 - Formación Académica Integral | D23: =IFERROR(VLOOKUP(FORMULACIÓN!C23,Lists!$A$2:$B$6,2,FALSE),"") -> Garantizar la formación en educación superior de manera integral e inclusiva, con calidad, pertinencia, flexibilidad, interdisciplinariedad, competencias digitales, internacionalización, multilingüismo e interculturalidad, mediante procesos de autorregulación sostenible y con perspectiva regional. | E23: 5. Fortalecer Políticas curriculares con pedagogías adecuadas que atiendan al principio de calidad académica con enfoque inclusivo a través del desarrollo de las disciplinas y las profesiones, la integración de saberes, el fortalecimiento de competencias digitales, la solución de problemas y la inserción de los egresados al mercado laboral. | F23: M2 - Transformación digital | G23: Implementar la Política de uso y apropiación de las TIC en la Universidad del Atlántico | H23: P1 - Competencias digitales | I23: 0.05 | J23: Implementar la Política de uso y apropiación de las TIC | K23: 0.3 | L23: Jefe del Departamento de Educación Virtual, Medios Educativos y Audiovisuales | M23: PDI | O23: Diseño e implementación de la Política de uso y apropiación de las TIC en la Universidad del Atlántico | P23: N° de lineamientos implementados de la Política / total de lineamientos de la Política de uso y apropiación de las TIC en la Universidad del Atlántico * 100 | Q23: Anual | R23: Porcentaje | S23: La venta de servicio por extensión - modalidad virtual Crear una red de investigadores de usos pe´dagogico de TIC De los 13 . 11 serán implementados | T23: Último valor reportado | U23: 0.77 | V23: 0 | W23: 0.8 | X23: =IFERROR(IF($T23=Lists!$S$2,SUM(FORMULACIÓN!U23:W23),IF(FORMULACIÓN!$T23=Lists!$S$3,SUM(FORMULACIÓN!V23:W23),IF(FORMULACIÓN!$T23=Lists!$S$4,AVERAGE(FORMULACIÓN!V23:W23),IF(FORMULACIÓN!$T23=Lists!$S$5,OFFSET(U23,0,COUNTA(V23:W23)),IF(FORMULACIÓN!$T23=Lists!$S$6,AVERAGE(V23:W23),""))))),"") -> 0.8 | Y23: =IF($R23=Lists!$R$3,TEXT(FORMULACIÓN!X23,"00,00%"),IF(FORMULACIÓN!X23=0,0,TEXT(FORMULACIÓN!X23,"##.###"))) -> 80,00%
A24: =IF(C24<>"",+A23+1,"") -> 15 | B24: 2026 | C24: L1 - Formación Académica Integral | D24: =IFERROR(VLOOKUP(FORMULACIÓN!C24,Lists!$A$2:$B$6,2,FALSE),"") -> Garantizar la formación en educación superior de manera integral e inclusiva, con calidad, pertinencia, flexibilidad, interdisciplinariedad, competencias digitales, internacionalización, multilingüismo e interculturalidad, mediante procesos de autorregulación sostenible y con perspectiva regional. | E24: 5. Fortalecer Políticas curriculares con pedagogías adecuadas que atiendan al principio de calidad académica con enfoque inclusivo a través del desarrollo de las disciplinas y las profesiones, la integración de saberes, el fortalecimiento de competencias digitales, la solución de problemas y la inserción de los egresados al mercado laboral. | F24: M2 - Transformación digital | G24: Lograr que al menos el 50% de los programas académicos apliquen prácticas de innovación educativa, y crear al menos 800 recursos digitales para la docencia con impacto positivo en la población y 20 herramientas digitales educativas habilitados por la UA (Ejemplos: aplica aprendizaje inverso, automatización de las prácticas de laboratorio, simuladores, plataformas, construcción de ebook) | H24: P1 - Competencias digitales | I24: 0.05 | J24: Fomentar las prácticas de innovación educativa mediadas por las TIC | K24: 0.35 | L24: Jefe del Departamento de Educación Virtual, Medios Educativos y Audiovisuales | M24: PDI - PA | N24: X | O24: N° de prácticas de innovación educativa con TIC por programa académico | P24: N° de prácticas de innovación educativa con TIC desarrolladas con Facultad | Q24: Anual | R24: Unidad | S24: Diagnostico de los estados de continuidad de las experiencias identificadas identificación de experiencias que requieran apoyo para investigación y continuidad Procurar que los programas técnicos de la Facultades se incluyan y adémas 9 programas que no han realizado experiencias Arquitectura 2 Bellas Artes 2 Economicas 1 básicas 2 Humanas 2 C. de la Salud 3 Farmacia 2 Jurídica 2 Educación 4 Ingenieiría 2 | T24: Nuevo gestionado durante la vigencia | U24: 41 | V24: 0 | W24: 25 | X24: =IFERROR(IF($T24=Lists!$S$2,SUM(FORMULACIÓN!U24:W24),IF(FORMULACIÓN!$T24=Lists!$S$3,SUM(FORMULACIÓN!V24:W24),IF(FORMULACIÓN!$T24=Lists!$S$4,AVERAGE(FORMULACIÓN!V24:W24),IF(FORMULACIÓN!$T24=Lists!$S$5,OFFSET(U24,0,COUNTA(V24:W24)),IF(FORMULACIÓN!$T24=Lists!$S$6,AVERAGE(V24:W24),""))))),"") -> 25 | Y24: =IF($R24=Lists!$R$3,TEXT(FORMULACIÓN!X24,"00,00%"),IF(FORMULACIÓN!X24=0,0,TEXT(FORMULACIÓN!X24,"##.###"))) -> 25
A25: =IF(C25<>"",+A24+1,"") -> 16 | B25: 2026 | C25: L1 - Formación Académica Integral | D25: =IFERROR(VLOOKUP(FORMULACIÓN!C25,Lists!$A$2:$B$6,2,FALSE),"") -> Garantizar la formación en educación superior de manera integral e inclusiva, con calidad, pertinencia, flexibilidad, interdisciplinariedad, competencias digitales, internacionalización, multilingüismo e interculturalidad, mediante procesos de autorregulación sostenible y con perspectiva regional. | E25: 5. Fortalecer Políticas curriculares con pedagogías adecuadas que atiendan al principio de calidad académica con enfoque inclusivo a través del desarrollo de las disciplinas y las profesiones, la integración de saberes, el fortalecimiento de competencias digitales, la solución de problemas y la inserción de los egresados al mercado laboral. | F25: M2 - Transformación digital | G25: Lograr que al menos el 50% de los programas académicos apliquen prácticas de innovación educativa, y crear al menos 800 recursos digitales para la docencia con impacto positivo en la población y 20 herramientas digitales educativas habilitados por la UA (Ejemplos: aplica aprendizaje inverso, automatización de las prácticas de laboratorio, simuladores, plataformas, construcción de ebook) | H25: P1 - Competencias digitales | I25: 0.05 | J25: Fomentar las prácticas de innovación educativa mediadas por las TIC | K25: 0.35 | L25: Jefe del Departamento de Educación Virtual, Medios Educativos y Audiovisuales | M25: PDI | O25: N° de prácticas de innovación educativa con TIC por programa académico | P25: N° de programas académicos que ha implementado prácticas de innovación educativa mediadas por TIC / total de programas académicos * 100 | Q25: Anual | R25: Porcentaje | S25: Tres nuevos programas que nunca han realizado experiencias de innovación, respectos a los 100 prohgramas que tiene la Universidad | T25: Último valor reportado | U25: 0.32 | V25: 0 | W25: 0.35 | X25: =IFERROR(IF($T25=Lists!$S$2,SUM(FORMULACIÓN!U25:W25),IF(FORMULACIÓN!$T25=Lists!$S$3,SUM(FORMULACIÓN!V25:W25),IF(FORMULACIÓN!$T25=Lists!$S$4,AVERAGE(FORMULACIÓN!V25:W25),IF(FORMULACIÓN!$T25=Lists!$S$5,OFFSET(U25,0,COUNTA(V25:W25)),IF(FORMULACIÓN!$T25=Lists!$S$6,AVERAGE(V25:W25),""))))),"") -> 0.35 | Y25: =IF($R25=Lists!$R$3,TEXT(FORMULACIÓN!X25,"00,00%"),IF(FORMULACIÓN!X25=0,0,TEXT(FORMULACIÓN!X25,"##.###"))) -> 35,00%
A26: =IF(C26<>"",+A25+1,"") -> 17 | B26: 2026 | C26: L1 - Formación Académica Integral | D26: =IFERROR(VLOOKUP(FORMULACIÓN!C26,Lists!$A$2:$B$6,2,FALSE),"") -> Garantizar la formación en educación superior de manera integral e inclusiva, con calidad, pertinencia, flexibilidad, interdisciplinariedad, competencias digitales, internacionalización, multilingüismo e interculturalidad, mediante procesos de autorregulación sostenible y con perspectiva regional. | E26: 9. Fomentar el uso y apropiación de las tecnologías de información y comunicación (TIC) integrada a los procesos misionales, fortaleciendo las competencias digitales de la comunidad universitaria, la oferta académica de excelencia, la innovación pedagógica y la interacción con diferentes actores a nivel global, nacional y local. | F26: M2 - Transformación digital | G26: Lograr que al menos el 50% de los programas académicos apliquen prácticas de innovación educativa, y crear al menos 800 recursos digitales para la docencia con impacto positivo en la población y 20 herramientas digitales educativas habilitados por la UA (Ejemplos: aplica aprendizaje inverso, automatización de las prácticas de laboratorio, simuladores, plataformas, construcción de ebook) | H26: P2 - Fortalecimiento de recursos digitales para la docencia | I26: 0.05 | J26: Fomentar las prácticas de innovación educativa mediadas por las TIC | K26: 0.5 | L26: Jefe del Departamento de Educación Virtual, Medios Educativos y Audiovisuales | M26: PDI | O26: Disponibilidad de Recursos digitales para apoyo a la Docencia ( Plataforma que ofrece la UA) | P26: No. De herramientas digitales educativas habilitados por la UA, para el Desarrollo de la Docencia | Q26: Anual | R26: Unidad | S26: Para este año el Dpto debe gestionar una nueva herramienta comprada: plataformas, Software Para el 2022:2 2023:1 2024;2 2025; 1 Total : 6 | T26: Nuevo gestionado durante la vigencia | U26: 6 | V26: 0 | W26: 1 | X26: =IFERROR(IF($T26=Lists!$S$2,SUM(FORMULACIÓN!U26:W26),IF(FORMULACIÓN!$T26=Lists!$S$3,SUM(FORMULACIÓN!V26:W26),IF(FORMULACIÓN!$T26=Lists!$S$4,AVERAGE(FORMULACIÓN!V26:W26),IF(FORMULACIÓN!$T26=Lists!$S$5,OFFSET(U26,0,COUNTA(V26:W26)),IF(FORMULACIÓN!$T26=Lists!$S$6,AVERAGE(V26:W26),""))))),"") -> 1 | Y26: =IF($R26=Lists!$R$3,TEXT(FORMULACIÓN!X26,"00,00%"),IF(FORMULACIÓN!X26=0,0,TEXT(FORMULACIÓN!X26,"##.###"))) -> 1
A27: =IF(C27<>"",+A26+1,"") -> 18 | B27: 2026 | C27: L1 - Formación Académica Integral | D27: =IFERROR(VLOOKUP(FORMULACIÓN!C27,Lists!$A$2:$B$6,2,FALSE),"") -> Garantizar la formación en educación superior de manera integral e inclusiva, con calidad, pertinencia, flexibilidad, interdisciplinariedad, competencias digitales, internacionalización, multilingüismo e interculturalidad, mediante procesos de autorregulación sostenible y con perspectiva regional. | E27: 9. Fomentar el uso y apropiación de las tecnologías de información y comunicación (TIC) integrada a los procesos misionales, fortaleciendo las competencias digitales de la comunidad universitaria, la oferta académica de excelencia, la innovación pedagógica y la interacción con diferentes actores a nivel global, nacional y local. | F27: M2 - Transformación digital | G27: Lograr que al menos el 50% de los programas académicos apliquen prácticas de innovación educativa, y crear al menos 800 recursos digitales para la docencia con impacto positivo en la población y 20 herramientas digitales educativas habilitados por la UA (Ejemplos: aplica aprendizaje inverso, automatización de las prácticas de laboratorio, simuladores, plataformas, construcción de ebook) | H27: P2 - Fortalecimiento de recursos digitales para la docencia | I27: 0.05 | J27: Fomentar las prácticas de innovación educativa mediadas por las TIC | K27: 0.5 | L27: Jefe del Departamento de Educación Virtual, Medios Educativos y Audiovisuales | M27: PDI | O27: Creación de recursos digitales por docentes | P27: N° de recursos digitales creados por los docentes para el desarrollo de la Docencia | Q27: Anual | R27: Unidad | T27: Nuevo gestionado durante la vigencia | U27: 475 | V27: 0 | W27: 100 | X27: =IFERROR(IF($T27=Lists!$S$2,SUM(FORMULACIÓN!U27:W27),IF(FORMULACIÓN!$T27=Lists!$S$3,SUM(FORMULACIÓN!V27:W27),IF(FORMULACIÓN!$T27=Lists!$S$4,AVERAGE(FORMULACIÓN!V27:W27),IF(FORMULACIÓN!$T27=Lists!$S$5,OFFSET(U27,0,COUNTA(V27:W27)),IF(FORMULACIÓN!$T27=Lists!$S$6,AVERAGE(V27:W27),""))))),"") -> 100 | Y27: =IF($R27=Lists!$R$3,TEXT(FORMULACIÓN!X27,"00,00%"),IF(FORMULACIÓN!X27=0,0,TEXT(FORMULACIÓN!X27,"##.###"))) -> 100
A28: =IF(C28<>"",+A27+1,"") -> 19 | B28: 2026 | C28: L1 - Formación Académica Integral | D28: =IFERROR(VLOOKUP(FORMULACIÓN!C28,Lists!$A$2:$B$6,2,FALSE),"") -> Garantizar la formación en educación superior de manera integral e inclusiva, con calidad, pertinencia, flexibilidad, interdisciplinariedad, competencias digitales, internacionalización, multilingüismo e interculturalidad, mediante procesos de autorregulación sostenible y con perspectiva regional. | E28: 6. Integrar los procesos académicos y administrativos que conlleve de manera funcional a un orden adecuado de interacciones, soportadas en tecnologías de la información, de acuerdo a la normatividad vigente. | F28: M2 - Transformación digital | G28: Integrar los procesos académicos y administrativos de manera funcional, garantizando una adecuada articulación de las interacciones institucionales, soportadas en tecnologías de la información y en concordancia con la normatividad vigente. | H28: P3 - Ampliación de la educación digital | I28: 0.04 | J28: Promover la Biblioteca Digital mediante jornadas de sensibilización y capacitación | K28: 0.333 | L28: Jefe del Departamento de Biblioteca | M28: PR | O28: Fortalecimiento del repositorio institucional | P28: N° de trabajos y tesis de grado nuevos disponibles en el repositorio institucional | Q28: Anual | R28: Unidad | T28: Nuevo gestionado durante la vigencia | U28: 340 | V28: 0 | W28: 300 | X28: =IFERROR(IF($T28=Lists!$S$2,SUM(FORMULACIÓN!U28:W28),IF(FORMULACIÓN!$T28=Lists!$S$3,SUM(FORMULACIÓN!V28:W28),IF(FORMULACIÓN!$T28=Lists!$S$4,AVERAGE(FORMULACIÓN!V28:W28),IF(FORMULACIÓN!$T28=Lists!$S$5,OFFSET(U28,0,COUNTA(V28:W28)),IF(FORMULACIÓN!$T28=Lists!$S$6,AVERAGE(V28:W28),""))))),"") -> 300 | Y28: =IF($R28=Lists!$R$3,TEXT(FORMULACIÓN!X28,"00,00%"),IF(FORMULACIÓN!X28=0,0,TEXT(FORMULACIÓN!X28,"##.###"))) -> 300
A29: =IF(C29<>"",+A28+1,"") -> 20 | B29: 2026 | C29: L1 - Formación Académica Integral | D29: =IFERROR(VLOOKUP(FORMULACIÓN!C29,Lists!$A$2:$B$6,2,FALSE),"") -> Garantizar la formación en educación superior de manera integral e inclusiva, con calidad, pertinencia, flexibilidad, interdisciplinariedad, competencias digitales, internacionalización, multilingüismo e interculturalidad, mediante procesos de autorregulación sostenible y con perspectiva regional. | E29: 9. Fomentar el uso y apropiación de las tecnologías de información y comunicación (TIC) integrada a los procesos misionales, fortaleciendo las competencias digitales de la comunidad universitaria, la oferta académica de excelencia, la innovación pedagógica y la interacción con diferentes actores a nivel global, nacional y local. | F29: M2 - Transformación digital | G29: Incluir mínimo 30 cursos en línea masivos y abiertos MOOC, como electivas de contexto con temáticas relacionadas con economía de bienestar, valores ético-morales, emprendimiento social y desarrollo endógeno. | H29: P3 - Ampliación de la educación digital | I29: 0.04 | J29: Diseñar electivas de contexto bajo la modalidad MOOC, con temáticas relacionadas con economía de bienestar, valores ético-morales, emprendimiento social y desarrollo endógeno. | K29: 0.333 | L29: Jefe del Departamento de Educación Virtual, Medios Educativos y Audiovisuales | M29: PDI-PR | N29: X | O29: Electivas de contexto bajo la modalidad MOOC, con temáticas relacionadas con economía de bienestar, valores ético-morales, emprendimiento social y desarrollo endógeno. | P29: N° de electivas de contexto bajo la modalidad MOOC, con temáticas relacionadas con economía de bienestar, valores ético-morales, emprendimiento social y desarrollo endógeno. | Q29: Anual | R29: Unidad | S29: Arquitectura 1 Bellas Artes 1 Economicas 1 básicas 1 Humanas 1 C. de la Salud 1 Farmacia 1 Jurídica 1 Educación 1 Ingenieiría 1 | T29: Nuevo gestionado durante la vigencia | U29: 6 | V29: 0 | W29: 10 | X29: =IFERROR(IF($T29=Lists!$S$2,SUM(FORMULACIÓN!U29:W29),IF(FORMULACIÓN!$T29=Lists!$S$3,SUM(FORMULACIÓN!V29:W29),IF(FORMULACIÓN!$T29=Lists!$S$4,AVERAGE(FORMULACIÓN!V29:W29),IF(FORMULACIÓN!$T29=Lists!$S$5,OFFSET(U29,0,COUNTA(V29:W29)),IF(FORMULACIÓN!$T29=Lists!$S$6,AVERAGE(V29:W29),""))))),"") -> 10 | Y29: =IF($R29=Lists!$R$3,TEXT(FORMULACIÓN!X29,"00,00%"),IF(FORMULACIÓN!X29=0,0,TEXT(FORMULACIÓN!X29,"##.###"))) -> 10
A30: =IF(C30<>"",+A29+1,"") -> 21 | B30: 2026 | C30: L1 - Formación Académica Integral | D30: =IFERROR(VLOOKUP(FORMULACIÓN!C30,Lists!$A$2:$B$6,2,FALSE),"") -> Garantizar la formación en educación superior de manera integral e inclusiva, con calidad, pertinencia, flexibilidad, interdisciplinariedad, competencias digitales, internacionalización, multilingüismo e interculturalidad, mediante procesos de autorregulación sostenible y con perspectiva regional. | E30: 9. Fomentar el uso y apropiación de las tecnologías de información y comunicación (TIC) integrada a los procesos misionales, fortaleciendo las competencias digitales de la comunidad universitaria, la oferta académica de excelencia, la innovación pedagógica y la interacción con diferentes actores a nivel global, nacional y local. | F30: M2 - Transformación digital | G30: Fomentar el uso de recursos digitales en la docencia | H30: P3 - Ampliación de la educación digital | I30: 0.04 | J30: Apoyar a los programas en el diseño de cursos virtuales | K30: 0.333 | L30: Jefe del Departamento de Educación Virtual, Medios Educativos y Audiovisuales | M30: PA | N30: X | O30: Diseño e implementación de cursos virtuales | P30: Número de cursos virtuales implementados para programas de pregrado | Q30: Anual | R30: Unidad | T30: Nuevo gestionado durante la vigencia | U30: 47 | V30: 0 | W30: 30 | X30: =IFERROR(IF($T30=Lists!$S$2,SUM(FORMULACIÓN!U30:W30),IF(FORMULACIÓN!$T30=Lists!$S$3,SUM(FORMULACIÓN!V30:W30),IF(FORMULACIÓN!$T30=Lists!$S$4,AVERAGE(FORMULACIÓN!V30:W30),IF(FORMULACIÓN!$T30=Lists!$S$5,OFFSET(U30,0,COUNTA(V30:W30)),IF(FORMULACIÓN!$T30=Lists!$S$6,AVERAGE(V30:W30),""))))),"") -> 30 | Y30: =IF($R30=Lists!$R$3,TEXT(FORMULACIÓN!X30,"00,00%"),IF(FORMULACIÓN!X30=0,0,TEXT(FORMULACIÓN!X30,"##.###"))) -> 30
A31: =IF(C31<>"",+A30+1,"") -> 22 | B31: 2026 | C31: L1 - Formación Académica Integral | D31: =IFERROR(VLOOKUP(FORMULACIÓN!C31,Lists!$A$2:$B$6,2,FALSE),"") -> Garantizar la formación en educación superior de manera integral e inclusiva, con calidad, pertinencia, flexibilidad, interdisciplinariedad, competencias digitales, internacionalización, multilingüismo e interculturalidad, mediante procesos de autorregulación sostenible y con perspectiva regional. | E31: 11. Desarrollar programas académicos con calidad y pertinencia para contribuir a las necesidades del contexto y la región Caribe. | F31: M3 - Regionalización en contexto | G31: Realizar 2 estudios de pertinencia, para fortalecer la oferta académica pertinente en la región, con 20 programas académicos de pregrado y postgrado, que den respuesta al sector productivo y/u otros actores regionales, incrementando a 1500 los egresados de región y propendiendo que mínimo 350 de ellos desarrollen actividades económicamente productivas, aportando así al desarrollo socioeconómico de la región. | H31: P1 - Programas académicos con calidad y pertinencia regional | I31: 0.08 | J31: Fortalecer la oferta de programas pertinentes para el desarrollo regional. | K31: 0.25 | L31: Vicerrector De Docencia | M31: PDI-PA | N31: X | O31: Programas académicos en pregrado y postgrado diseñados según la pertinencia para la región con apoyo del sector productivo y/o otros actores regionales | P31: Número de programas de pregrado y postgrado académicos radicados ante el ministerios y diseñados a partir de necesidades identificadas con apoyo del sector productivo y/o otros actores regionales | Q31: Anual | R31: Unidad | S31: Facultad de Arquitectura (2) Ciclo profesional de Construcción Profesional Urbanismo | T31: Nuevo gestionado durante la vigencia | U31: 19 | V31: 0 | W31: 2 | X31: =IFERROR(IF($T31=Lists!$S$2,SUM(FORMULACIÓN!U31:W31),IF(FORMULACIÓN!$T31=Lists!$S$3,SUM(FORMULACIÓN!V31:W31),IF(FORMULACIÓN!$T31=Lists!$S$4,AVERAGE(FORMULACIÓN!V31:W31),IF(FORMULACIÓN!$T31=Lists!$S$5,OFFSET(U31,0,COUNTA(V31:W31)),IF(FORMULACIÓN!$T31=Lists!$S$6,AVERAGE(V31:W31),""))))),"") -> 2 | Y31: =IF($R31=Lists!$R$3,TEXT(FORMULACIÓN!X31,"00,00%"),IF(FORMULACIÓN!X31=0,0,TEXT(FORMULACIÓN!X31,"##.###"))) -> 2
A32: =IF(C32<>"",+A31+1,"") -> 23 | B32: 2026 | C32: L1 - Formación Académica Integral | D32: =IFERROR(VLOOKUP(FORMULACIÓN!C32,Lists!$A$2:$B$6,2,FALSE),"") -> Garantizar la formación en educación superior de manera integral e inclusiva, con calidad, pertinencia, flexibilidad, interdisciplinariedad, competencias digitales, internacionalización, multilingüismo e interculturalidad, mediante procesos de autorregulación sostenible y con perspectiva regional. | E32: 13. Aumentar la formación de la población rural en programas académicos de la Universidad para cerrar la brecha urbano – rural | F32: M3 - Regionalización en contexto | G32: Realizar 2 estudios de pertinencia, para fortalecer la oferta académica pertinente en la región, con 20 programas académicos de pregrado y postgrado, que den respuesta al sector productivo y/u otros actores regionales, incrementando a 1500 los egresados de región y propendiendo que mínimo 350 de ellos desarrollen actividades económicamente productivas, aportando así al desarrollo socioeconómico de la región. | H32: P1 - Programas académicos con calidad y pertinencia regional | I32: 0.08 | J32: Impulsar la graduación oportuna de los estudiantes en región. | K32: 0.25 | L32: Director de Regionalización nivel Sede | M32: PDI | N32: X | O32: Egresados graduados en región | P32: Cantidad de estudiantes graduados en los programas en las sedes regionales | Q32: Anual | R32: Unidad | S32: Arquitectura 12 Básicas: 3 C. de la Salud:30 Educación: 50 Ingenieriía 20 | T32: Nuevo gestionado durante la vigencia | U32: 188 | V32: 0 | W32: 115 | X32: =IFERROR(IF($T32=Lists!$S$2,SUM(FORMULACIÓN!U32:W32),IF(FORMULACIÓN!$T32=Lists!$S$3,SUM(FORMULACIÓN!V32:W32),IF(FORMULACIÓN!$T32=Lists!$S$4,AVERAGE(FORMULACIÓN!V32:W32),IF(FORMULACIÓN!$T32=Lists!$S$5,OFFSET(U32,0,COUNTA(V32:W32)),IF(FORMULACIÓN!$T32=Lists!$S$6,AVERAGE(V32:W32),""))))),"") -> 115 | Y32: =IF($R32=Lists!$R$3,TEXT(FORMULACIÓN!X32,"00,00%"),IF(FORMULACIÓN!X32=0,0,TEXT(FORMULACIÓN!X32,"##.###"))) -> 115
A33: =IF(C33<>"",+A32+1,"") -> 24 | B33: 2026 | C33: L1 - Formación Académica Integral | D33: =IFERROR(VLOOKUP(FORMULACIÓN!C33,Lists!$A$2:$B$6,2,FALSE),"") -> Garantizar la formación en educación superior de manera integral e inclusiva, con calidad, pertinencia, flexibilidad, interdisciplinariedad, competencias digitales, internacionalización, multilingüismo e interculturalidad, mediante procesos de autorregulación sostenible y con perspectiva regional. | E33: 13. Aumentar la formación de la población rural en programas académicos de la Universidad para cerrar la brecha urbano – rural | F33: M3 - Regionalización en contexto | G33: Realizar 2 estudios de pertinencia, para fortalecer la oferta académica pertinente en la región, con 20 programas académicos de pregrado y postgrado, que den respuesta al sector productivo y/u otros actores regionales, incrementando a 1500 los egresados de región y propendiendo que mínimo 350 de ellos desarrollen actividades económicamente productivas, aportando así al desarrollo socioeconómico de la región. | H33: P1 - Programas académicos con calidad y pertinencia regional | I33: 0.08 | J33: Promover la vinculación de los egresados graduados en región al mercado laboral. | K33: 0.25 | L33: Jefe de Oficina de Egresados | M33: PDI | O33: Egresados graduados en región | P33: Número de egresados graduados en región activos en el mercado laboral y/o con emprendimientos | Q33: Anual | R33: Unidad | T33: Nuevo gestionado durante la vigencia | U33: 153 | V33: 0 | W33: 35 | X33: =IFERROR(IF($T33=Lists!$S$2,SUM(FORMULACIÓN!U33:W33),IF(FORMULACIÓN!$T33=Lists!$S$3,SUM(FORMULACIÓN!V33:W33),IF(FORMULACIÓN!$T33=Lists!$S$4,AVERAGE(FORMULACIÓN!V33:W33),IF(FORMULACIÓN!$T33=Lists!$S$5,OFFSET(U33,0,COUNTA(V33:W33)),IF(FORMULACIÓN!$T33=Lists!$S$6,AVERAGE(V33:W33),""))))),"") -> 35 | Y33: =IF($R33=Lists!$R$3,TEXT(FORMULACIÓN!X33,"00,00%"),IF(FORMULACIÓN!X33=0,0,TEXT(FORMULACIÓN!X33,"##.###"))) -> 35
A34: =IF(C34<>"",+A33+1,"") -> 25 | B34: 2026 | C34: L1 - Formación Académica Integral | D34: =IFERROR(VLOOKUP(FORMULACIÓN!C34,Lists!$A$2:$B$6,2,FALSE),"") -> Garantizar la formación en educación superior de manera integral e inclusiva, con calidad, pertinencia, flexibilidad, interdisciplinariedad, competencias digitales, internacionalización, multilingüismo e interculturalidad, mediante procesos de autorregulación sostenible y con perspectiva regional. | E34: 12. Articular la investigación y la extensión a la docencia para la formación integral de estudiantes de programas académico especialmente de las sedes regionales. | F34: M3 - Regionalización en contexto | G34: Propender por aumentar la dedicación de los docentes con vinculación de medio tiempo y/o tiempo completo de los programas regionalizados, en actividades misionales en las sedes | H34: P1 - Programas académicos con calidad y pertinencia regional | I34: 0.08 | J34: Gestionar la disponibilidad y dedicación de docentes para los programas en región | K34: 0.25 | L34: Director de Regionalización nivel Sede | M34: PA | N34: X | O34: Docentes dedicados actividades de la sede regionales | P34: N° de Docentes de tiempo completo y medio tiempo dedicados a actividades de sedes regionales | Q34: Semestral | R34: Unidad | S34: Arquitectura: 2 Básicas: 5 C. de la Salud: 2 Educación: 4 Ingenieriía:3 | T34: Promedio | U34: 17 | V34: 16 | W34: 16 | X34: =IFERROR(IF($T34=Lists!$S$2,SUM(FORMULACIÓN!U34:W34),IF(FORMULACIÓN!$T34=Lists!$S$3,SUM(FORMULACIÓN!V34:W34),IF(FORMULACIÓN!$T34=Lists!$S$4,AVERAGE(FORMULACIÓN!V34:W34),IF(FORMULACIÓN!$T34=Lists!$S$5,OFFSET(U34,0,COUNTA(V34:W34)),IF(FORMULACIÓN!$T34=Lists!$S$6,AVERAGE(V34:W34),""))))),"") -> 16 | Y34: =IF($R34=Lists!$R$3,TEXT(FORMULACIÓN!X34,"00,00%"),IF(FORMULACIÓN!X34=0,0,TEXT(FORMULACIÓN!X34,"##.###"))) -> 16
A35: =IF(C35<>"",+A34+1,"") -> 26 | B35: 2026 | C35: L1 - Formación Académica Integral | D35: =IFERROR(VLOOKUP(FORMULACIÓN!C35,Lists!$A$2:$B$6,2,FALSE),"") -> Garantizar la formación en educación superior de manera integral e inclusiva, con calidad, pertinencia, flexibilidad, interdisciplinariedad, competencias digitales, internacionalización, multilingüismo e interculturalidad, mediante procesos de autorregulación sostenible y con perspectiva regional. | E35: 13. Aumentar la formación de la población rural en programas académicos de la Universidad para cerrar la brecha urbano – rural | F35: M3 - Regionalización en contexto | G35: Fortalecer los procesos académicos en región para lograr 1200 estudiantes en programas de pregrado y/o postgrado. | H35: P2 - Acceso de población rural a programas académicos | I35: 0.04 | J35: Promover la vinculación de estudiantes a los programas académicos en región | K35: 0.5 | L35: Director de Regionalización nivel Sede | M35: PA | O35: Estudiantes matriculados en pregrado y postgrado en las sedes regionales | P35: Número de estudiantes matriculados en pregrado y postgrado en las sedes regionales | Q35: Semestral | R35: Unidad | T35: Promedio | U35: 1400 | V35: 1400 | W35: 1400 | X35: =IFERROR(IF($T35=Lists!$S$2,SUM(FORMULACIÓN!U35:W35),IF(FORMULACIÓN!$T35=Lists!$S$3,SUM(FORMULACIÓN!V35:W35),IF(FORMULACIÓN!$T35=Lists!$S$4,AVERAGE(FORMULACIÓN!V35:W35),IF(FORMULACIÓN!$T35=Lists!$S$5,OFFSET(U35,0,COUNTA(V35:W35)),IF(FORMULACIÓN!$T35=Lists!$S$6,AVERAGE(V35:W35),""))))),"") -> 1400 | Y35: =IF($R35=Lists!$R$3,TEXT(FORMULACIÓN!X35,"00,00%"),IF(FORMULACIÓN!X35=0,0,TEXT(FORMULACIÓN!X35,"##.###"))) -> 1.400
A36: =IF(C36<>"",+A35+1,"") -> 27 | B36: 2026 | C36: L1 - Formación Académica Integral | D36: =IFERROR(VLOOKUP(FORMULACIÓN!C36,Lists!$A$2:$B$6,2,FALSE),"") -> Garantizar la formación en educación superior de manera integral e inclusiva, con calidad, pertinencia, flexibilidad, interdisciplinariedad, competencias digitales, internacionalización, multilingüismo e interculturalidad, mediante procesos de autorregulación sostenible y con perspectiva regional. | E36: 7. Fortalecer académica y administrativamente los programas para lograr un mayor reconocimiento regional y la acreditación nacional e internacional. | F36: M3 - Regionalización en contexto | G36: Incrementar en un 30% el número de inscritos a programas de pregrado a través de la visibilización de la oferta académica en la región y departamentos vecinos | H36: P2 - Acceso de población rural a programas académicos | I36: 0.04 | J36: Levar la oferta académica a los diferentes municipios de la región, ferias de orientación ocupacional que realiza el MEN y alcaldes | K36: 0.5 | L36: Jefe del Departamento de Admisiones y Registro | M36: PA | O36: Tasa de crecimiento anual del número de aspirantes inscritos provenientes de municipios o regiones de todo el territorio Nacional | P36: Tasa de Crecimiento Anual (%)=(Número de Aspirantes Año Anterior - Número de Aspirantes Año Actual / Número de Aspirantes Año Anterior)×100 | Q36: Anual | R36: Porcentaje | T36: Nuevo gestionado durante la vigencia | U36: 0.5 | V36: 0 | W36: 0.5 | X36: =IFERROR(IF($T36=Lists!$S$2,SUM(FORMULACIÓN!U36:W36),IF(FORMULACIÓN!$T36=Lists!$S$3,SUM(FORMULACIÓN!V36:W36),IF(FORMULACIÓN!$T36=Lists!$S$4,AVERAGE(FORMULACIÓN!V36:W36),IF(FORMULACIÓN!$T36=Lists!$S$5,OFFSET(U36,0,COUNTA(V36:W36)),IF(FORMULACIÓN!$T36=Lists!$S$6,AVERAGE(V36:W36),""))))),"") -> 0.5 | Y36: =IF($R36=Lists!$R$3,TEXT(FORMULACIÓN!X36,"00,00%"),IF(FORMULACIÓN!X36=0,0,TEXT(FORMULACIÓN!X36,"##.###"))) -> 50,00%
A37: =IF(C37<>"",+A36+1,"") -> 28 | B37: 2026 | C37: L1 - Formación Académica Integral | D37: =IFERROR(VLOOKUP(FORMULACIÓN!C37,Lists!$A$2:$B$6,2,FALSE),"") -> Garantizar la formación en educación superior de manera integral e inclusiva, con calidad, pertinencia, flexibilidad, interdisciplinariedad, competencias digitales, internacionalización, multilingüismo e interculturalidad, mediante procesos de autorregulación sostenible y con perspectiva regional. | E37: 12. Articular la investigación y la extensión a la docencia para la formación integral de estudiantes de programas académico especialmente de las sedes regionales. | F37: M3 - Regionalización en contexto | G37: Impulsar el desarrollo regional a través de mínimo 40 convenios y/o venta de servicio, que propendan entre otros aspectos a la formación académica en región y al mejoramiento de los resultados de las pruebas Saber 11 de las instituciones educativas de la región. | H37: P3 - Articulación de la docencia con la investigación y extensión en región | I37: 0.05 | J37: Gestionar convenios con los entes territoriales y/o empresas para apoyar la formación académica en región | K37: 0.5 | L37: Director de Regionalización nivel Sede | M37: PDI | N37: X | O37: Convenios para apoyar la formación académica en región | P37: Número de convenios activos con los entes territoriales y/o empresas para apoyar la formación académica en región (pasantías, prácticas académicas, movilidad, laboratorios prestados o en comodato) | Q37: Anual | R37: Unidad | S37: Arquitectura 2 C básicas : 2 C. de la Salud: 3 Educación: 2 Ingeniería 1 Se refiere a todos los convenios independiente a la fecha de firma, pero que se encuentren activos | T37: Nuevo gestionado durante la vigencia | U37: 17 | V37: 0 | W37: 10 | X37: =IFERROR(IF($T37=Lists!$S$2,SUM(FORMULACIÓN!U37:W37),IF(FORMULACIÓN!$T37=Lists!$S$3,SUM(FORMULACIÓN!V37:W37),IF(FORMULACIÓN!$T37=Lists!$S$4,AVERAGE(FORMULACIÓN!V37:W37),IF(FORMULACIÓN!$T37=Lists!$S$5,OFFSET(U37,0,COUNTA(V37:W37)),IF(FORMULACIÓN!$T37=Lists!$S$6,AVERAGE(V37:W37),""))))),"") -> 10 | Y37: =IF($R37=Lists!$R$3,TEXT(FORMULACIÓN!X37,"00,00%"),IF(FORMULACIÓN!X37=0,0,TEXT(FORMULACIÓN!X37,"##.###"))) -> 10
A38: =IF(C38<>"",+A37+1,"") -> 29 | B38: 2026 | C38: L1 - Formación Académica Integral | D38: =IFERROR(VLOOKUP(FORMULACIÓN!C38,Lists!$A$2:$B$6,2,FALSE),"") -> Garantizar la formación en educación superior de manera integral e inclusiva, con calidad, pertinencia, flexibilidad, interdisciplinariedad, competencias digitales, internacionalización, multilingüismo e interculturalidad, mediante procesos de autorregulación sostenible y con perspectiva regional. | E38: 12. Articular la investigación y la extensión a la docencia para la formación integral de estudiantes de programas académico especialmente de las sedes regionales. | F38: M3 - Regionalización en contexto | G38: Fomentar la formación práctica en investigación para lograr al menos 125 estudiantes vinculados a semilleros de investigación | H38: P3 - Articulación de la docencia con la investigación y extensión en región | I38: 0.05 | J38: Articular con la Vicerrectoría de Investigación, Extensión y Proyección Social para el desarrollo de actividades en región de formación investigativa y proyección social región | K38: 0.5 | L38: Director de Regionalización nivel Sede | M38: PA | N38: X | O38: Estudiantes con formación práctica en investigación | P38: Número de estudiantes de la sede regional vinculados a Semilleros de Investigación | Q38: Anual | R38: Unidad | S38: Arquitectura: 20 C básicas : 6 C. de la Salud: 10 Educación: 30 Ingeniería: 15 Jurídica | T38: Promedio | U38: 66 | V38: 81 | W38: 81 | X38: =IFERROR(IF($T38=Lists!$S$2,SUM(FORMULACIÓN!U38:W38),IF(FORMULACIÓN!$T38=Lists!$S$3,SUM(FORMULACIÓN!V38:W38),IF(FORMULACIÓN!$T38=Lists!$S$4,AVERAGE(FORMULACIÓN!V38:W38),IF(FORMULACIÓN!$T38=Lists!$S$5,OFFSET(U38,0,COUNTA(V38:W38)),IF(FORMULACIÓN!$T38=Lists!$S$6,AVERAGE(V38:W38),""))))),"") -> 81 | Y38: =IF($R38=Lists!$R$3,TEXT(FORMULACIÓN!X38,"00,00%"),IF(FORMULACIÓN!X38=0,0,TEXT(FORMULACIÓN!X38,"##.###"))) -> 81
A39: =IF(C39<>"",+A38+1,"") -> 30 | B39: 2026 | C39: L1 - Formación Académica Integral | D39: =IFERROR(VLOOKUP(FORMULACIÓN!C39,Lists!$A$2:$B$6,2,FALSE),"") -> Garantizar la formación en educación superior de manera integral e inclusiva, con calidad, pertinencia, flexibilidad, interdisciplinariedad, competencias digitales, internacionalización, multilingüismo e interculturalidad, mediante procesos de autorregulación sostenible y con perspectiva regional. | E39: 5. Fortalecer Políticas curriculares con pedagogías adecuadas que atiendan al principio de calidad académica con enfoque inclusivo a través del desarrollo de las disciplinas y las profesiones, la integración de saberes, el fortalecimiento de competencias digitales, la solución de problemas y la inserción de los egresados al mercado laboral. | F39: M4 - Procesos académicos inclusivos e interculturales | G39: Diseñar, aprobar e implementar la Política de Educación inclusiva e intercultural. | H39: P1 - Política de Educación Inclusiva e Intercultural | I39: 0.03 | J39: Gestionar aprobación de la politica de Educación Inclusiva Intercultural de la UA | K39: 1 | L39: Vicerrector De Docencia | M39: PDI-PA | O39: Gestión de aprobación de la política de Educación Inclusiva Intercultural de la UA | P39: Acto Administrativo de aprobación de la política de Educación Inclusiva Intercultural de la UA por el Consejo Superior | Q39: Semestral | R39: Unidad | S39: acuerdo superior | T39: Nuevo gestionado durante la vigencia | U39: 0 | V39: 0 | W39: 1 | X39: =IFERROR(IF($T39=Lists!$S$2,SUM(FORMULACIÓN!U39:W39),IF(FORMULACIÓN!$T39=Lists!$S$3,SUM(FORMULACIÓN!V39:W39),IF(FORMULACIÓN!$T39=Lists!$S$4,AVERAGE(FORMULACIÓN!V39:W39),IF(FORMULACIÓN!$T39=Lists!$S$5,OFFSET(U39,0,COUNTA(V39:W39)),IF(FORMULACIÓN!$T39=Lists!$S$6,AVERAGE(V39:W39),""))))),"") -> 1 | Y39: =IF($R39=Lists!$R$3,TEXT(FORMULACIÓN!X39,"00,00%"),IF(FORMULACIÓN!X39=0,0,TEXT(FORMULACIÓN!X39,"##.###"))) -> 1
A40: =IF(C40<>"",+A39+1,"") -> 31 | B40: 2026 | C40: L1 - Formación Académica Integral | D40: =IFERROR(VLOOKUP(FORMULACIÓN!C40,Lists!$A$2:$B$6,2,FALSE),"") -> Garantizar la formación en educación superior de manera integral e inclusiva, con calidad, pertinencia, flexibilidad, interdisciplinariedad, competencias digitales, internacionalización, multilingüismo e interculturalidad, mediante procesos de autorregulación sostenible y con perspectiva regional. | E40: 14. Fortalecer la vinculación del sector productivo y/o otros actores regionales para el fortalecimiento de oferta académica en región. | F40: M4 - Procesos académicos inclusivos e interculturales | G40: Lograr 10 convenios con las Secretarías de Educación y/u organizaciones públicas o privadas de la región para beneficiar a la población diversa de la educación media y fomentar el acceso a la educación superior. | H40: P2 - Articulación con la educación básica y media para el fortalecimiento de los procesos de educación inclusiva | I40: 0.03 | J40: Operacionalizar los convenios y/o alianzas activos con Secretarías de Educación y/o organizaciones públicas o privadas en beneficio de la educación básica y media | K40: 1 | L40: Vicerrector De Docencia | M40: PDI | O40: Número de convenios y/o alianzas operando con Secretarías de Educación y/u organizaciones públicas o privadas para fomentar el acceso a la educación superior en articulación con la educación básica y media | P40: N° de convenios y/o alianzas activas con Secretarías de Educación y/u organizaciones públicas o privadas | Q40: Anual | R40: Unidad | S40: Convenios y/o alianzas activos, en el 2025 se reañlizaron (2) convenios con Telecaribe y Unidad de Victima. Para el 2026, se proyectan dos convenios con : ICBF FUNDAVE | T40: Nuevo gestionado durante la vigencia | U40: 6 | V40: 0 | W40: 2 | X40: =IFERROR(IF($T40=Lists!$S$2,SUM(FORMULACIÓN!U40:W40),IF(FORMULACIÓN!$T40=Lists!$S$3,SUM(FORMULACIÓN!V40:W40),IF(FORMULACIÓN!$T40=Lists!$S$4,AVERAGE(FORMULACIÓN!V40:W40),IF(FORMULACIÓN!$T40=Lists!$S$5,OFFSET(U40,0,COUNTA(V40:W40)),IF(FORMULACIÓN!$T40=Lists!$S$6,AVERAGE(V40:W40),""))))),"") -> 2 | Y40: =IF($R40=Lists!$R$3,TEXT(FORMULACIÓN!X40,"00,00%"),IF(FORMULACIÓN!X40=0,0,TEXT(FORMULACIÓN!X40,"##.###"))) -> 2
A41: =IF(C41<>"",+A40+1,"") -> 32 | B41: 2026 | C41: L1 - Formación Académica Integral | D41: =IFERROR(VLOOKUP(FORMULACIÓN!C41,Lists!$A$2:$B$6,2,FALSE),"") -> Garantizar la formación en educación superior de manera integral e inclusiva, con calidad, pertinencia, flexibilidad, interdisciplinariedad, competencias digitales, internacionalización, multilingüismo e interculturalidad, mediante procesos de autorregulación sostenible y con perspectiva regional. | E41: 5. Fortalecer Políticas curriculares con pedagogías adecuadas que atiendan al principio de calidad académica con enfoque inclusivo a través del desarrollo de las disciplinas y las profesiones, la integración de saberes, el fortalecimiento de competencias digitales, la solución de problemas y la inserción de los egresados al mercado laboral. | F41: M4 - Procesos académicos inclusivos e interculturales | G41: Implementar un centro de documentación de materiales educativos accesibles para la población diversa con 2000 productos catalogados por área de conocimiento | H41: P3 - Materiales accesibles diseñados, creados y adaptados para población diversa | I41: 0.05 | J41: Catalogar los materiales educativos accesibles por área de conocimiento | K41: 1 | L41: Vicerrector De Docencia | M41: PDI | O41: Creación de materiales educativos accesibles para la población diversa | P41: Materiales educativos accesibles catalogados por área de conocimiento | Q41: Anual | R41: Unidad | T41: Nuevo gestionado durante la vigencia | U41: 1029 | V41: 0 | W41: 120 | X41: =IFERROR(IF($T41=Lists!$S$2,SUM(FORMULACIÓN!U41:W41),IF(FORMULACIÓN!$T41=Lists!$S$3,SUM(FORMULACIÓN!V41:W41),IF(FORMULACIÓN!$T41=Lists!$S$4,AVERAGE(FORMULACIÓN!V41:W41),IF(FORMULACIÓN!$T41=Lists!$S$5,OFFSET(U41,0,COUNTA(V41:W41)),IF(FORMULACIÓN!$T41=Lists!$S$6,AVERAGE(V41:W41),""))))),"") -> 120 | Y41: =IF($R41=Lists!$R$3,TEXT(FORMULACIÓN!X41,"00,00%"),IF(FORMULACIÓN!X41=0,0,TEXT(FORMULACIÓN!X41,"##.###"))) -> 120
A42: =IF(C42<>"",+A41+1,"") -> 33 | B42: 2026 | C42: L1 - Formación Académica Integral | D42: =IFERROR(VLOOKUP(FORMULACIÓN!C42,Lists!$A$2:$B$6,2,FALSE),"") -> Garantizar la formación en educación superior de manera integral e inclusiva, con calidad, pertinencia, flexibilidad, interdisciplinariedad, competencias digitales, internacionalización, multilingüismo e interculturalidad, mediante procesos de autorregulación sostenible y con perspectiva regional. | E42: 5. Fortalecer Políticas curriculares con pedagogías adecuadas que atiendan al principio de calidad académica con enfoque inclusivo a través del desarrollo de las disciplinas y las profesiones, la integración de saberes, el fortalecimiento de competencias digitales, la solución de problemas y la inserción de los egresados al mercado laboral. | F42: M4 - Procesos académicos inclusivos e interculturales | G42: Lograr el 100% de los programas académicos resignificados con base en la Política de Educación inclusiva e intercultural (componente inclusivo en los cursos del pensum, actividades para población diversa, didáctica inclusiva, metodología flexible, recursos digitales con componente de inclusión, entre otras) | H42: P4 - Formación para la transformación institucional basado en educación inclusiva, intercultural y pluridiversa | I42: 0.02 | J42: Revisar y adecuar los programas académicos bajo un enfoque inclusivo e intercultural. | K42: 0.333 | L42: Vicerrector De Docencia | M42: PDI | O42: Porcentaje de programas académicos resignificados bajo un enfoque inclusivo e intercultural. | P42: N° de programas académicos resignificados /Total de programas académicos de la institución *100 | Q42: Anual | R42: Porcentaje | S42: Del total de programas de la UA, se debe cumplir por lo menos el 20%, icluyendo los que ya se encuentran resignificados | T42: Último valor reportado | U42: 0.09 | V42: 0 | W42: 0.2 | X42: =IFERROR(IF($T42=Lists!$S$2,SUM(FORMULACIÓN!U42:W42),IF(FORMULACIÓN!$T42=Lists!$S$3,SUM(FORMULACIÓN!V42:W42),IF(FORMULACIÓN!$T42=Lists!$S$4,AVERAGE(FORMULACIÓN!V42:W42),IF(FORMULACIÓN!$T42=Lists!$S$5,OFFSET(U42,0,COUNTA(V42:W42)),IF(FORMULACIÓN!$T42=Lists!$S$6,AVERAGE(V42:W42),""))))),"") -> 0.2 | Y42: =IF($R42=Lists!$R$3,TEXT(FORMULACIÓN!X42,"00,00%"),IF(FORMULACIÓN!X42=0,0,TEXT(FORMULACIÓN!X42,"##.###"))) -> 20,00%
A43: =IF(C43<>"",+A42+1,"") -> 34 | B43: 2026 | C43: L1 - Formación Académica Integral | D43: =IFERROR(VLOOKUP(FORMULACIÓN!C43,Lists!$A$2:$B$6,2,FALSE),"") -> Garantizar la formación en educación superior de manera integral e inclusiva, con calidad, pertinencia, flexibilidad, interdisciplinariedad, competencias digitales, internacionalización, multilingüismo e interculturalidad, mediante procesos de autorregulación sostenible y con perspectiva regional. | E43: 10. Promover la formación y desarrollo en temas de innovación educativa inclusiva. | F43: M4 - Procesos académicos inclusivos e interculturales | G43: Capacitar a 3000 estudiantes o más en educación inclusiva, intercultural y pluridiversa | H43: P4 - Formación para la transformación institucional basado en educación inclusiva, intercultural y pluridiversa | I43: 0.02 | J43: Capacitar a los estudiantes en educación inclusiva, intercultural y pluridiversa | K43: 0.333 | L43: Vicerrector De Docencia | M43: PA | O43: Estudiantes capacitados en temáticas relacionadas con educación inclusiva, interculturalidad y pluridiversidad | P43: N° de estudiantes capacitados en temáticas relacionadas con educación inclusiva, interculturalidad y pluridiversidad | Q43: Anual | R43: Unidad | T43: Nuevo gestionado durante la vigencia | U43: 265 | V43: 0 | W43: 200 | X43: =IFERROR(IF($T43=Lists!$S$2,SUM(FORMULACIÓN!U43:W43),IF(FORMULACIÓN!$T43=Lists!$S$3,SUM(FORMULACIÓN!V43:W43),IF(FORMULACIÓN!$T43=Lists!$S$4,AVERAGE(FORMULACIÓN!V43:W43),IF(FORMULACIÓN!$T43=Lists!$S$5,OFFSET(U43,0,COUNTA(V43:W43)),IF(FORMULACIÓN!$T43=Lists!$S$6,AVERAGE(V43:W43),""))))),"") -> 200 | Y43: =IF($R43=Lists!$R$3,TEXT(FORMULACIÓN!X43,"00,00%"),IF(FORMULACIÓN!X43=0,0,TEXT(FORMULACIÓN!X43,"##.###"))) -> 200
A44: =IF(C44<>"",+A43+1,"") -> 35 | B44: 2026 | C44: L1 - Formación Académica Integral | D44: =IFERROR(VLOOKUP(FORMULACIÓN!C44,Lists!$A$2:$B$6,2,FALSE),"") -> Garantizar la formación en educación superior de manera integral e inclusiva, con calidad, pertinencia, flexibilidad, interdisciplinariedad, competencias digitales, internacionalización, multilingüismo e interculturalidad, mediante procesos de autorregulación sostenible y con perspectiva regional. | E44: 10. Promover la formación y desarrollo en temas de innovación educativa inclusiva. | F44: M4 - Procesos académicos inclusivos e interculturales | G44: Capacitar al 80% de los administrativos en educación inclusiva, intercultural y pluridiversa | H44: P4 - Formación para la transformación institucional basado en educación inclusiva, intercultural y pluridiversa | I44: 0.02 | J44: Capacitar a los administrativos en educación inclusiva, intercultural y pluridiversa | K44: 0.333 | L44: Vicerrector De Docencia | M44: PA | O44: Administrativos capacitados en temáticas relacionadas con educación inclusiva, interculturalidad y pluridiversidad | P44: N° de administrativos capacitados en temáticas relacionadas con educación inclusiva, interculturalidad y pluridiversidad | Q44: Anual | R44: Unidad | T44: Nuevo gestionado durante la vigencia | U44: 40 | V44: 0 | W44: 60 | X44: =IFERROR(IF($T44=Lists!$S$2,SUM(FORMULACIÓN!U44:W44),IF(FORMULACIÓN!$T44=Lists!$S$3,SUM(FORMULACIÓN!V44:W44),IF(FORMULACIÓN!$T44=Lists!$S$4,AVERAGE(FORMULACIÓN!V44:W44),IF(FORMULACIÓN!$T44=Lists!$S$5,OFFSET(U44,0,COUNTA(V44:W44)),IF(FORMULACIÓN!$T44=Lists!$S$6,AVERAGE(V44:W44),""))))),"") -> 60 | Y44: =IF($R44=Lists!$R$3,TEXT(FORMULACIÓN!X44,"00,00%"),IF(FORMULACIÓN!X44=0,0,TEXT(FORMULACIÓN!X44,"##.###"))) -> 60
A45: =IF(C45<>"",+A44+1,"") -> 36 | B45: 2026 | C45: L1 - Formación Académica Integral | D45: =IFERROR(VLOOKUP(FORMULACIÓN!C45,Lists!$A$2:$B$6,2,FALSE),"") -> Garantizar la formación en educación superior de manera integral e inclusiva, con calidad, pertinencia, flexibilidad, interdisciplinariedad, competencias digitales, internacionalización, multilingüismo e interculturalidad, mediante procesos de autorregulación sostenible y con perspectiva regional. | E45: 2. Consolidar la estructura y el funcionamiento del Sistema de Aseguramiento Interno de la Calidad, de acuerdo a la normatividad y lineamientos vigentes del Ministerio de Educación Nacional. | F45: M5 - Autoevaluación y acreditación Institucional y de programas académicos en el contexto nacional e internacional | G45: Diseñar e implementar el Sistema Interno Integrado para la excelencia institucional | H45: P1 - Excelencia académica | I45: 0.12 | J45: Gestionar el fortalecimiento de las Capacidades Técnicas para Sistema Interno Integrado | K45: 0.35 | L45: Jefe del Departamento Calidad Academica | M45: PDI | O45: Implementación del Sistema Interno Integrado | P45: N° de componentes del Sistema Interno Integrado implementados / N° de componentes del Sistema Interno Integrado aprobados * 100. | Q45: Anual | R45: Porcentaje | S45: Debe gestioanr el 25% de todos los componentes para alcanzar el 35% | T45: Último valor reportado | U45: 0.1 | V45: 0 | W45: 0.35 | X45: =IFERROR(IF($T45=Lists!$S$2,SUM(FORMULACIÓN!U45:W45),IF(FORMULACIÓN!$T45=Lists!$S$3,SUM(FORMULACIÓN!V45:W45),IF(FORMULACIÓN!$T45=Lists!$S$4,AVERAGE(FORMULACIÓN!V45:W45),IF(FORMULACIÓN!$T45=Lists!$S$5,OFFSET(U45,0,COUNTA(V45:W45)),IF(FORMULACIÓN!$T45=Lists!$S$6,AVERAGE(V45:W45),""))))),"") -> 0.35 | Y45: =IF($R45=Lists!$R$3,TEXT(FORMULACIÓN!X45,"00,00%"),IF(FORMULACIÓN!X45=0,0,TEXT(FORMULACIÓN!X45,"##.###"))) -> 35,00%
A46: =IF(C46<>"",+A45+1,"") -> 37 | B46: 2026 | C46: L1 - Formación Académica Integral | D46: =IFERROR(VLOOKUP(FORMULACIÓN!C46,Lists!$A$2:$B$6,2,FALSE),"") -> Garantizar la formación en educación superior de manera integral e inclusiva, con calidad, pertinencia, flexibilidad, interdisciplinariedad, competencias digitales, internacionalización, multilingüismo e interculturalidad, mediante procesos de autorregulación sostenible y con perspectiva regional. | E46: 7. Fortalecer académica y administrativamente los programas para lograr un mayor reconocimiento regional y la acreditación nacional e internacional. | F46: M5 - Autoevaluación y acreditación Institucional y de programas académicos en el contexto nacional e internacional | G46: Lograr el reconocimiento nacional e internacional de los procesos misionales y de apoyo a la gestión, con el 70% de programas académicos acreditados a nivel nacional y al menos 5 a nivel internacional | H46: P1 - Excelencia académica | I46: 0.12 | J46: Gestionar la acreditación de nuestros programas académicos. | K46: 0.35 | L46: Jefe del Departamento Calidad Academica | M46: PDI | O46: Porcentaje de programas académicos acreditados respecto a los acreditables | P46: N° programas académicos acreditados / total de programas académicos acreditables * 100 | Q46: Anual | R46: Porcentaje | T46: Último valor reportado | U46: 0.76 | V46: 0 | W46: 0.65 | X46: =IFERROR(IF($T46=Lists!$S$2,SUM(FORMULACIÓN!U46:W46),IF(FORMULACIÓN!$T46=Lists!$S$3,SUM(FORMULACIÓN!V46:W46),IF(FORMULACIÓN!$T46=Lists!$S$4,AVERAGE(FORMULACIÓN!V46:W46),IF(FORMULACIÓN!$T46=Lists!$S$5,OFFSET(U46,0,COUNTA(V46:W46)),IF(FORMULACIÓN!$T46=Lists!$S$6,AVERAGE(V46:W46),""))))),"") -> 0.65 | Y46: =IF($R46=Lists!$R$3,TEXT(FORMULACIÓN!X46,"00,00%"),IF(FORMULACIÓN!X46=0,0,TEXT(FORMULACIÓN!X46,"##.###"))) -> 65,00%
A47: =IF(C47<>"",+A46+1,"") -> 38 | B47: 2026 | C47: L1 - Formación Académica Integral | D47: =IFERROR(VLOOKUP(FORMULACIÓN!C47,Lists!$A$2:$B$6,2,FALSE),"") -> Garantizar la formación en educación superior de manera integral e inclusiva, con calidad, pertinencia, flexibilidad, interdisciplinariedad, competencias digitales, internacionalización, multilingüismo e interculturalidad, mediante procesos de autorregulación sostenible y con perspectiva regional. | E47: 7. Fortalecer académica y administrativamente los programas para lograr un mayor reconocimiento regional y la acreditación nacional e internacional. | F47: M5 - Autoevaluación y acreditación Institucional y de programas académicos en el contexto nacional e internacional | G47: Lograr el reconocimiento nacional e internacional de los procesos misionales y de apoyo a la gestión, con el 70% de programas académicos acreditados a nivel nacional y al menos 5 a nivel internacional | H47: P1 - Excelencia académica | I47: 0.12 | J47: Gestionar la acreditación de nuestros programas académicos. | K47: 0.3 | L47: Jefe del Departamento Calidad Academica | M47: PDI | N47: X | O47: Programas académicos acreditados internacionalmente | P47: N° de programas acreditados internacionalmente | Q47: Anual | R47: Unidad | S47: Ingeniería industrial | T47: Nuevo gestionado durante la vigencia | U47: 1 | V47: 0 | W47: 1 | X47: =IFERROR(IF($T47=Lists!$S$2,SUM(FORMULACIÓN!U47:W47),IF(FORMULACIÓN!$T47=Lists!$S$3,SUM(FORMULACIÓN!V47:W47),IF(FORMULACIÓN!$T47=Lists!$S$4,AVERAGE(FORMULACIÓN!V47:W47),IF(FORMULACIÓN!$T47=Lists!$S$5,OFFSET(U47,0,COUNTA(V47:W47)),IF(FORMULACIÓN!$T47=Lists!$S$6,AVERAGE(V47:W47),""))))),"") -> 1 | Y47: =IF($R47=Lists!$R$3,TEXT(FORMULACIÓN!X47,"00,00%"),IF(FORMULACIÓN!X47=0,0,TEXT(FORMULACIÓN!X47,"##.###"))) -> 1
A48: =IF(C48<>"",+A47+1,"") -> 39 | B48: 2026 | C48: L1 - Formación Académica Integral | D48: =IFERROR(VLOOKUP(FORMULACIÓN!C48,Lists!$A$2:$B$6,2,FALSE),"") -> Garantizar la formación en educación superior de manera integral e inclusiva, con calidad, pertinencia, flexibilidad, interdisciplinariedad, competencias digitales, internacionalización, multilingüismo e interculturalidad, mediante procesos de autorregulación sostenible y con perspectiva regional. | E48: 1. Fortalecer la oferta académica de manera flexible e interdisciplinar con diversas modalidades, articulada a procesos de enseñanza y aprendizaje innovadores en sus diferentes niveles y campos de formación. | F48: M5 - Autoevaluación y acreditación Institucional y de programas académicos en el contexto nacional e internacional | G48: Fortalecer la oferta académica pertinente con 55 programas de pregrado, 25 especializaciones, 30 maestrías, 10 doctorados, de los cuales 15 tengan modalidad virtual o mixta. | H48: P2 - Ampliación y diversificación de la oferta académica | I48: 0.06 | J48: Gestionar la creación de nuevos programas académicos que den repuesta a las necesidades del entorno | K48: 0.1 | L48: Jefe del Departamento de Postgrado | M48: PDI | N48: X | O48: Número de nuevos programas académicos de pregrado activos | P48: N° de programas académicos de pregrado activos | Q48: Anual | R48: Unidad | S48: Nota: se van a contar los registros calificados vigentes Partimos de una línea base de 51 programas , teniendo en cuenta que los programas de Lic música de valledupar y San andrés aún se encuentran activos en el Snies Ingeniaería: Ing. De Software | T48: Acumulado | U48: 51 | V48: 0 | W48: 1 | X48: =IFERROR(IF($T48=Lists!$S$2,SUM(FORMULACIÓN!U48:W48),IF(FORMULACIÓN!$T48=Lists!$S$3,SUM(FORMULACIÓN!V48:W48),IF(FORMULACIÓN!$T48=Lists!$S$4,AVERAGE(FORMULACIÓN!V48:W48),IF(FORMULACIÓN!$T48=Lists!$S$5,OFFSET(U48,0,COUNTA(V48:W48)),IF(FORMULACIÓN!$T48=Lists!$S$6,AVERAGE(V48:W48),""))))),"") -> 52 | Y48: =IF($R48=Lists!$R$3,TEXT(FORMULACIÓN!X48,"00,00%"),IF(FORMULACIÓN!X48=0,0,TEXT(FORMULACIÓN!X48,"##.###"))) -> 52
A49: =IF(C49<>"",+A48+1,"") -> 40 | B49: 2026 | C49: L1 - Formación Académica Integral | D49: =IFERROR(VLOOKUP(FORMULACIÓN!C49,Lists!$A$2:$B$6,2,FALSE),"") -> Garantizar la formación en educación superior de manera integral e inclusiva, con calidad, pertinencia, flexibilidad, interdisciplinariedad, competencias digitales, internacionalización, multilingüismo e interculturalidad, mediante procesos de autorregulación sostenible y con perspectiva regional. | E49: 1. Fortalecer la oferta académica de manera flexible e interdisciplinar con diversas modalidades, articulada a procesos de enseñanza y aprendizaje innovadores en sus diferentes niveles y campos de formación. | F49: M5 - Autoevaluación y acreditación Institucional y de programas académicos en el contexto nacional e internacional | G49: Fortalecer la oferta académica pertinente con 55 programas de pregrado, 25 especializaciones, 30 maestrías, 10 doctorados, de los cuales 15 tengan modalidad virtual o mixta. | H49: P2 - Ampliación y diversificación de la oferta académica | I49: 0.06 | J49: Gestionar la creación de nuevos programas académicos que den repuesta a las necesidades del entorno | K49: 0.1 | L49: Jefe del Departamento Calidad Academica | M49: PDI | N49: X | O49: Número de nuevos programas académicos en modalidad virtual o mixta activos | P49: N° de programas académicos en modalidad virtual o mixta activos | Q49: Anual | R49: Unidad | S49: Ingeniería de Software | T49: Acumulado | U49: 11 | V49: 0 | W49: 1 | X49: =IFERROR(IF($T49=Lists!$S$2,SUM(FORMULACIÓN!U49:W49),IF(FORMULACIÓN!$T49=Lists!$S$3,SUM(FORMULACIÓN!V49:W49),IF(FORMULACIÓN!$T49=Lists!$S$4,AVERAGE(FORMULACIÓN!V49:W49),IF(FORMULACIÓN!$T49=Lists!$S$5,OFFSET(U49,0,COUNTA(V49:W49)),IF(FORMULACIÓN!$T49=Lists!$S$6,AVERAGE(V49:W49),""))))),"") -> 12 | Y49: =IF($R49=Lists!$R$3,TEXT(FORMULACIÓN!X49,"00,00%"),IF(FORMULACIÓN!X49=0,0,TEXT(FORMULACIÓN!X49,"##.###"))) -> 12
A50: =IF(C50<>"",+A49+1,"") -> 41 | B50: 2026 | C50: L1 - Formación Académica Integral | D50: =IFERROR(VLOOKUP(FORMULACIÓN!C50,Lists!$A$2:$B$6,2,FALSE),"") -> Garantizar la formación en educación superior de manera integral e inclusiva, con calidad, pertinencia, flexibilidad, interdisciplinariedad, competencias digitales, internacionalización, multilingüismo e interculturalidad, mediante procesos de autorregulación sostenible y con perspectiva regional. | E50: 1. Fortalecer la oferta académica de manera flexible e interdisciplinar con diversas modalidades, articulada a procesos de enseñanza y aprendizaje innovadores en sus diferentes niveles y campos de formación. | F50: M5 - Autoevaluación y acreditación Institucional y de programas académicos en el contexto nacional e internacional | G50: Fortalecer la oferta académica pertinente con 55 programas de pregrado, 25 especializaciones, 30 maestrías, 10 doctorados, de los cuales 15 tengan modalidad virtual o mixta | H50: P2 - Ampliación y diversificación de la oferta académica | I50: 0.06 | J50: Asegurar oferta pertinente de programas académicos. | K50: 0.2 | L50: Jefe del Departamento Calidad Academica | M50: PDI | N50: X | O50: Número nuevos programas académicos de posgrado activos | P50: N° de programas académicos de especialización activos | Q50: Anual | R50: Unidad | S50: Especialización Gestión Integral del turismo | T50: Acumulado | U50: 16 | V50: 0 | W50: 1 | X50: =IFERROR(IF($T50=Lists!$S$2,SUM(FORMULACIÓN!U50:W50),IF(FORMULACIÓN!$T50=Lists!$S$3,SUM(FORMULACIÓN!V50:W50),IF(FORMULACIÓN!$T50=Lists!$S$4,AVERAGE(FORMULACIÓN!V50:W50),IF(FORMULACIÓN!$T50=Lists!$S$5,OFFSET(U50,0,COUNTA(V50:W50)),IF(FORMULACIÓN!$T50=Lists!$S$6,AVERAGE(V50:W50),""))))),"") -> 17 | Y50: =IF($R50=Lists!$R$3,TEXT(FORMULACIÓN!X50,"00,00%"),IF(FORMULACIÓN!X50=0,0,TEXT(FORMULACIÓN!X50,"##.###"))) -> 17
A51: =IF(C51<>"",+A50+1,"") -> 42 | B51: 2026 | C51: L1 - Formación Académica Integral | D51: =IFERROR(VLOOKUP(FORMULACIÓN!C51,Lists!$A$2:$B$6,2,FALSE),"") -> Garantizar la formación en educación superior de manera integral e inclusiva, con calidad, pertinencia, flexibilidad, interdisciplinariedad, competencias digitales, internacionalización, multilingüismo e interculturalidad, mediante procesos de autorregulación sostenible y con perspectiva regional. | E51: 1. Fortalecer la oferta académica de manera flexible e interdisciplinar con diversas modalidades, articulada a procesos de enseñanza y aprendizaje innovadores en sus diferentes niveles y campos de formación. | F51: M5 - Autoevaluación y acreditación Institucional y de programas académicos en el contexto nacional e internacional | G51: Fortalecer la oferta académica pertinente con 55 programas de pregrado, 25 especializaciones, 30 maestrías, 10 doctorados, de los cuales 15 tengan modalidad virtual o mixta | H51: P2 - Ampliación y diversificación de la oferta académica | I51: 0.06 | J51: Asegurar oferta pertinente de programas académicos. | K51: 0.2 | L51: Jefe del Departamento Calidad Academica | M51: PDI | N51: X | O51: Número nuevos programas académicos de posgrado activos | P51: N° de programas académicos de maestría activos | Q51: Anual | R51: Unidad | S51: Maestria en Educación Ambiental | T51: Acumulado | U51: 28 | V51: 0 | W51: 1 | X51: =IFERROR(IF($T51=Lists!$S$2,SUM(FORMULACIÓN!U51:W51),IF(FORMULACIÓN!$T51=Lists!$S$3,SUM(FORMULACIÓN!V51:W51),IF(FORMULACIÓN!$T51=Lists!$S$4,AVERAGE(FORMULACIÓN!V51:W51),IF(FORMULACIÓN!$T51=Lists!$S$5,OFFSET(U51,0,COUNTA(V51:W51)),IF(FORMULACIÓN!$T51=Lists!$S$6,AVERAGE(V51:W51),""))))),"") -> 29 | Y51: =IF($R51=Lists!$R$3,TEXT(FORMULACIÓN!X51,"00,00%"),IF(FORMULACIÓN!X51=0,0,TEXT(FORMULACIÓN!X51,"##.###"))) -> 29
A52: =IF(C52<>"",+A51+1,"") -> 43 | B52: 2026 | C52: L1 - Formación Académica Integral | D52: =IFERROR(VLOOKUP(FORMULACIÓN!C52,Lists!$A$2:$B$6,2,FALSE),"") -> Garantizar la formación en educación superior de manera integral e inclusiva, con calidad, pertinencia, flexibilidad, interdisciplinariedad, competencias digitales, internacionalización, multilingüismo e interculturalidad, mediante procesos de autorregulación sostenible y con perspectiva regional. | E52: 7. Fortalecer académica y administrativamente los programas para lograr un mayor reconocimiento regional y la acreditación nacional e internacional. | F52: M5 - Autoevaluación y acreditación Institucional y de programas académicos en el contexto nacional e internacional | G52: Fortalecer la vinculación con el sector externo para beneficiar a los estudiantes de postgrados (facilidades de acceso a los programas, desarrollo de actividades académicas e investigativas, entre otros) | H52: P2 - Ampliación y diversificación de la oferta académica | I52: 0.06 | J52: Asegurar convenios con entes externos para favorecer a los estudiantes de Postgrados | K52: 0.2 | L52: Jefe del Departamento de Postgrado | M52: PA | O52: Impacto de los convenios de vinculación gestionados con el sector productivo, el sector público o el sector social para estudiar programas de postgrado | P52: N° de estudiantes de postgrado beneficiados a través de los convenios gestionados con el sector productivo, el sector público o el sector social | Q52: Anual | R52: Unidad | T52: Nuevo gestionado durante la vigencia | U52: 18 | V52: 0 | W52: 10 | X52: =IFERROR(IF($T52=Lists!$S$2,SUM(FORMULACIÓN!U52:W52),IF(FORMULACIÓN!$T52=Lists!$S$3,SUM(FORMULACIÓN!V52:W52),IF(FORMULACIÓN!$T52=Lists!$S$4,AVERAGE(FORMULACIÓN!V52:W52),IF(FORMULACIÓN!$T52=Lists!$S$5,OFFSET(U52,0,COUNTA(V52:W52)),IF(FORMULACIÓN!$T52=Lists!$S$6,AVERAGE(V52:W52),""))))),"") -> 10 | Y52: =IF($R52=Lists!$R$3,TEXT(FORMULACIÓN!X52,"00,00%"),IF(FORMULACIÓN!X52=0,0,TEXT(FORMULACIÓN!X52,"##.###"))) -> 10
A53: =IF(C53<>"",+A52+1,"") -> 44 | B53: 2026 | C53: L1 - Formación Académica Integral | D53: =IFERROR(VLOOKUP(FORMULACIÓN!C53,Lists!$A$2:$B$6,2,FALSE),"") -> Garantizar la formación en educación superior de manera integral e inclusiva, con calidad, pertinencia, flexibilidad, interdisciplinariedad, competencias digitales, internacionalización, multilingüismo e interculturalidad, mediante procesos de autorregulación sostenible y con perspectiva regional. | E53: 7. Fortalecer académica y administrativamente los programas para lograr un mayor reconocimiento regional y la acreditación nacional e internacional. | F53: M5 - Autoevaluación y acreditación Institucional y de programas académicos en el contexto nacional e internacional | G53: Medir el crecimiento semestral de la matrícula de estudiantes en los programas de postgrado. | H53: P2 - Ampliación y diversificación de la oferta académica | I53: 0.06 | J53: Medir el crecimiento semestral de la matrícula de estudiantes en los programas de postgrado. | K53: 0.2 | L53: Jefe del Departamento de Postgrado | M53: PA | O53: Tasa de variación porcentual de los matriculados de postgrados | P53: [(Matriculados t1- matriculados t0) / matriculados t0] * 100 | Q53: Semestral | R53: Porcentaje | T53: Promedio | U53: 0.04 | V53: 0.06 | W53: 0.06 | X53: =IFERROR(IF($T53=Lists!$S$2,SUM(FORMULACIÓN!U53:W53),IF(FORMULACIÓN!$T53=Lists!$S$3,SUM(FORMULACIÓN!V53:W53),IF(FORMULACIÓN!$T53=Lists!$S$4,AVERAGE(FORMULACIÓN!V53:W53),IF(FORMULACIÓN!$T53=Lists!$S$5,OFFSET(U53,0,COUNTA(V53:W53)),IF(FORMULACIÓN!$T53=Lists!$S$6,AVERAGE(V53:W53),""))))),"") -> 0.06 | Y53: =IF($R53=Lists!$R$3,TEXT(FORMULACIÓN!X53,"00,00%"),IF(FORMULACIÓN!X53=0,0,TEXT(FORMULACIÓN!X53,"##.###"))) -> 06,00%
A54: =IF(C54<>"",+A53+1,"") -> 45 | B54: 2026 | C54: L1 - Formación Académica Integral | D54: =IFERROR(VLOOKUP(FORMULACIÓN!C54,Lists!$A$2:$B$6,2,FALSE),"") -> Garantizar la formación en educación superior de manera integral e inclusiva, con calidad, pertinencia, flexibilidad, interdisciplinariedad, competencias digitales, internacionalización, multilingüismo e interculturalidad, mediante procesos de autorregulación sostenible y con perspectiva regional. | E54: 1. Fortalecer la oferta académica de manera flexible e interdisciplinar con diversas modalidades, articulada a procesos de enseñanza y aprendizaje innovadores en sus diferentes niveles y campos de formación. | F54: M5 - Autoevaluación y acreditación Institucional y de programas académicos en el contexto nacional e internacional | G54: Formación profesional con enfoque hacia la responsabilidad social universitaria (RSU) en el 100% de los programas académicos. | H54: P3 - Gestión y mejoramiento curricular | I54: 0.05 | J54: Diseñar cursos que contengan las temáticas ciudadanas y de responsabilidad social en el currículo (DD.HH, desarrollo sostenible, ética profesional y cívica, gestión de la RS, ODS) | K54: 0.2 | L54: Vicerrector De Docencia | M54: PDI - PA | N54: x | O54: Cursos de los planes de estudio que aborden temáticas ciudadanas y de responsabilidad social (DD.HH, desarrollo sostenible, ética profesional y cívica, gestión de la RS, ODS). | P54: N° de programas académicos que en su plan de estudio contengan al menos 20% pregrado y 10% en postgrado de los cursos que aborden temas de los Objetivos del Milenio, el Pacto Global, la Carta de la Tierra, el Decenio de Naciones Unidas de la Educación para el Desarrollo Sustentable, entre otros | Q54: Anual | R54: Unidad | S54: Arquitectura: 3 Bellas Artes: 1 Ciencias Economicas: 2 Ciencias Basicas: 4 Ciencias Humanas 1 Quimica y farmacia:1 Ciencias Juridica:1 Educación: 2 Ingenieria: 1 Ciencias de la Salud: 4 Nota: Cada Facultad debe dos programas, indicando los cursos que en su sílabo aborden algunos de los temas relacionados ( No se incluyen Electiva de Contexto) Ej. Ing Ind reporta 15 cursos entonces 15/60=25% | T54: Nuevo gestionado durante la vigencia | U54: 22 | V54: 0 | W54: 20 | X54: =IFERROR(IF($T54=Lists!$S$2,SUM(FORMULACIÓN!U54:W54),IF(FORMULACIÓN!$T54=Lists!$S$3,SUM(FORMULACIÓN!V54:W54),IF(FORMULACIÓN!$T54=Lists!$S$4,AVERAGE(FORMULACIÓN!V54:W54),IF(FORMULACIÓN!$T54=Lists!$S$5,OFFSET(U54,0,COUNTA(V54:W54)),IF(FORMULACIÓN!$T54=Lists!$S$6,AVERAGE(V54:W54),""))))),"") -> 20 | Y54: =IF($R54=Lists!$R$3,TEXT(FORMULACIÓN!X54,"00,00%"),IF(FORMULACIÓN!X54=0,0,TEXT(FORMULACIÓN!X54,"##.###"))) -> 20
A55: =IF(C55<>"",+A54+1,"") -> 46 | B55: 2026 | C55: L1 - Formación Académica Integral | D55: =IFERROR(VLOOKUP(FORMULACIÓN!C55,Lists!$A$2:$B$6,2,FALSE),"") -> Garantizar la formación en educación superior de manera integral e inclusiva, con calidad, pertinencia, flexibilidad, interdisciplinariedad, competencias digitales, internacionalización, multilingüismo e interculturalidad, mediante procesos de autorregulación sostenible y con perspectiva regional. | E55: 1. Fortalecer la oferta académica de manera flexible e interdisciplinar con diversas modalidades, articulada a procesos de enseñanza y aprendizaje innovadores en sus diferentes niveles y campos de formación. | F55: M5 - Autoevaluación y acreditación Institucional y de programas académicos en el contexto nacional e internacional | G55: Incrementar en un 20% los niveles de desempeño globales en Pruebas Saber Pro de los programas académicos y 50 puntos en el puntaje de la institución. | H55: P3 - Gestión y mejoramiento curricular | I55: 0.05 | J55: Fortalecer actividades académicas direccionadas a lograr un mejor resultado en Saber Pro, TyT o su equivalente. | K55: 0.2 | L55: Jefe del Departamento Calidad Academica | M55: PDI | O55: Porcentaje de programas académicos con promedio del puntaje global superior y/o similar al grupo de referencia NBC (Núcleo Básico de Conocimiento) en Saber Pro, TyT o su equivalente por 3 años consecutivos | P55: (N° de programas académicos de pregrado con promedio del puntaje global superior y/o similar al grupo de referencia NBC durante los 3 últimos años/ total de programas académicos de pregrado que presentan las pruebas Saber Pro y TyT )* 100. | Q55: Anual | R55: Porcentaje | T55: Último valor reportado | U55: 0.63 | V55: 0 | W55: 0.65 | X55: =IFERROR(IF($T55=Lists!$S$2,SUM(FORMULACIÓN!U55:W55),IF(FORMULACIÓN!$T55=Lists!$S$3,SUM(FORMULACIÓN!V55:W55),IF(FORMULACIÓN!$T55=Lists!$S$4,AVERAGE(FORMULACIÓN!V55:W55),IF(FORMULACIÓN!$T55=Lists!$S$5,OFFSET(U55,0,COUNTA(V55:W55)),IF(FORMULACIÓN!$T55=Lists!$S$6,AVERAGE(V55:W55),""))))),"") -> 0.65 | Y55: =IF($R55=Lists!$R$3,TEXT(FORMULACIÓN!X55,"00,00%"),IF(FORMULACIÓN!X55=0,0,TEXT(FORMULACIÓN!X55,"##.###"))) -> 65,00%
A56: =IF(C56<>"",+A55+1,"") -> 47 | B56: 2026 | C56: L1 - Formación Académica Integral | D56: =IFERROR(VLOOKUP(FORMULACIÓN!C56,Lists!$A$2:$B$6,2,FALSE),"") -> Garantizar la formación en educación superior de manera integral e inclusiva, con calidad, pertinencia, flexibilidad, interdisciplinariedad, competencias digitales, internacionalización, multilingüismo e interculturalidad, mediante procesos de autorregulación sostenible y con perspectiva regional. | E56: 1. Fortalecer la oferta académica de manera flexible e interdisciplinar con diversas modalidades, articulada a procesos de enseñanza y aprendizaje innovadores en sus diferentes niveles y campos de formación. | F56: M5 - Autoevaluación y acreditación Institucional y de programas académicos en el contexto nacional e internacional | G56: Incrementar en un 20% los niveles de desempeño globales en Pruebas Saber Pro de los programas académicos y 50 puntos en el puntaje de la institución. | H56: P3 - Gestión y mejoramiento curricular | I56: 0.05 | J56: Fortalecer actividades académicas direccionadas a lograr un mejor resultado en Saber Pro, TyT o su equivalente. | K56: 0.2 | L56: Jefe del Departamento Calidad Academica | M56: PDI | O56: Puntaje global institucional en Pruebas Saber Pro | P56: Promedio de puntaje global de la institución en nivel superior y/o similar al de otras IES a nivel nacional durante los 3 últimos años | Q56: Anual | R56: Unidad | T56: Último valor reportado | U56: 165 | V56: 0 | W56: 165 | X56: =IFERROR(IF($T56=Lists!$S$2,SUM(FORMULACIÓN!U56:W56),IF(FORMULACIÓN!$T56=Lists!$S$3,SUM(FORMULACIÓN!V56:W56),IF(FORMULACIÓN!$T56=Lists!$S$4,AVERAGE(FORMULACIÓN!V56:W56),IF(FORMULACIÓN!$T56=Lists!$S$5,OFFSET(U56,0,COUNTA(V56:W56)),IF(FORMULACIÓN!$T56=Lists!$S$6,AVERAGE(V56:W56),""))))),"") -> 165 | Y56: =IF($R56=Lists!$R$3,TEXT(FORMULACIÓN!X56,"00,00%"),IF(FORMULACIÓN!X56=0,0,TEXT(FORMULACIÓN!X56,"##.###"))) -> 165
A57: =IF(C57<>"",+A56+1,"") -> 48 | B57: 2026 | C57: L1 - Formación Académica Integral | D57: =IFERROR(VLOOKUP(FORMULACIÓN!C57,Lists!$A$2:$B$6,2,FALSE),"") -> Garantizar la formación en educación superior de manera integral e inclusiva, con calidad, pertinencia, flexibilidad, interdisciplinariedad, competencias digitales, internacionalización, multilingüismo e interculturalidad, mediante procesos de autorregulación sostenible y con perspectiva regional. | E57: 5. Fortalecer Políticas curriculares con pedagogías adecuadas que atiendan al principio de calidad académica con enfoque inclusivo a través del desarrollo de las disciplinas y las profesiones, la integración de saberes, el fortalecimiento de competencias digitales, la solución de problemas y la inserción de los egresados al mercado laboral. | F57: M5 - Autoevaluación y acreditación Institucional y de programas académicos en el contexto nacional e internacional | G57: Implementar al menos un 70% de las estrategias académico administrativas dirigidas a la permanencia para alcanzar un 60% en la tasa graduación de los estudiantes. | H57: P3 - Gestión y mejoramiento curricular | I57: 0.05 | J57: Elaborar y socializar Informe por facultad del Estudio de impacto de las estrategias académico administrativas de acompañamiento para la permanencia y graduación. | K57: 0.2 | L57: Vicerrector De Docencia | M57: PDI | N57: X | O57: Impacto de las estrategias académico administrativas de acompañamiento al estudiante en su proceso formativo por facultad por año | P57: Informe por facultad del Estudio de impacto de las estrategias académico administrativas de acompañamiento para la permanencia y graduación elaborado y socializado | Q57: Anual | R57: Unidad | S57: Diseñar una matriz que baje a las Faculatdes para medir el impacto de los graduandos y matriculados | T57: Nuevo gestionado durante la vigencia | U57: 10 | V57: 0 | W57: 10 | X57: =IFERROR(IF($T57=Lists!$S$2,SUM(FORMULACIÓN!U57:W57),IF(FORMULACIÓN!$T57=Lists!$S$3,SUM(FORMULACIÓN!V57:W57),IF(FORMULACIÓN!$T57=Lists!$S$4,AVERAGE(FORMULACIÓN!V57:W57),IF(FORMULACIÓN!$T57=Lists!$S$5,OFFSET(U57,0,COUNTA(V57:W57)),IF(FORMULACIÓN!$T57=Lists!$S$6,AVERAGE(V57:W57),""))))),"") -> 10 | Y57: =IF($R57=Lists!$R$3,TEXT(FORMULACIÓN!X57,"00,00%"),IF(FORMULACIÓN!X57=0,0,TEXT(FORMULACIÓN!X57,"##.###"))) -> 10
A58: =IF(C58<>"",+A57+1,"") -> 49 | B58: 2026 | C58: L1 - Formación Académica Integral | D58: =IFERROR(VLOOKUP(FORMULACIÓN!C58,Lists!$A$2:$B$6,2,FALSE),"") -> Garantizar la formación en educación superior de manera integral e inclusiva, con calidad, pertinencia, flexibilidad, interdisciplinariedad, competencias digitales, internacionalización, multilingüismo e interculturalidad, mediante procesos de autorregulación sostenible y con perspectiva regional. | E58: 5. Fortalecer Políticas curriculares con pedagogías adecuadas que atiendan al principio de calidad académica con enfoque inclusivo a través del desarrollo de las disciplinas y las profesiones, la integración de saberes, el fortalecimiento de competencias digitales, la solución de problemas y la inserción de los egresados al mercado laboral. | F58: M5 - Autoevaluación y acreditación Institucional y de programas académicos en el contexto nacional e internacional | G58: Implementar al menos un 70% de las estrategias académico administrativas dirigidas a la permanencia para alcanzar un 60% en la tasa graduación de los estudiantes. | H58: P3 - Gestión y mejoramiento curricular | I58: 0.05 | J58: Gestionar la graduación oportuna. | K58: 0.2 | L58: Jefe del Departamento Calidad Academica | M58: PDI | O58: Tasa de graduación acumulada. | P58: (N° de estudiantes graduados acumulados de todas las cohortes hasta el periodo t / Total de estudiantes acumulados de primer ingreso de todas las cohortes hasta el periodo t) * 100. | Q58: Anual | R58: Porcentaje | T58: Último valor reportado | U58: 0.486 | V58: 0 | W58: 0.05 | X58: =IFERROR(IF($T58=Lists!$S$2,SUM(FORMULACIÓN!U58:W58),IF(FORMULACIÓN!$T58=Lists!$S$3,SUM(FORMULACIÓN!V58:W58),IF(FORMULACIÓN!$T58=Lists!$S$4,AVERAGE(FORMULACIÓN!V58:W58),IF(FORMULACIÓN!$T58=Lists!$S$5,OFFSET(U58,0,COUNTA(V58:W58)),IF(FORMULACIÓN!$T58=Lists!$S$6,AVERAGE(V58:W58),""))))),"") -> 0.05 | Y58: =IF($R58=Lists!$R$3,TEXT(FORMULACIÓN!X58,"00,00%"),IF(FORMULACIÓN!X58=0,0,TEXT(FORMULACIÓN!X58,"##.###"))) -> 05,00%
A59: =IF(C59<>"",+A58+1,"") -> 50 | B59: 2026 | C59: L1 - Formación Académica Integral | D59: =IFERROR(VLOOKUP(FORMULACIÓN!C59,Lists!$A$2:$B$6,2,FALSE),"") -> Garantizar la formación en educación superior de manera integral e inclusiva, con calidad, pertinencia, flexibilidad, interdisciplinariedad, competencias digitales, internacionalización, multilingüismo e interculturalidad, mediante procesos de autorregulación sostenible y con perspectiva regional. | E59: 5. Fortalecer Políticas curriculares con pedagogías adecuadas que atiendan al principio de calidad académica con enfoque inclusivo a través del desarrollo de las disciplinas y las profesiones, la integración de saberes, el fortalecimiento de competencias digitales, la solución de problemas y la inserción de los egresados al mercado laboral. | F59: M5 - Autoevaluación y acreditación Institucional y de programas académicos en el contexto nacional e internacional | G59: realizar al menos 2 concursos públicos de mérito con resultados de 80% de efectividad. | H59: P4 - Fortalecimiento de las capacidades del capital humano docente | I59: 0.06 | J59: Evaluar la efectividad del concurso docente | K59: 0.2 | L59: Vicerrector De Docencia | M59: PDI | O59: Concurso docente público de méritos | P59: N° de concursos docente público de méritos | Q59: Anual | R59: Unidad | T59: Nuevo gestionado durante la vigencia | U59: 0 | V59: 0 | W59: 1 | X59: =IFERROR(IF($T59=Lists!$S$2,SUM(FORMULACIÓN!U59:W59),IF(FORMULACIÓN!$T59=Lists!$S$3,SUM(FORMULACIÓN!V59:W59),IF(FORMULACIÓN!$T59=Lists!$S$4,AVERAGE(FORMULACIÓN!V59:W59),IF(FORMULACIÓN!$T59=Lists!$S$5,OFFSET(U59,0,COUNTA(V59:W59)),IF(FORMULACIÓN!$T59=Lists!$S$6,AVERAGE(V59:W59),""))))),"") -> 1 | Y59: =IF($R59=Lists!$R$3,TEXT(FORMULACIÓN!X59,"00,00%"),IF(FORMULACIÓN!X59=0,0,TEXT(FORMULACIÓN!X59,"##.###"))) -> 1
A60: =IF(C60<>"",+A59+1,"") -> 51 | B60: 2026 | C60: L1 - Formación Académica Integral | D60: =IFERROR(VLOOKUP(FORMULACIÓN!C60,Lists!$A$2:$B$6,2,FALSE),"") -> Garantizar la formación en educación superior de manera integral e inclusiva, con calidad, pertinencia, flexibilidad, interdisciplinariedad, competencias digitales, internacionalización, multilingüismo e interculturalidad, mediante procesos de autorregulación sostenible y con perspectiva regional. | E60: 7. Fortalecer académica y administrativamente los programas para lograr un mayor reconocimiento regional y la acreditación nacional e internacional. | F60: M5 - Autoevaluación y acreditación Institucional y de programas académicos en el contexto nacional e internacional | G60: realizar al menos 2 concursos públicos de mérito con resultados de 80% de efectividad. | H60: P4 - Fortalecimiento de las capacidades del capital humano docente | I60: 0.06 | J60: Fortalecer la planta docente | K60: 0.2 | L60: Vicerrector De Docencia | M60: PDI | O60: Efectividad del concurso docente | P60: N° de plazas cubiertas / total de plazas ofertadas* 100 | Q60: Anual | R60: Porcentaje | S60: Se ofertaran 100 plazas, para el concurso 2026 de 247 que se requieren | T60: Último valor reportado | U60: 0.8 | V60: 0 | W60: 0.8 | X60: =IFERROR(IF($T60=Lists!$S$2,SUM(FORMULACIÓN!U60:W60),IF(FORMULACIÓN!$T60=Lists!$S$3,SUM(FORMULACIÓN!V60:W60),IF(FORMULACIÓN!$T60=Lists!$S$4,AVERAGE(FORMULACIÓN!V60:W60),IF(FORMULACIÓN!$T60=Lists!$S$5,OFFSET(U60,0,COUNTA(V60:W60)),IF(FORMULACIÓN!$T60=Lists!$S$6,AVERAGE(V60:W60),""))))),"") -> 0.8 | Y60: =IF($R60=Lists!$R$3,TEXT(FORMULACIÓN!X60,"00,00%"),IF(FORMULACIÓN!X60=0,0,TEXT(FORMULACIÓN!X60,"##.###"))) -> 80,00%
A61: =IF(C61<>"",+A60+1,"") -> 52 | B61: 2026 | C61: L1 - Formación Académica Integral | D61: =IFERROR(VLOOKUP(FORMULACIÓN!C61,Lists!$A$2:$B$6,2,FALSE),"") -> Garantizar la formación en educación superior de manera integral e inclusiva, con calidad, pertinencia, flexibilidad, interdisciplinariedad, competencias digitales, internacionalización, multilingüismo e interculturalidad, mediante procesos de autorregulación sostenible y con perspectiva regional. | E61: 7. Fortalecer académica y administrativamente los programas para lograr un mayor reconocimiento regional y la acreditación nacional e internacional. | F61: M5 - Autoevaluación y acreditación Institucional y de programas académicos en el contexto nacional e internacional | G61: Alcanzar el 60% de nivel de formación doctoral y un 40% de maestría de la planta docente (carrera profesoral). | H61: P4 - Fortalecimiento de las capacidades del capital humano docente | I61: 0.06 | J61: Fortalecer la planta docente | K61: 0.2 | L61: Vicerrector De Docencia | M61: PDI | O61: Porcentaje de docentes de carrera profesoral con nivel de formación de doctorado. | P61: N° de docentes de carrera profesoral con nivel de formación de doctorado / total de docentes de carrera profesoral * 100 | Q61: Anual | R61: Porcentaje | T61: Último valor reportado | U61: 0.4 | V61: 0 | W61: 0.4 | X61: =IFERROR(IF($T61=Lists!$S$2,SUM(FORMULACIÓN!U61:W61),IF(FORMULACIÓN!$T61=Lists!$S$3,SUM(FORMULACIÓN!V61:W61),IF(FORMULACIÓN!$T61=Lists!$S$4,AVERAGE(FORMULACIÓN!V61:W61),IF(FORMULACIÓN!$T61=Lists!$S$5,OFFSET(U61,0,COUNTA(V61:W61)),IF(FORMULACIÓN!$T61=Lists!$S$6,AVERAGE(V61:W61),""))))),"") -> 0.4 | Y61: =IF($R61=Lists!$R$3,TEXT(FORMULACIÓN!X61,"00,00%"),IF(FORMULACIÓN!X61=0,0,TEXT(FORMULACIÓN!X61,"##.###"))) -> 40,00%
A62: =IF(C62<>"",+A61+1,"") -> 53 | B62: 2026 | C62: L1 - Formación Académica Integral | D62: =IFERROR(VLOOKUP(FORMULACIÓN!C62,Lists!$A$2:$B$6,2,FALSE),"") -> Garantizar la formación en educación superior de manera integral e inclusiva, con calidad, pertinencia, flexibilidad, interdisciplinariedad, competencias digitales, internacionalización, multilingüismo e interculturalidad, mediante procesos de autorregulación sostenible y con perspectiva regional. | E62: 6. Integrar los procesos académicos y administrativos que conlleve de manera funcional a un orden adecuado de interacciones, soportadas en tecnologías de la información, de acuerdo a la normatividad vigente. | F62: M5 - Autoevaluación y acreditación Institucional y de programas académicos en el contexto nacional e internacional | G62: Alcanzar el 60% de nivel de formación doctoral y un 40% de maestría de la planta docente (carrera profesoral). | H62: P4 - Fortalecimiento de las capacidades del capital humano docente | I62: 0.06 | J62: Docentes certificados mediante las actividades de capacitación o cualificación docente por año | K62: 0.2 | L62: Vicerrector De Docencia | M62: PDI | O62: Porcentaje de docentes de carrera profesoral con nivel de formación de maestría. | P62: N° de docentes de carrera profesoral con nivel de formación de maestría / total de docentes de carrera profesoral * 100 | Q62: Anual | R62: Porcentaje | T62: Nuevo gestionado durante la vigencia | U62: 0.4 | V62: 0 | W62: 0.4 | X62: =IFERROR(IF($T62=Lists!$S$2,SUM(FORMULACIÓN!U62:W62),IF(FORMULACIÓN!$T62=Lists!$S$3,SUM(FORMULACIÓN!V62:W62),IF(FORMULACIÓN!$T62=Lists!$S$4,AVERAGE(FORMULACIÓN!V62:W62),IF(FORMULACIÓN!$T62=Lists!$S$5,OFFSET(U62,0,COUNTA(V62:W62)),IF(FORMULACIÓN!$T62=Lists!$S$6,AVERAGE(V62:W62),""))))),"") -> 0.4 | Y62: =IF($R62=Lists!$R$3,TEXT(FORMULACIÓN!X62,"00,00%"),IF(FORMULACIÓN!X62=0,0,TEXT(FORMULACIÓN!X62,"##.###"))) -> 40,00%
A63: =IF(C63<>"",+A62+1,"") -> 54 | B63: 2026 | C63: L1 - Formación Académica Integral | D63: =IFERROR(VLOOKUP(FORMULACIÓN!C63,Lists!$A$2:$B$6,2,FALSE),"") -> Garantizar la formación en educación superior de manera integral e inclusiva, con calidad, pertinencia, flexibilidad, interdisciplinariedad, competencias digitales, internacionalización, multilingüismo e interculturalidad, mediante procesos de autorregulación sostenible y con perspectiva regional. | E63: 7. Fortalecer académica y administrativamente los programas para lograr un mayor reconocimiento regional y la acreditación nacional e internacional. | F63: M5 - Autoevaluación y acreditación Institucional y de programas académicos en el contexto nacional e internacional | G63: Alcanzar la certificación de al menos 900 docentes mediante las actividades de capacitación o cualificación docente. | H63: P4 - Fortalecimiento de las capacidades del capital humano docente | I63: 0.06 | J63: Fortalecer la inducción docente, y promover diálogos intergeneracionales y encuentros de experiencia, como actividad integradora a la carrera profesoral para docentes que ingresan por primera vez a la universidad. | K63: 0.2 | L63: Vicerrector De Docencia | M63: PR | N63: X | O63: Docentes certificados mediante las actividades de capacitación o cualificación docente por año | P63: N° de docentes certificados como resultado de las actividades de capacitación o cualificación docente realizadas al año | Q63: Semestral | R63: Unidad | S63: Arquitectura: 35 Bellas Artes: 30 Ciencias Economicas: 60 Ciencias Basicas:80 Ciencias Humanas:80 Ciencias de la salud:30 Quimica y farmacia:20 Ciencias Juridica:50 Educación:100 Ingenieria:60 los docentes certificados no no se repiten de un semestre a otro, eso quiere decir que un docente solo contaria una vez por año | T63: Nuevo gestionado durante la vigencia | U63: 837 | V63: 0 | W63: 545 | X63: =IFERROR(IF($T63=Lists!$S$2,SUM(FORMULACIÓN!U63:W63),IF(FORMULACIÓN!$T63=Lists!$S$3,SUM(FORMULACIÓN!V63:W63),IF(FORMULACIÓN!$T63=Lists!$S$4,AVERAGE(FORMULACIÓN!V63:W63),IF(FORMULACIÓN!$T63=Lists!$S$5,OFFSET(U63,0,COUNTA(V63:W63)),IF(FORMULACIÓN!$T63=Lists!$S$6,AVERAGE(V63:W63),""))))),"") -> 545 | Y63: =IF($R63=Lists!$R$3,TEXT(FORMULACIÓN!X63,"00,00%"),IF(FORMULACIÓN!X63=0,0,TEXT(FORMULACIÓN!X63,"##.###"))) -> 545
A64: =IF(C64<>"",+A63+1,"") -> 55 | B64: 2026 | C64: L2 - Investigación y Redes de conocimiento para el desarrollo de la sociedad | D64: =IFERROR(VLOOKUP(FORMULACIÓN!C64,Lists!$A$2:$B$6,2,FALSE),"") -> Fortalecer y consolidar los procesos de investigación, creación e innovación al servicio del progreso científico, tecnológico, ambiental, cultural, social y humano, en el contexto regional, nacional e internacional. | E64: 2. Actualizar y desarrollar la agenda de investigación-innovación-creación institucional, en torno con el contexto y tendencias globales. | F64: M1 - Creación o investigación creación. | G64: Fortalecer y visibilizar el impacto de la creación e investigación para las industrias creativas y culturales con miras a disminuir la brecha en la generación de conocimiento en el sector de las artes y el patrimonio cultural, con 90 proyectos que aprobados en convocatorias internas y/o externas, asimismo categorizar 3 grupo en A1, 2 grupos en A, 3 grupos en B | H64: P1 - Desarrollo de las artes, la creación y la investigación creación | I64: 0.15 | J64: Desarrollar convocatorias internas para fomentar los proyectos de creación o investigación creación | K64: 0.35 | L64: Jefe del Departamento de Fomento y Apoyo a la Investigación | M64: PDI | O64: Participación de proyectos de creación o investigación creación en convocatorias internas y externas | P64: N° de proyectos de creación o investigación creación aprobados mediante convocatorias internas | Q64: Anual | R64: Unidad | T64: Nuevo gestionado durante la vigencia | U64: 9 | V64: 0 | W64: 6 | X64: =IFERROR(IF($T64=Lists!$S$2,SUM(FORMULACIÓN!U64:W64),IF(FORMULACIÓN!$T64=Lists!$S$3,SUM(FORMULACIÓN!V64:W64),IF(FORMULACIÓN!$T64=Lists!$S$4,AVERAGE(FORMULACIÓN!V64:W64),IF(FORMULACIÓN!$T64=Lists!$S$5,OFFSET(U64,0,COUNTA(V64:W64)),IF(FORMULACIÓN!$T64=Lists!$S$6,AVERAGE(V64:W64),""))))),"") -> 6 | Y64: =IF($R64=Lists!$R$3,TEXT(FORMULACIÓN!X64,"00,00%"),IF(FORMULACIÓN!X64=0,0,TEXT(FORMULACIÓN!X64,"##.###"))) -> 6
A65: =IF(C65<>"",+A64+1,"") -> 56 | B65: 2026 | C65: L2 - Investigación y Redes de conocimiento para el desarrollo de la sociedad | D65: =IFERROR(VLOOKUP(FORMULACIÓN!C65,Lists!$A$2:$B$6,2,FALSE),"") -> Fortalecer y consolidar los procesos de investigación, creación e innovación al servicio del progreso científico, tecnológico, ambiental, cultural, social y humano, en el contexto regional, nacional e internacional. | E65: 2. Actualizar y desarrollar la agenda de investigación-innovación-creación institucional, en torno con el contexto y tendencias globales. | F65: M1 - Creación o investigación creación. | G65: Fortalecer y visibilizar el impacto de la creación e investigación para las industrias creativas y culturales con miras a disminuir la brecha en la generación de conocimiento en el sector de las artes y el patrimonio cultural, con 90 proyectos que aprobados en convocatorias internas y/o externas, asimismo categorizar 3 grupo en A1, 2 grupos en A, 3 grupos en B | H65: P1 - Desarrollo de las artes, la creación y la investigación creación | I65: 0.15 | J65: Promover la participación en convocatorias externas para proyectos de creación o investigación creación. | K65: 0.35 | L65: Jefe del Departamento de Fomento y Apoyo a la Investigación | M65: PDI | N65: X | O65: Participación de proyectos de creación o investigación creación en convocatorias internas y externas | P65: N° de proyectos de creación o investigación creación aprobados mediante convocatorias externas | Q65: Anual | R65: Unidad | T65: Nuevo gestionado durante la vigencia | U65: 15 | V65: 0 | W65: 3 | X65: =IFERROR(IF($T65=Lists!$S$2,SUM(FORMULACIÓN!U65:W65),IF(FORMULACIÓN!$T65=Lists!$S$3,SUM(FORMULACIÓN!V65:W65),IF(FORMULACIÓN!$T65=Lists!$S$4,AVERAGE(FORMULACIÓN!V65:W65),IF(FORMULACIÓN!$T65=Lists!$S$5,OFFSET(U65,0,COUNTA(V65:W65)),IF(FORMULACIÓN!$T65=Lists!$S$6,AVERAGE(V65:W65),""))))),"") -> 3 | Y65: =IF($R65=Lists!$R$3,TEXT(FORMULACIÓN!X65,"00,00%"),IF(FORMULACIÓN!X65=0,0,TEXT(FORMULACIÓN!X65,"##.###"))) -> 3
A66: =IF(C66<>"",+A65+1,"") -> 57 | B66: 2026 | C66: L2 - Investigación y Redes de conocimiento para el desarrollo de la sociedad | D66: =IFERROR(VLOOKUP(FORMULACIÓN!C66,Lists!$A$2:$B$6,2,FALSE),"") -> Fortalecer y consolidar los procesos de investigación, creación e innovación al servicio del progreso científico, tecnológico, ambiental, cultural, social y humano, en el contexto regional, nacional e internacional. | E66: 1. Fortalecer y visibilizar la producción científica, humanística, cultural y creativa. | F66: M1 - Creación o investigación creación. | G66: Fortalecer y visibilizar el impacto de la creación e investigación para las industrias creativas y culturales con miras a disminuir la brecha en la generación de conocimiento en el sector de las artes y el patrimonio cultural, con 90 proyectos que aprobados en convocatorias internas y/o externas, asimismo categorizar 3 grupo en A1, 2 grupos en A, 3 grupos en B | H66: P1 - Desarrollo de las artes, la creación y la investigación creación | I66: 0.15 | J66: Impulsar los productos de creación en categoría A y B | K66: 0.2 | L66: Jefe del Departamento de Fomento y Apoyo a la Investigación | M66: PA | O66: Participación en proyectos de creación o investigación creación solidaria | P66: Nº de productos derivados de proyectos de investigación solidaria | Q66: Anual | R66: Unidad | T66: Nuevo gestionado durante la vigencia | U66: 0 | V66: 0 | W66: 10 | X66: =IFERROR(IF($T66=Lists!$S$2,SUM(FORMULACIÓN!U66:W66),IF(FORMULACIÓN!$T66=Lists!$S$3,SUM(FORMULACIÓN!V66:W66),IF(FORMULACIÓN!$T66=Lists!$S$4,AVERAGE(FORMULACIÓN!V66:W66),IF(FORMULACIÓN!$T66=Lists!$S$5,OFFSET(U66,0,COUNTA(V66:W66)),IF(FORMULACIÓN!$T66=Lists!$S$6,AVERAGE(V66:W66),""))))),"") -> 10 | Y66: =IF($R66=Lists!$R$3,TEXT(FORMULACIÓN!X66,"00,00%"),IF(FORMULACIÓN!X66=0,0,TEXT(FORMULACIÓN!X66,"##.###"))) -> 10
A67: =IF(C67<>"",+A66+1,"") -> 58 | B67: 2026 | C67: L2 - Investigación y Redes de conocimiento para el desarrollo de la sociedad | D67: =IFERROR(VLOOKUP(FORMULACIÓN!C67,Lists!$A$2:$B$6,2,FALSE),"") -> Fortalecer y consolidar los procesos de investigación, creación e innovación al servicio del progreso científico, tecnológico, ambiental, cultural, social y humano, en el contexto regional, nacional e internacional. | E67: 1. Fortalecer y visibilizar la producción científica, humanística, cultural y creativa. | F67: M1 - Creación o investigación creación. | G67: Fortalecer y visibilizar el impacto de la creación e investigación para las industrias creativas y culturales con miras a disminuir la brecha en la generación de conocimiento en el sector de las artes y el patrimonio cultural, con 90 proyectos que aprobados en convocatorias internas y/o externas, asimismo categorizar 3 grupo en A1, 2 grupos en A, 3 grupos en B | H67: P1 - Desarrollo de las artes, la creación y la investigación creación | I67: 0.15 | J67: Fomentar la categorización en A1, A Y B de los grupos de investigación en industrias creativas y culturales | K67: 0.1 | L67: Jefe del Departamento de Fomento y Apoyo a la Investigación | M67: PDI | N67: X | O67: Productos de investigación creación | P67: N° de productos Tipo TOP o Tipo A, de las tipologías de generación de nuevo conocimiento o desarrollo tecnológico de innovación | Q67: Anual | R67: Unidad | T67: Nuevo gestionado durante la vigencia | U67: 25 | V67: 0 | W67: 12 | X67: =IFERROR(IF($T67=Lists!$S$2,SUM(FORMULACIÓN!U67:W67),IF(FORMULACIÓN!$T67=Lists!$S$3,SUM(FORMULACIÓN!V67:W67),IF(FORMULACIÓN!$T67=Lists!$S$4,AVERAGE(FORMULACIÓN!V67:W67),IF(FORMULACIÓN!$T67=Lists!$S$5,OFFSET(U67,0,COUNTA(V67:W67)),IF(FORMULACIÓN!$T67=Lists!$S$6,AVERAGE(V67:W67),""))))),"") -> 12 | Y67: =IF($R67=Lists!$R$3,TEXT(FORMULACIÓN!X67,"00,00%"),IF(FORMULACIÓN!X67=0,0,TEXT(FORMULACIÓN!X67,"##.###"))) -> 12
A68: =IF(C68<>"",+A67+1,"") -> 59 | B68: 2026 | C68: L2 - Investigación y Redes de conocimiento para el desarrollo de la sociedad | D68: =IFERROR(VLOOKUP(FORMULACIÓN!C68,Lists!$A$2:$B$6,2,FALSE),"") -> Fortalecer y consolidar los procesos de investigación, creación e innovación al servicio del progreso científico, tecnológico, ambiental, cultural, social y humano, en el contexto regional, nacional e internacional. | E68: 4. Impulsar la interacción entre los grupos de investigación de la Universidad y el Sistema Nacional de Ciencia, Tecnología e Innovación (SNCTI) y sus homólogos internacionales, para la conformación de redes de conocimiento y cooperación, que faciliten el desarrollo investigativo y tecnológico. | F68: M1 - Creación o investigación creación. | G68: Consolidar e implementar el laboratorio de investigación creación para las áreas artísticas logrando 10 convenios interinstitucionales y 18 productos articulados en redes | H68: P2 - Laboratorio de investigación creación | I68: 0.15 | J68: Promover el desarrollo de proyectos en redes colaborativas. | K68: 0.5 | L68: Jefe del Departamento de Fomento y Apoyo a la Investigación | M68: PDI | O68: Convenios interinstitucionales y productos derivados del trabajo en redes | P68: N° de convenios interinstitucionales aprobados en investigación + creación | Q68: Anual | R68: Unidad | T68: Nuevo gestionado durante la vigencia | U68: 0 | V68: 0 | W68: 2 | X68: =IFERROR(IF($T68=Lists!$S$2,SUM(FORMULACIÓN!U68:W68),IF(FORMULACIÓN!$T68=Lists!$S$3,SUM(FORMULACIÓN!V68:W68),IF(FORMULACIÓN!$T68=Lists!$S$4,AVERAGE(FORMULACIÓN!V68:W68),IF(FORMULACIÓN!$T68=Lists!$S$5,OFFSET(U68,0,COUNTA(V68:W68)),IF(FORMULACIÓN!$T68=Lists!$S$6,AVERAGE(V68:W68),""))))),"") -> 2 | Y68: =IF($R68=Lists!$R$3,TEXT(FORMULACIÓN!X68,"00,00%"),IF(FORMULACIÓN!X68=0,0,TEXT(FORMULACIÓN!X68,"##.###"))) -> 2
A69: =IF(C69<>"",+A68+1,"") -> 60 | B69: 2026 | C69: L2 - Investigación y Redes de conocimiento para el desarrollo de la sociedad | D69: =IFERROR(VLOOKUP(FORMULACIÓN!C69,Lists!$A$2:$B$6,2,FALSE),"") -> Fortalecer y consolidar los procesos de investigación, creación e innovación al servicio del progreso científico, tecnológico, ambiental, cultural, social y humano, en el contexto regional, nacional e internacional. | E69: 4. Impulsar la interacción entre los grupos de investigación de la Universidad y el Sistema Nacional de Ciencia, Tecnología e Innovación (SNCTI) y sus homólogos internacionales, para la conformación de redes de conocimiento y cooperación, que faciliten el desarrollo investigativo y tecnológico. | F69: M1 - Creación o investigación creación. | G69: Consolidar e implementar el laboratorio de investigación creación para las áreas artísticas logrando 10 convenios interinstitucionales y 18 productos articulados en redes | H69: P2 - Laboratorio de investigación creación | I69: 0.15 | J69: Promover el desarrollo de proyectos en redes colaborativas. | K69: 0.5 | L69: Jefe del Departamento de Fomento y Apoyo a la Investigación | M69: PDI - PA | N69: X | O69: Convenios interinstitucionales y productos derivados del trabajo en redes | P69: N° de productos de investigación + creación derivados del trabajo en redes | Q69: Anual | R69: Unidad | T69: Nuevo gestionado durante la vigencia | U69: 11 | V69: 0 | W69: 8 | X69: =IFERROR(IF($T69=Lists!$S$2,SUM(FORMULACIÓN!U69:W69),IF(FORMULACIÓN!$T69=Lists!$S$3,SUM(FORMULACIÓN!V69:W69),IF(FORMULACIÓN!$T69=Lists!$S$4,AVERAGE(FORMULACIÓN!V69:W69),IF(FORMULACIÓN!$T69=Lists!$S$5,OFFSET(U69,0,COUNTA(V69:W69)),IF(FORMULACIÓN!$T69=Lists!$S$6,AVERAGE(V69:W69),""))))),"") -> 8 | Y69: =IF($R69=Lists!$R$3,TEXT(FORMULACIÓN!X69,"00,00%"),IF(FORMULACIÓN!X69=0,0,TEXT(FORMULACIÓN!X69,"##.###"))) -> 8
A70: =IF(C70<>"",+A69+1,"") -> 61 | B70: 2026 | C70: L2 - Investigación y Redes de conocimiento para el desarrollo de la sociedad | D70: =IFERROR(VLOOKUP(FORMULACIÓN!C70,Lists!$A$2:$B$6,2,FALSE),"") -> Fortalecer y consolidar los procesos de investigación, creación e innovación al servicio del progreso científico, tecnológico, ambiental, cultural, social y humano, en el contexto regional, nacional e internacional. | E70: 1. Fortalecer y visibilizar la producción científica, humanística, cultural y creativa. | F70: M2 - Investigación y desarrollo científico. | G70: Incrementar, apropiar y divulgar la generación de nuevo conocimiento de calidad e impacto con 391 publicaciones indexadas en Publindex, 1400 en Wos y/o Scopus, 100 libros publicados, 5 revistas científicas con sello editorial Uniatlántico. | H70: P1 - Desarrollo de la investigación básica y aplicada con impacto en aspectos sociales, políticos, culturales, económicos y/o tecnológicos en los contextos regional, nacional e internacional | I70: 0.27 | J70: Impulsar la publicación de artículos en revistas indexadas en Publindex | K70: 0.1 | L70: Jefe del Departamento de Fomento y Apoyo a la Investigación | M70: PDI | N70: X | O70: Publicación de artículos en revistas indexadas en bases de datos de alto impacto | P70: N° de artículos publicados en revistas nacionales indexedas en Publindex | Q70: Anual | R70: Unidad | S70: Categoria A1, A2, B y C | T70: Nuevo gestionado durante la vigencia | U70: 28 | V70: 0 | W70: 51 | X70: =IFERROR(IF($T70=Lists!$S$2,SUM(FORMULACIÓN!U70:W70),IF(FORMULACIÓN!$T70=Lists!$S$3,SUM(FORMULACIÓN!V70:W70),IF(FORMULACIÓN!$T70=Lists!$S$4,AVERAGE(FORMULACIÓN!V70:W70),IF(FORMULACIÓN!$T70=Lists!$S$5,OFFSET(U70,0,COUNTA(V70:W70)),IF(FORMULACIÓN!$T70=Lists!$S$6,AVERAGE(V70:W70),""))))),"") -> 51 | Y70: =IF($R70=Lists!$R$3,TEXT(FORMULACIÓN!X70,"00,00%"),IF(FORMULACIÓN!X70=0,0,TEXT(FORMULACIÓN!X70,"##.###"))) -> 51
A71: =IF(C71<>"",+A70+1,"") -> 62 | B71: 2026 | C71: L2 - Investigación y Redes de conocimiento para el desarrollo de la sociedad | D71: =IFERROR(VLOOKUP(FORMULACIÓN!C71,Lists!$A$2:$B$6,2,FALSE),"") -> Fortalecer y consolidar los procesos de investigación, creación e innovación al servicio del progreso científico, tecnológico, ambiental, cultural, social y humano, en el contexto regional, nacional e internacional. | E71: 1. Fortalecer y visibilizar la producción científica, humanística, cultural y creativa. | F71: M2 - Investigación y desarrollo científico. | G71: Incrementar, apropiar y divulgar la generación de nuevo conocimiento de calidad e impacto con 391 publicaciones indexadas en Publindex, 1400 en Wos y/o Scopus, 100 libros publicados, 5 revistas científicas con sello editorial Uniatlántico. | H71: P1 - Desarrollo de la investigación básica y aplicada con impacto en aspectos sociales, políticos, culturales, económicos y/o tecnológicos en los contextos regional, nacional e internacional | I71: 0.27 | J71: Impulsar la publicación de artículos en revistas indexadas en Wos y/o Scopus | K71: 0.1 | L71: Jefe del Departamento de Fomento y Apoyo a la Investigación | M71: PDI | N71: X | O71: Publicación de artículos en revistas indexadas en bases de datos de alto impacto | P71: N° de artículos publicados en revistas indexadas en Wos y/o Scopus | Q71: Anual | R71: Unidad | S71: Revistas internacionales Internacionales | T71: Nuevo gestionado durante la vigencia | U71: 150 | V71: 0 | W71: 128 | X71: =IFERROR(IF($T71=Lists!$S$2,SUM(FORMULACIÓN!U71:W71),IF(FORMULACIÓN!$T71=Lists!$S$3,SUM(FORMULACIÓN!V71:W71),IF(FORMULACIÓN!$T71=Lists!$S$4,AVERAGE(FORMULACIÓN!V71:W71),IF(FORMULACIÓN!$T71=Lists!$S$5,OFFSET(U71,0,COUNTA(V71:W71)),IF(FORMULACIÓN!$T71=Lists!$S$6,AVERAGE(V71:W71),""))))),"") -> 128 | Y71: =IF($R71=Lists!$R$3,TEXT(FORMULACIÓN!X71,"00,00%"),IF(FORMULACIÓN!X71=0,0,TEXT(FORMULACIÓN!X71,"##.###"))) -> 128
A72: =IF(C72<>"",+A71+1,"") -> 63 | B72: 2026 | C72: L2 - Investigación y Redes de conocimiento para el desarrollo de la sociedad | D72: =IFERROR(VLOOKUP(FORMULACIÓN!C72,Lists!$A$2:$B$6,2,FALSE),"") -> Fortalecer y consolidar los procesos de investigación, creación e innovación al servicio del progreso científico, tecnológico, ambiental, cultural, social y humano, en el contexto regional, nacional e internacional. | E72: 1. Fortalecer y visibilizar la producción científica, humanística, cultural y creativa. | F72: M2 - Investigación y desarrollo científico. | G72: Incrementar, apropiar y divulgar la generación de nuevo conocimiento de calidad e impacto con 391 publicaciones indexadas en Publindex, 1400 en Wos y/o Scopus, 100 libros publicados, 5 revistas científicas con sello editorial Uniatlántico. | H72: P1 - Desarrollo de la investigación básica y aplicada con impacto en aspectos sociales, políticos, culturales, económicos y/o tecnológicos en los contextos regional, nacional e internacional | I72: 0.27 | J72: Impulsar la publicación de los libros | K72: 0.1 | L72: Jefe del Departamento de Fomento y Apoyo a la Investigación | M72: PDI | N72: X | O72: Publicación de artículos en revistas indexadas en bases de datos de alto impacto | P72: N° de libros publicados resultado de proyectos de investigación | Q72: Anual | R72: Unidad | S72: Productos de Investigacion de un proyecto radicado en la editorial de la UA | T72: Nuevo gestionado durante la vigencia | U72: 32 | V72: 0 | W72: 23 | X72: =IFERROR(IF($T72=Lists!$S$2,SUM(FORMULACIÓN!U72:W72),IF(FORMULACIÓN!$T72=Lists!$S$3,SUM(FORMULACIÓN!V72:W72),IF(FORMULACIÓN!$T72=Lists!$S$4,AVERAGE(FORMULACIÓN!V72:W72),IF(FORMULACIÓN!$T72=Lists!$S$5,OFFSET(U72,0,COUNTA(V72:W72)),IF(FORMULACIÓN!$T72=Lists!$S$6,AVERAGE(V72:W72),""))))),"") -> 23 | Y72: =IF($R72=Lists!$R$3,TEXT(FORMULACIÓN!X72,"00,00%"),IF(FORMULACIÓN!X72=0,0,TEXT(FORMULACIÓN!X72,"##.###"))) -> 23
A73: =IF(C73<>"",+A72+1,"") -> 64 | B73: 2026 | C73: L2 - Investigación y Redes de conocimiento para el desarrollo de la sociedad | D73: =IFERROR(VLOOKUP(FORMULACIÓN!C73,Lists!$A$2:$B$6,2,FALSE),"") -> Fortalecer y consolidar los procesos de investigación, creación e innovación al servicio del progreso científico, tecnológico, ambiental, cultural, social y humano, en el contexto regional, nacional e internacional. | E73: 5. Armonizar los procesos administrativos y recursos tecnológicos de manera integral y efectiva en función de la misión investigativa. | F73: M2 - Investigación y desarrollo científico. | G73: Incrementar, apropiar y divulgar la generación de nuevo conocimiento de calidad e impacto con 391 publicaciones indexadas en Publindex, 1400 en Wos y/o Scopus, 100 libros publicados, 5 revistas científicas con sello editorial Uniatlántico. | H73: P1 - Desarrollo de la investigación básica y aplicada con impacto en aspectos sociales, políticos, culturales, económicos y/o tecnológicos en los contextos regional, nacional e internacional | I73: 0.27 | J73: Fortalecer las revistas del sello editorial Uniatlántico | K73: 0.1 | L73: Jefe del Departamento de Fomento y Apoyo a la Investigación | M73: PDI - PA | O73: Revistas científicas editadas bajo el sello Editorial Uniatlántico | P73: N° de artículos traducidos de las revistas editadas bajo el sello Editorial Uniatlántico | Q73: Anual | R73: Unidad | T73: Nuevo gestionado durante la vigencia | U73: 20 | V73: 0 | W73: 10 | X73: =IFERROR(IF($T73=Lists!$S$2,SUM(FORMULACIÓN!U73:W73),IF(FORMULACIÓN!$T73=Lists!$S$3,SUM(FORMULACIÓN!V73:W73),IF(FORMULACIÓN!$T73=Lists!$S$4,AVERAGE(FORMULACIÓN!V73:W73),IF(FORMULACIÓN!$T73=Lists!$S$5,OFFSET(U73,0,COUNTA(V73:W73)),IF(FORMULACIÓN!$T73=Lists!$S$6,AVERAGE(V73:W73),""))))),"") -> 10 | Y73: =IF($R73=Lists!$R$3,TEXT(FORMULACIÓN!X73,"00,00%"),IF(FORMULACIÓN!X73=0,0,TEXT(FORMULACIÓN!X73,"##.###"))) -> 10
A74: =IF(C74<>"",+A73+1,"") -> 65 | B74: 2026 | C74: L2 - Investigación y Redes de conocimiento para el desarrollo de la sociedad | D74: =IFERROR(VLOOKUP(FORMULACIÓN!C74,Lists!$A$2:$B$6,2,FALSE),"") -> Fortalecer y consolidar los procesos de investigación, creación e innovación al servicio del progreso científico, tecnológico, ambiental, cultural, social y humano, en el contexto regional, nacional e internacional. | E74: 5. Armonizar los procesos administrativos y recursos tecnológicos de manera integral y efectiva en función de la misión investigativa. | F74: M2 - Investigación y desarrollo científico. | G74: Incrementar, apropiar y divulgar la generación de nuevo conocimiento de calidad e impacto con 391 publicaciones indexadas en Publindex, 1400 en Wos y/o Scopus, 100 libros publicados, 5 revistas científicas con sello editorial Uniatlántico. | H74: P1 - Desarrollo de la investigación básica y aplicada con impacto en aspectos sociales, políticos, culturales, económicos y/o tecnológicos en los contextos regional, nacional e internacional | I74: 0.27 | J74: Fortalecer las revistas del sello editorial Uniatlántico | K74: 0.1 | L74: Jefe del Departamento de Fomento y Apoyo a la Investigación | M74: PDI | O74: Revistas científicas editadas bajo el sello Editorial Uniatlántico | P74: N° de revista editadas bajo el sello Editorial Uniatlántico indexada en Scopus | Q74: Anual | R74: Unidad | T74: Nuevo gestionado durante la vigencia | U74: 0 | V74: 0 | W74: 1 | X74: =IFERROR(IF($T74=Lists!$S$2,SUM(FORMULACIÓN!U74:W74),IF(FORMULACIÓN!$T74=Lists!$S$3,SUM(FORMULACIÓN!V74:W74),IF(FORMULACIÓN!$T74=Lists!$S$4,AVERAGE(FORMULACIÓN!V74:W74),IF(FORMULACIÓN!$T74=Lists!$S$5,OFFSET(U74,0,COUNTA(V74:W74)),IF(FORMULACIÓN!$T74=Lists!$S$6,AVERAGE(V74:W74),""))))),"") -> 1 | Y74: =IF($R74=Lists!$R$3,TEXT(FORMULACIÓN!X74,"00,00%"),IF(FORMULACIÓN!X74=0,0,TEXT(FORMULACIÓN!X74,"##.###"))) -> 1
A75: =IF(C75<>"",+A74+1,"") -> 66 | B75: 2026 | C75: L2 - Investigación y Redes de conocimiento para el desarrollo de la sociedad | D75: =IFERROR(VLOOKUP(FORMULACIÓN!C75,Lists!$A$2:$B$6,2,FALSE),"") -> Fortalecer y consolidar los procesos de investigación, creación e innovación al servicio del progreso científico, tecnológico, ambiental, cultural, social y humano, en el contexto regional, nacional e internacional. | E75: 4. Impulsar la interacción entre los grupos de investigación de la Universidad y el Sistema Nacional de Ciencia, Tecnología e Innovación (SNCTI) y sus homólogos internacionales, para la conformación de redes de conocimiento y cooperación, que faciliten el desarrollo investigativo y tecnológico. | F75: M2 - Investigación y desarrollo científico. | G75: Fortalecer la articulación con redes académicas y científicas para la investigación y la producción académica, impulsando la movilidad saliente internacional con 350 docentes y la nacional con 300 docentes, asimismo la movilidad de estudiantes vinculados a semilleros en 1.300 a nivel nacional y 100 a nivel internacional. | H75: P1 - Desarrollo de la investigación básica y aplicada con impacto en aspectos sociales, políticos, culturales, económicos y/o tecnológicos en los contextos regional, nacional e internacional | I75: 0.27 | J75: Incentivar la movilidad saliente de estudiantes investigadores | K75: 0.1 | L75: Jefe del Departamento de Fomento y Apoyo a la Investigación | M75: PDI | N75: X | O75: Movilidad de estudiantes UA vinculados a semilleros a nivel nacional e internacional | P75: N° de estudiantes vinculados a semilleros de investigación que realizan movilidad nacional | Q75: Anual | R75: Unidad | S75: La movilidad se puede contar a partir desde el punto que se le da el aval a la persona que va a realizar este proceso. | T75: Nuevo gestionado durante la vigencia | U75: 371 | V75: 0 | W75: 177 | X75: =IFERROR(IF($T75=Lists!$S$2,SUM(FORMULACIÓN!U75:W75),IF(FORMULACIÓN!$T75=Lists!$S$3,SUM(FORMULACIÓN!V75:W75),IF(FORMULACIÓN!$T75=Lists!$S$4,AVERAGE(FORMULACIÓN!V75:W75),IF(FORMULACIÓN!$T75=Lists!$S$5,OFFSET(U75,0,COUNTA(V75:W75)),IF(FORMULACIÓN!$T75=Lists!$S$6,AVERAGE(V75:W75),""))))),"") -> 177 | Y75: =IF($R75=Lists!$R$3,TEXT(FORMULACIÓN!X75,"00,00%"),IF(FORMULACIÓN!X75=0,0,TEXT(FORMULACIÓN!X75,"##.###"))) -> 177
A76: =IF(C76<>"",+A75+1,"") -> 67 | B76: 2026 | C76: L2 - Investigación y Redes de conocimiento para el desarrollo de la sociedad | D76: =IFERROR(VLOOKUP(FORMULACIÓN!C76,Lists!$A$2:$B$6,2,FALSE),"") -> Fortalecer y consolidar los procesos de investigación, creación e innovación al servicio del progreso científico, tecnológico, ambiental, cultural, social y humano, en el contexto regional, nacional e internacional. | E76: 4. Impulsar la interacción entre los grupos de investigación de la Universidad y el Sistema Nacional de Ciencia, Tecnología e Innovación (SNCTI) y sus homólogos internacionales, para la conformación de redes de conocimiento y cooperación, que faciliten el desarrollo investigativo y tecnológico. | F76: M2 - Investigación y desarrollo científico. | G76: Fortalecer la articulación con redes académicas y científicas para la investigación y la producción académica, impulsando la movilidad saliente internacional con 350 docentes y la nacional con 300 docentes, asimismo la movilidad de estudiantes vinculados a semilleros en 1.300 a nivel nacional y 100 a nivel internacional. | H76: P1 - Desarrollo de la investigación básica y aplicada con impacto en aspectos sociales, políticos, culturales, económicos y/o tecnológicos en los contextos regional, nacional e internacional | I76: 0.27 | J76: Incentivar la movilidad saliente de estudiantes investigadores | K76: 0.1 | L76: Jefe del Departamento de Fomento y Apoyo a la Investigación | M76: PDI | N76: X | O76: Movilidad de estudiantes UA vinculados a semilleros a nivel nacional e internacional | P76: N° de estudiantes vinculados a semilleros de investigación que realizan movilidad internacional | Q76: Anual | R76: Unidad | S76: La movilidad se puede contar a partir desde el punto que se le da el aval a la persona que va a realizar este proceso. | T76: Nuevo gestionado durante la vigencia | U76: 58 | V76: 0 | W76: 40 | X76: =IFERROR(IF($T76=Lists!$S$2,SUM(FORMULACIÓN!U76:W76),IF(FORMULACIÓN!$T76=Lists!$S$3,SUM(FORMULACIÓN!V76:W76),IF(FORMULACIÓN!$T76=Lists!$S$4,AVERAGE(FORMULACIÓN!V76:W76),IF(FORMULACIÓN!$T76=Lists!$S$5,OFFSET(U76,0,COUNTA(V76:W76)),IF(FORMULACIÓN!$T76=Lists!$S$6,AVERAGE(V76:W76),""))))),"") -> 40 | Y76: =IF($R76=Lists!$R$3,TEXT(FORMULACIÓN!X76,"00,00%"),IF(FORMULACIÓN!X76=0,0,TEXT(FORMULACIÓN!X76,"##.###"))) -> 40
A77: =IF(C77<>"",+A76+1,"") -> 68 | B77: 2026 | C77: L2 - Investigación y Redes de conocimiento para el desarrollo de la sociedad | D77: =IFERROR(VLOOKUP(FORMULACIÓN!C77,Lists!$A$2:$B$6,2,FALSE),"") -> Fortalecer y consolidar los procesos de investigación, creación e innovación al servicio del progreso científico, tecnológico, ambiental, cultural, social y humano, en el contexto regional, nacional e internacional. | E77: 4. Impulsar la interacción entre los grupos de investigación de la Universidad y el Sistema Nacional de Ciencia, Tecnología e Innovación (SNCTI) y sus homólogos internacionales, para la conformación de redes de conocimiento y cooperación, que faciliten el desarrollo investigativo y tecnológico. | F77: M2 - Investigación y desarrollo científico. | G77: Garantizar la formación académica integral a través de las competencias investigativas | H77: P1 - Desarrollo de la investigación básica y aplicada con impacto en aspectos sociales, políticos, culturales, económicos y/o tecnológicos en los contextos regional, nacional e internacional | I77: 0.27 | J77: Fomentar la vinculación de estudiantes a los semilleros de investigación | K77: 0.1 | L77: Jefe del Departamento de Fomento y Apoyo a la Investigación | M77: PA | N77: X | O77: Vinculación de estudiantes a semilleros de investigación | P77: N° de estudiantes articulados a semilleros de investigación | Q77: Semestral | R77: Unidad | S77: Aplica promedio tambien para las facultades | T77: Promedio | U77: 4550 | V77: 4000 | W77: 4000 | X77: =IFERROR(IF($T77=Lists!$S$2,SUM(FORMULACIÓN!U77:W77),IF(FORMULACIÓN!$T77=Lists!$S$3,SUM(FORMULACIÓN!V77:W77),IF(FORMULACIÓN!$T77=Lists!$S$4,AVERAGE(FORMULACIÓN!V77:W77),IF(FORMULACIÓN!$T77=Lists!$S$5,OFFSET(U77,0,COUNTA(V77:W77)),IF(FORMULACIÓN!$T77=Lists!$S$6,AVERAGE(V77:W77),""))))),"") -> 4000 | Y77: =IF($R77=Lists!$R$3,TEXT(FORMULACIÓN!X77,"00,00%"),IF(FORMULACIÓN!X77=0,0,TEXT(FORMULACIÓN!X77,"##.###"))) -> 4.000
A78: =IF(C78<>"",+A77+1,"") -> 69 | B78: 2026 | C78: L2 - Investigación y Redes de conocimiento para el desarrollo de la sociedad | D78: =IFERROR(VLOOKUP(FORMULACIÓN!C78,Lists!$A$2:$B$6,2,FALSE),"") -> Fortalecer y consolidar los procesos de investigación, creación e innovación al servicio del progreso científico, tecnológico, ambiental, cultural, social y humano, en el contexto regional, nacional e internacional. | E78: 4. Impulsar la interacción entre los grupos de investigación de la Universidad y el Sistema Nacional de Ciencia, Tecnología e Innovación (SNCTI) y sus homólogos internacionales, para la conformación de redes de conocimiento y cooperación, que faciliten el desarrollo investigativo y tecnológico. | F78: M2 - Investigación y desarrollo científico. | G78: Garantizar la formación académica integral a través de las competencias investigativas | H78: P1 - Desarrollo de la investigación básica y aplicada con impacto en aspectos sociales, políticos, culturales, económicos y/o tecnológicos en los contextos regional, nacional e internacional | I78: 0.27 | J78: Fomentar la vinculación de estudiantes a los semilleros de investigación | K78: 0.1 | L78: Jefe del Departamento de Fomento y Apoyo a la Investigación | M78: PA | N78: X | O78: Vinculación de estudiantes de posgrados a grupos de investigación | P78: N° de estudiantes de posgrado articulados a grupos de investigación | Q78: Semestral | R78: Unidad | S78: Aplica promedio tambien para las facultades | T78: Promedio | U78: 35 | V78: 43 | W78: 43 | X78: =IFERROR(IF($T78=Lists!$S$2,SUM(FORMULACIÓN!U78:W78),IF(FORMULACIÓN!$T78=Lists!$S$3,SUM(FORMULACIÓN!V78:W78),IF(FORMULACIÓN!$T78=Lists!$S$4,AVERAGE(FORMULACIÓN!V78:W78),IF(FORMULACIÓN!$T78=Lists!$S$5,OFFSET(U78,0,COUNTA(V78:W78)),IF(FORMULACIÓN!$T78=Lists!$S$6,AVERAGE(V78:W78),""))))),"") -> 43 | Y78: =IF($R78=Lists!$R$3,TEXT(FORMULACIÓN!X78,"00,00%"),IF(FORMULACIÓN!X78=0,0,TEXT(FORMULACIÓN!X78,"##.###"))) -> 43
A79: =IF(C79<>"",+A78+1,"") -> 70 | B79: 2026 | C79: L2 - Investigación y Redes de conocimiento para el desarrollo de la sociedad | D79: =IFERROR(VLOOKUP(FORMULACIÓN!C79,Lists!$A$2:$B$6,2,FALSE),"") -> Fortalecer y consolidar los procesos de investigación, creación e innovación al servicio del progreso científico, tecnológico, ambiental, cultural, social y humano, en el contexto regional, nacional e internacional. | E79: 3. Gestionar relaciones estratégicas con otras instituciones para el desarrollo de actividades investigativas financiadas de carácter nacional e internacional. | F79: M2 - Investigación y desarrollo científico. | G79: Garantizar la formación académica integral a través de las competencias investigativas | H79: P1 - Desarrollo de la investigación básica y aplicada con impacto en aspectos sociales, políticos, culturales, económicos y/o tecnológicos en los contextos regional, nacional e internacional | I79: 0.27 | J79: Apoyar a los jóvenes investigadores en su formación postgradual | K79: 0.1 | L79: Jefe del Departamento de Fomento y Apoyo a la Investigación | M79: PA | O79: Jóvenes investigadores apoyados para su formación (becas pasantía- convocatorias externas (Minciencias) | P79: N° de Jóvenes investigadores financiados | Q79: Anual | R79: Unidad | T79: Nuevo gestionado durante la vigencia | U79: 30 | V79: 0 | W79: 10 | X79: =IFERROR(IF($T79=Lists!$S$2,SUM(FORMULACIÓN!U79:W79),IF(FORMULACIÓN!$T79=Lists!$S$3,SUM(FORMULACIÓN!V79:W79),IF(FORMULACIÓN!$T79=Lists!$S$4,AVERAGE(FORMULACIÓN!V79:W79),IF(FORMULACIÓN!$T79=Lists!$S$5,OFFSET(U79,0,COUNTA(V79:W79)),IF(FORMULACIÓN!$T79=Lists!$S$6,AVERAGE(V79:W79),""))))),"") -> 10 | Y79: =IF($R79=Lists!$R$3,TEXT(FORMULACIÓN!X79,"00,00%"),IF(FORMULACIÓN!X79=0,0,TEXT(FORMULACIÓN!X79,"##.###"))) -> 10
A80: =IF(C80<>"",+A79+1,"") -> 71 | B80: 2026 | C80: L2 - Investigación y Redes de conocimiento para el desarrollo de la sociedad | D80: =IFERROR(VLOOKUP(FORMULACIÓN!C80,Lists!$A$2:$B$6,2,FALSE),"") -> Fortalecer y consolidar los procesos de investigación, creación e innovación al servicio del progreso científico, tecnológico, ambiental, cultural, social y humano, en el contexto regional, nacional e internacional. | E80: 4. Impulsar la interacción entre los grupos de investigación de la Universidad y el Sistema Nacional de Ciencia, Tecnología e Innovación (SNCTI) y sus homólogos internacionales, para la conformación de redes de conocimiento y cooperación, que faciliten el desarrollo investigativo y tecnológico. | F80: M2 - Investigación y desarrollo científico. | G80: Fortalecer la articulación con redes académicas y científicas para la investigación y la producción académica, impulsando la movilidad saliente internacional con 350 docentes y la nacional con 300 docentes, asimismo la movilidad de estudiantes vinculados a semilleros en 1.300 a nivel nacional y 100 a nivel internacional. | H80: P2 - Movilidad docente para el fortalecimiento de la investigación | I80: 0.08 | J80: Incentivar la movilidad saliente de docentes investigadores | K80: 0.5 | L80: Jefe del Departamento de Fomento y Apoyo a la Investigación | M80: PDI | N80: X | O80: Movilidad saliente nacional e internacional de docentes investigadores | P80: N° de docentes investigadores que realizan movilidad saliente a nivel nacional | Q80: Anual | R80: Unidad | S80: La movilidad se puede contar a partir desde el punto que se le da el aval a la persona que va a realizar este proceso. | T80: Nuevo gestionado durante la vigencia | U80: 51 | V80: 0 | W80: 63 | X80: =IFERROR(IF($T80=Lists!$S$2,SUM(FORMULACIÓN!U80:W80),IF(FORMULACIÓN!$T80=Lists!$S$3,SUM(FORMULACIÓN!V80:W80),IF(FORMULACIÓN!$T80=Lists!$S$4,AVERAGE(FORMULACIÓN!V80:W80),IF(FORMULACIÓN!$T80=Lists!$S$5,OFFSET(U80,0,COUNTA(V80:W80)),IF(FORMULACIÓN!$T80=Lists!$S$6,AVERAGE(V80:W80),""))))),"") -> 63 | Y80: =IF($R80=Lists!$R$3,TEXT(FORMULACIÓN!X80,"00,00%"),IF(FORMULACIÓN!X80=0,0,TEXT(FORMULACIÓN!X80,"##.###"))) -> 63
A81: =IF(C81<>"",+A80+1,"") -> 72 | B81: 2026 | C81: L2 - Investigación y Redes de conocimiento para el desarrollo de la sociedad | D81: =IFERROR(VLOOKUP(FORMULACIÓN!C81,Lists!$A$2:$B$6,2,FALSE),"") -> Fortalecer y consolidar los procesos de investigación, creación e innovación al servicio del progreso científico, tecnológico, ambiental, cultural, social y humano, en el contexto regional, nacional e internacional. | E81: 4. Impulsar la interacción entre los grupos de investigación de la Universidad y el Sistema Nacional de Ciencia, Tecnología e Innovación (SNCTI) y sus homólogos internacionales, para la conformación de redes de conocimiento y cooperación, que faciliten el desarrollo investigativo y tecnológico. | F81: M2 - Investigación y desarrollo científico. | G81: Fortalecer la articulación con redes académicas y científicas para la investigación y la producción académica, impulsando la movilidad saliente internacional con 350 docentes y la nacional con 300 docentes, asimismo la movilidad de estudiantes vinculados a semilleros en 1.300 a nivel nacional y 100 a nivel internacional. | H81: P2 - Movilidad docente para el fortalecimiento de la investigación | I81: 0.08 | J81: Incentivar la movilidad saliente de docentes investigadores | K81: 0.5 | L81: Jefe del Departamento de Fomento y Apoyo a la Investigación | M81: PDI | N81: X | O81: Movilidad saliente nacional e internacional de docentes investigadores | P81: N° de docentes investigadores que realizan movilidad saliente a nivel internacional | Q81: Anual | R81: Unidad | S81: La movilidad se puede contar a partir desde el punto que se le da el aval a la persona que va a realizar este proceso. | T81: Nuevo gestionado durante la vigencia | U81: 74 | V81: 0 | W81: 56 | X81: =IFERROR(IF($T81=Lists!$S$2,SUM(FORMULACIÓN!U81:W81),IF(FORMULACIÓN!$T81=Lists!$S$3,SUM(FORMULACIÓN!V81:W81),IF(FORMULACIÓN!$T81=Lists!$S$4,AVERAGE(FORMULACIÓN!V81:W81),IF(FORMULACIÓN!$T81=Lists!$S$5,OFFSET(U81,0,COUNTA(V81:W81)),IF(FORMULACIÓN!$T81=Lists!$S$6,AVERAGE(V81:W81),""))))),"") -> 56 | Y81: =IF($R81=Lists!$R$3,TEXT(FORMULACIÓN!X81,"00,00%"),IF(FORMULACIÓN!X81=0,0,TEXT(FORMULACIÓN!X81,"##.###"))) -> 56
A82: =IF(C82<>"",+A81+1,"") -> 73 | B82: 2026 | C82: L2 - Investigación y Redes de conocimiento para el desarrollo de la sociedad | D82: =IFERROR(VLOOKUP(FORMULACIÓN!C82,Lists!$A$2:$B$6,2,FALSE),"") -> Fortalecer y consolidar los procesos de investigación, creación e innovación al servicio del progreso científico, tecnológico, ambiental, cultural, social y humano, en el contexto regional, nacional e internacional. | E82: 2. Actualizar y desarrollar la agenda de investigación-innovación-creación institucional, en torno con el contexto y tendencias globales. | F82: M2 - Investigación y desarrollo científico. | G82: Incrementar en al menos 520 los proyectos de investigación aprobados por convocatorias | H82: P3 - Articulación con el sector externo para el fortalecimiento de la investigación | I82: 0.06 | J82: Desarrollar convocatorias internas y financiar proyectos de investigación. | K82: 0.2 | L82: Jefe del Departamento de Fomento y Apoyo a la Investigación | M82: PDI | O82: Proyectos de investigación financiados por convocatorias (tipo de proyecto, valor financiado) | P82: N° de proyectos de investigación aprobados por convocatorias internas | Q82: Anual | R82: Unidad | T82: Nuevo gestionado durante la vigencia | U82: 42 | V82: 0 | W82: 30 | X82: =IFERROR(IF($T82=Lists!$S$2,SUM(FORMULACIÓN!U82:W82),IF(FORMULACIÓN!$T82=Lists!$S$3,SUM(FORMULACIÓN!V82:W82),IF(FORMULACIÓN!$T82=Lists!$S$4,AVERAGE(FORMULACIÓN!V82:W82),IF(FORMULACIÓN!$T82=Lists!$S$5,OFFSET(U82,0,COUNTA(V82:W82)),IF(FORMULACIÓN!$T82=Lists!$S$6,AVERAGE(V82:W82),""))))),"") -> 30 | Y82: =IF($R82=Lists!$R$3,TEXT(FORMULACIÓN!X82,"00,00%"),IF(FORMULACIÓN!X82=0,0,TEXT(FORMULACIÓN!X82,"##.###"))) -> 30
A83: =IF(C83<>"",+A82+1,"") -> 74 | B83: 2026 | C83: L2 - Investigación y Redes de conocimiento para el desarrollo de la sociedad | D83: =IFERROR(VLOOKUP(FORMULACIÓN!C83,Lists!$A$2:$B$6,2,FALSE),"") -> Fortalecer y consolidar los procesos de investigación, creación e innovación al servicio del progreso científico, tecnológico, ambiental, cultural, social y humano, en el contexto regional, nacional e internacional. | E83: 3. Gestionar relaciones estratégicas con otras instituciones para el desarrollo de actividades investigativas financiadas de carácter nacional e internacional. | F83: M2 - Investigación y desarrollo científico. | G83: Incrementar en al menos 520 los proyectos de investigación aprobados por convocatorias | H83: P3 - Articulación con el sector externo para el fortalecimiento de la investigación | I83: 0.06 | J83: Promover la participación en convocatorias externas para lograr financiación de proyectos. | K83: 0.2 | L83: Jefe del Departamento de Fomento y Apoyo a la Investigación | M83: PDI | O83: Proyectos de investigación financiados por convocatorias (tipo de proyecto, valor financiado) | P83: N° de proyectos de investigación financiados por convocatorias externas | Q83: Anual | R83: Unidad | T83: Nuevo gestionado durante la vigencia | U83: 20 | V83: 0 | W83: 7 | X83: =IFERROR(IF($T83=Lists!$S$2,SUM(FORMULACIÓN!U83:W83),IF(FORMULACIÓN!$T83=Lists!$S$3,SUM(FORMULACIÓN!V83:W83),IF(FORMULACIÓN!$T83=Lists!$S$4,AVERAGE(FORMULACIÓN!V83:W83),IF(FORMULACIÓN!$T83=Lists!$S$5,OFFSET(U83,0,COUNTA(V83:W83)),IF(FORMULACIÓN!$T83=Lists!$S$6,AVERAGE(V83:W83),""))))),"") -> 7 | Y83: =IF($R83=Lists!$R$3,TEXT(FORMULACIÓN!X83,"00,00%"),IF(FORMULACIÓN!X83=0,0,TEXT(FORMULACIÓN!X83,"##.###"))) -> 7
A84: =IF(C84<>"",+A83+1,"") -> 75 | B84: 2026 | C84: L2 - Investigación y Redes de conocimiento para el desarrollo de la sociedad | D84: =IFERROR(VLOOKUP(FORMULACIÓN!C84,Lists!$A$2:$B$6,2,FALSE),"") -> Fortalecer y consolidar los procesos de investigación, creación e innovación al servicio del progreso científico, tecnológico, ambiental, cultural, social y humano, en el contexto regional, nacional e internacional. | E84: 6. Fomentar actividades para el desarrollo científico, tecnológico, ambiental, cultural, social y humano con impacto positivo hacia el entorno regional, nacional e internacional. | F84: M2 - Investigación y desarrollo científico. | G84: Afianzar la producción académica investigativa | H84: P3 - Articulación con el sector externo para el fortalecimiento de la investigación | I84: 0.06 | J84: Impulsar la participación en eventos de semilleros | K84: 0.2 | L84: Jefe del Departamento de Fomento y Apoyo a la Investigación | M84: PA | N84: X | O84: No. Proyectos presentados en eventos de semilleros de investigación a nivel regional, nacional e internacional | P84: N° de proyectos presentados en eventos de semilleros regionales por año | Q84: Anual | R84: Unidad | T84: Nuevo gestionado durante la vigencia | U84: 365 | V84: 0 | W84: 289 | X84: =IFERROR(IF($T84=Lists!$S$2,SUM(FORMULACIÓN!U84:W84),IF(FORMULACIÓN!$T84=Lists!$S$3,SUM(FORMULACIÓN!V84:W84),IF(FORMULACIÓN!$T84=Lists!$S$4,AVERAGE(FORMULACIÓN!V84:W84),IF(FORMULACIÓN!$T84=Lists!$S$5,OFFSET(U84,0,COUNTA(V84:W84)),IF(FORMULACIÓN!$T84=Lists!$S$6,AVERAGE(V84:W84),""))))),"") -> 289 | Y84: =IF($R84=Lists!$R$3,TEXT(FORMULACIÓN!X84,"00,00%"),IF(FORMULACIÓN!X84=0,0,TEXT(FORMULACIÓN!X84,"##.###"))) -> 289
A85: =IF(C85<>"",+A84+1,"") -> 76 | B85: 2026 | C85: L2 - Investigación y Redes de conocimiento para el desarrollo de la sociedad | D85: =IFERROR(VLOOKUP(FORMULACIÓN!C85,Lists!$A$2:$B$6,2,FALSE),"") -> Fortalecer y consolidar los procesos de investigación, creación e innovación al servicio del progreso científico, tecnológico, ambiental, cultural, social y humano, en el contexto regional, nacional e internacional. | E85: 6. Fomentar actividades para el desarrollo científico, tecnológico, ambiental, cultural, social y humano con impacto positivo hacia el entorno regional, nacional e internacional. | F85: M2 - Investigación y desarrollo científico. | G85: Afianzar la producción académica investigativa | H85: P3 - Articulación con el sector externo para el fortalecimiento de la investigación | I85: 0.06 | J85: Impulsar la participación en eventos de semilleros | K85: 0.14 | L85: Jefe del Departamento de Fomento y Apoyo a la Investigación | M85: PA | O85: Proyectos presentados en eventos de semilleros de investigación a nivel regional, nacional e internacional | P85: N° de proyectos presentados en eventos de semilleros nacionales por año | Q85: Anual | R85: Unidad | T85: Nuevo gestionado durante la vigencia | U85: 210 | V85: 0 | W85: 215 | X85: =IFERROR(IF($T85=Lists!$S$2,SUM(FORMULACIÓN!U85:W85),IF(FORMULACIÓN!$T85=Lists!$S$3,SUM(FORMULACIÓN!V85:W85),IF(FORMULACIÓN!$T85=Lists!$S$4,AVERAGE(FORMULACIÓN!V85:W85),IF(FORMULACIÓN!$T85=Lists!$S$5,OFFSET(U85,0,COUNTA(V85:W85)),IF(FORMULACIÓN!$T85=Lists!$S$6,AVERAGE(V85:W85),""))))),"") -> 215 | Y85: =IF($R85=Lists!$R$3,TEXT(FORMULACIÓN!X85,"00,00%"),IF(FORMULACIÓN!X85=0,0,TEXT(FORMULACIÓN!X85,"##.###"))) -> 215
A86: =IF(C86<>"",+A85+1,"") -> 77 | B86: 2026 | C86: L2 - Investigación y Redes de conocimiento para el desarrollo de la sociedad | D86: =IFERROR(VLOOKUP(FORMULACIÓN!C86,Lists!$A$2:$B$6,2,FALSE),"") -> Fortalecer y consolidar los procesos de investigación, creación e innovación al servicio del progreso científico, tecnológico, ambiental, cultural, social y humano, en el contexto regional, nacional e internacional. | E86: 6. Fomentar actividades para el desarrollo científico, tecnológico, ambiental, cultural, social y humano con impacto positivo hacia el entorno regional, nacional e internacional. | F86: M2 - Investigación y desarrollo científico. | G86: Afianzar la producción académica investigativa | H86: P3 - Articulación con el sector externo para el fortalecimiento de la investigación | I86: 0.06 | J86: Impulsar la participación en eventos de semilleros | K86: 0.14 | L86: Jefe del Departamento de Fomento y Apoyo a la Investigación | M86: PA | O86: Proyectos presentados en eventos de semilleros de investigación a nivel regional, nacional e internacional | P86: N° de proyectos presentados en eventos de semilleros internacionales por año. | Q86: Anual | R86: Unidad | T86: Nuevo gestionado durante la vigencia | U86: 11 | V86: 0 | W86: 4 | X86: =IFERROR(IF($T86=Lists!$S$2,SUM(FORMULACIÓN!U86:W86),IF(FORMULACIÓN!$T86=Lists!$S$3,SUM(FORMULACIÓN!V86:W86),IF(FORMULACIÓN!$T86=Lists!$S$4,AVERAGE(FORMULACIÓN!V86:W86),IF(FORMULACIÓN!$T86=Lists!$S$5,OFFSET(U86,0,COUNTA(V86:W86)),IF(FORMULACIÓN!$T86=Lists!$S$6,AVERAGE(V86:W86),""))))),"") -> 4 | Y86: =IF($R86=Lists!$R$3,TEXT(FORMULACIÓN!X86,"00,00%"),IF(FORMULACIÓN!X86=0,0,TEXT(FORMULACIÓN!X86,"##.###"))) -> 4
A87: =IF(C87<>"",+A86+1,"") -> 78 | B87: 2026 | C87: L2 - Investigación y Redes de conocimiento para el desarrollo de la sociedad | D87: =IFERROR(VLOOKUP(FORMULACIÓN!C87,Lists!$A$2:$B$6,2,FALSE),"") -> Fortalecer y consolidar los procesos de investigación, creación e innovación al servicio del progreso científico, tecnológico, ambiental, cultural, social y humano, en el contexto regional, nacional e internacional. | E87: 5. Armonizar los procesos administrativos y recursos tecnológicos de manera integral y efectiva en función de la misión investigativa. | F87: M2 - Investigación y desarrollo científico. | G87: Potencializar la sostenibilidad investigativa con proyectos viables para el fortalecimiento de las capacidades institucionales. | H87: P3 - Articulación con el sector externo para el fortalecimiento de la investigación | I87: 0.06 | J87: Fomentar los proyectos en articulación con las MIPYMES | K87: 0.12 | L87: Jefe del Departamento de Fomento y Apoyo a la Investigación | M87: PR | O87: Articulación investigativa con el sector productivo | P87: N° de proyectos de investigación desarrollados en articulación con el sector productivo | Q87: Anual | R87: Unidad | T87: Nuevo gestionado durante la vigencia | U87: 0 | V87: 0 | W87: 6 | X87: =IFERROR(IF($T87=Lists!$S$2,SUM(FORMULACIÓN!U87:W87),IF(FORMULACIÓN!$T87=Lists!$S$3,SUM(FORMULACIÓN!V87:W87),IF(FORMULACIÓN!$T87=Lists!$S$4,AVERAGE(FORMULACIÓN!V87:W87),IF(FORMULACIÓN!$T87=Lists!$S$5,OFFSET(U87,0,COUNTA(V87:W87)),IF(FORMULACIÓN!$T87=Lists!$S$6,AVERAGE(V87:W87),""))))),"") -> 6 | Y87: =IF($R87=Lists!$R$3,TEXT(FORMULACIÓN!X87,"00,00%"),IF(FORMULACIÓN!X87=0,0,TEXT(FORMULACIÓN!X87,"##.###"))) -> 6
A88: =IF(C88<>"",+A87+1,"") -> 79 | B88: 2026 | C88: L2 - Investigación y Redes de conocimiento para el desarrollo de la sociedad | D88: =IFERROR(VLOOKUP(FORMULACIÓN!C88,Lists!$A$2:$B$6,2,FALSE),"") -> Fortalecer y consolidar los procesos de investigación, creación e innovación al servicio del progreso científico, tecnológico, ambiental, cultural, social y humano, en el contexto regional, nacional e internacional. | E88: 5. Armonizar los procesos administrativos y recursos tecnológicos de manera integral y efectiva en función de la misión investigativa. | F88: M3 - Innovación y desarrollo tecnológico. | G88: Fomentar el desarrollo de proyectos de base tecnológica y la participación en convocatorias, y así lograr ejecutar mínimo 8 proyectos con financiación. | H88: P1 - Apropiación de proyectos de investigación de base tecnológica | I88: 0.13 | J88: Fomentar convocatorias internas para proyectos de base tecnológica | K88: 1 | L88: Jefe del Departamento de Fomento y Apoyo a la Investigación | M88: PDI | O88: Tecnologías con alcance en las etapas TRL 4, 5 y 6 según criterio de Minciencias | P88: N° de tecnologías con alcance en las etapas TRL 4, 5 y 6 según criterio de Minciencias | Q88: Anual | R88: Unidad | T88: Nuevo gestionado durante la vigencia | U88: 2 | V88: 0 | W88: 2 | X88: =IFERROR(IF($T88=Lists!$S$2,SUM(FORMULACIÓN!U88:W88),IF(FORMULACIÓN!$T88=Lists!$S$3,SUM(FORMULACIÓN!V88:W88),IF(FORMULACIÓN!$T88=Lists!$S$4,AVERAGE(FORMULACIÓN!V88:W88),IF(FORMULACIÓN!$T88=Lists!$S$5,OFFSET(U88,0,COUNTA(V88:W88)),IF(FORMULACIÓN!$T88=Lists!$S$6,AVERAGE(V88:W88),""))))),"") -> 2 | Y88: =IF($R88=Lists!$R$3,TEXT(FORMULACIÓN!X88,"00,00%"),IF(FORMULACIÓN!X88=0,0,TEXT(FORMULACIÓN!X88,"##.###"))) -> 2
A89: =IF(C89<>"",+A88+1,"") -> 80 | B89: 2026 | C89: L2 - Investigación y Redes de conocimiento para el desarrollo de la sociedad | D89: =IFERROR(VLOOKUP(FORMULACIÓN!C89,Lists!$A$2:$B$6,2,FALSE),"") -> Fortalecer y consolidar los procesos de investigación, creación e innovación al servicio del progreso científico, tecnológico, ambiental, cultural, social y humano, en el contexto regional, nacional e internacional. | E89: 6. Fomentar actividades para el desarrollo científico, tecnológico, ambiental, cultural, social y humano con impacto positivo hacia el entorno regional, nacional e internacional. | F89: M3 - Innovación y desarrollo tecnológico. | G89: Operacionalizar el Parque Tecnológico del Caribe PTC e integrar el ecosistema de ciencia, tecnología e innovación del Caribe, vinculando el PTC y el Centro de Investigaciones Científicas y Tecnológicas de la Universidad del Atlántico CICIT, así como otros laboratorios de investigación para impactar a las empresas de base tecnológica a través de servicios de investigación alcanzando 5 proyectos que involucren propiedad industrial, 10 contratos con empresas de base tecnológica, 10 proyectos con financiación internacional | H89: P2 - Consolidación del Centro de Investigaciones Científicas y Tecnológicas de la Universidad del Atlántico | I89: 0.16 | J89: Apoyar proyectos que impliquen desarrollo de patentes | K89: 0.2 | L89: Jefe del Departamento de Fomento y Apoyo a la Investigación | M89: PDI | O89: Proyectos de investigación desarrollados por grupos de investigación adscritos al CICIT que contienen desarrollo de patentes | P89: N° de proyectos de investigación desarrollados por grupos de investigación adscritos al CICIT que implica propiedad industrial (patentes, diseños industriales, variedades vegetales, marcas) | Q89: Anual | R89: Unidad | T89: Nuevo gestionado durante la vigencia | U89: 3 | V89: 0 | W89: 1 | X89: =IFERROR(IF($T89=Lists!$S$2,SUM(FORMULACIÓN!U89:W89),IF(FORMULACIÓN!$T89=Lists!$S$3,SUM(FORMULACIÓN!V89:W89),IF(FORMULACIÓN!$T89=Lists!$S$4,AVERAGE(FORMULACIÓN!V89:W89),IF(FORMULACIÓN!$T89=Lists!$S$5,OFFSET(U89,0,COUNTA(V89:W89)),IF(FORMULACIÓN!$T89=Lists!$S$6,AVERAGE(V89:W89),""))))),"") -> 1 | Y89: =IF($R89=Lists!$R$3,TEXT(FORMULACIÓN!X89,"00,00%"),IF(FORMULACIÓN!X89=0,0,TEXT(FORMULACIÓN!X89,"##.###"))) -> 1
A90: =IF(C90<>"",+A89+1,"") -> 81 | B90: 2026 | C90: L2 - Investigación y Redes de conocimiento para el desarrollo de la sociedad | D90: =IFERROR(VLOOKUP(FORMULACIÓN!C90,Lists!$A$2:$B$6,2,FALSE),"") -> Fortalecer y consolidar los procesos de investigación, creación e innovación al servicio del progreso científico, tecnológico, ambiental, cultural, social y humano, en el contexto regional, nacional e internacional. | E90: 3. Gestionar relaciones estratégicas con otras instituciones para el desarrollo de actividades investigativas financiadas de carácter nacional e internacional. | F90: M3 - Innovación y desarrollo tecnológico. | G90: Operacionalizar el Parque Tecnológico del Caribe PTC e integrar el ecosistema de ciencia, tecnología e innovación del Caribe, vinculando el PTC y el Centro de Investigaciones Científicas y Tecnológicas de la Universidad del Atlántico CICIT, así como otros laboratorios de investigación para impactar a las empresas de base tecnológica a través de servicios de investigación alcanzando 5 proyectos que involucren propiedad industrial, 10 contratos con empresas de base tecnológica, 10 proyectos con financiación internacional | H90: P2 - Consolidación del Centro de Investigaciones Científicas y Tecnológicas de la Universidad del Atlántico | I90: 0.16 | J90: Impulsar convenios con empresas de base tecnológica | K90: 0.2 | L90: Jefe del Departamento de Fomento y Apoyo a la Investigación | M90: PDI | O90: Contratos y/o convenios en alianzas con empresas de base tecnológica para ejecución de proyectos de investigación en alianza con el CICIT, así como otros laboratorios de investigación con el PTC, | P90: N° de contratos y/o convenios con empresas de base tecnológica | Q90: Anual | R90: Unidad | T90: Nuevo gestionado durante la vigencia | U90: 2 | V90: 0 | W90: 1 | X90: =IFERROR(IF($T90=Lists!$S$2,SUM(FORMULACIÓN!U90:W90),IF(FORMULACIÓN!$T90=Lists!$S$3,SUM(FORMULACIÓN!V90:W90),IF(FORMULACIÓN!$T90=Lists!$S$4,AVERAGE(FORMULACIÓN!V90:W90),IF(FORMULACIÓN!$T90=Lists!$S$5,OFFSET(U90,0,COUNTA(V90:W90)),IF(FORMULACIÓN!$T90=Lists!$S$6,AVERAGE(V90:W90),""))))),"") -> 1 | Y90: =IF($R90=Lists!$R$3,TEXT(FORMULACIÓN!X90,"00,00%"),IF(FORMULACIÓN!X90=0,0,TEXT(FORMULACIÓN!X90,"##.###"))) -> 1
A91: =IF(C91<>"",+A90+1,"") -> 82 | B91: 2026 | C91: L2 - Investigación y Redes de conocimiento para el desarrollo de la sociedad | D91: =IFERROR(VLOOKUP(FORMULACIÓN!C91,Lists!$A$2:$B$6,2,FALSE),"") -> Fortalecer y consolidar los procesos de investigación, creación e innovación al servicio del progreso científico, tecnológico, ambiental, cultural, social y humano, en el contexto regional, nacional e internacional. | E91: 3. Gestionar relaciones estratégicas con otras instituciones para el desarrollo de actividades investigativas financiadas de carácter nacional e internacional. | F91: M3 - Innovación y desarrollo tecnológico. | G91: Operacionalizar el Parque Tecnológico del Caribe PTC e integrar el ecosistema de ciencia, tecnología e innovación del Caribe, vinculando el PTC y el Centro de Investigaciones Científicas y Tecnológicas de la Universidad del Atlántico CICIT, así como otros laboratorios de investigación para impactar a las empresas de base tecnológica a través de servicios de investigación alcanzando 5 proyectos que involucren propiedad industrial, 10 contratos con empresas de base tecnológica, 10 proyectos con financiación internacional | H91: P2 - Consolidación del Centro de Investigaciones Científicas y Tecnológicas de la Universidad del Atlántico | I91: 0.16 | J91: Promover proyectos I+D+i | K91: 0.2 | L91: Jefe del Departamento de Fomento y Apoyo a la Investigación | M91: PDI | N91: X | O91: Proyectos I+D+i en ejecución con participación de pares internacionales y/o financiación con recursos internacionales | P91: N° Proyectos I+D+i en ejecución con participación de pares internacionales y/o financiación con recursos internacionales | Q91: Anual | R91: Unidad | T91: Nuevo gestionado durante la vigencia | U91: 16 | V91: 0 | W91: 3 | X91: =IFERROR(IF($T91=Lists!$S$2,SUM(FORMULACIÓN!U91:W91),IF(FORMULACIÓN!$T91=Lists!$S$3,SUM(FORMULACIÓN!V91:W91),IF(FORMULACIÓN!$T91=Lists!$S$4,AVERAGE(FORMULACIÓN!V91:W91),IF(FORMULACIÓN!$T91=Lists!$S$5,OFFSET(U91,0,COUNTA(V91:W91)),IF(FORMULACIÓN!$T91=Lists!$S$6,AVERAGE(V91:W91),""))))),"") -> 3 | Y91: =IF($R91=Lists!$R$3,TEXT(FORMULACIÓN!X91,"00,00%"),IF(FORMULACIÓN!X91=0,0,TEXT(FORMULACIÓN!X91,"##.###"))) -> 3
A92: =IF(C92<>"",+A91+1,"") -> 83 | B92: 2026 | C92: L2 - Investigación y Redes de conocimiento para el desarrollo de la sociedad | D92: =IFERROR(VLOOKUP(FORMULACIÓN!C92,Lists!$A$2:$B$6,2,FALSE),"") -> Fortalecer y consolidar los procesos de investigación, creación e innovación al servicio del progreso científico, tecnológico, ambiental, cultural, social y humano, en el contexto regional, nacional e internacional. | E92: 5. Armonizar los procesos administrativos y recursos tecnológicos de manera integral y efectiva en función de la misión investigativa. | F92: M3 - Innovación y desarrollo tecnológico. | G92: 8 laboratorios reconocidos (con Acreditación, certificación, habilitación, autorización y/o registros) de acuerdo a los ensayos de prestación de servicios de investigación para prestación de servicios de investigación. | H92: P2 - Consolidación del Centro de Investigaciones Científicas y Tecnológicas de la Universidad del Atlántico | I92: 0.16 | J92: Gestionar la certificación de los laboratorios para la prestación de servicios de investigación | K92: 0.2 | L92: Jefe del Departamento de Fomento y Apoyo a la Investigación | M92: PDI - PA | O92: Laboratorios con certificación o acreditados para la prestación de servicios de investigación | P92: N°. de laboratorios reconocidos (con Acreditación, certificación, habilitación, autorización y/o registros) de acuerdo a los ensayos de prestación de servicios de investigación. | Q92: Anual | R92: Unidad | T92: Nuevo gestionado durante la vigencia | U92: 3 | V92: 0 | W92: 1 | X92: =IFERROR(IF($T92=Lists!$S$2,SUM(FORMULACIÓN!U92:W92),IF(FORMULACIÓN!$T92=Lists!$S$3,SUM(FORMULACIÓN!V92:W92),IF(FORMULACIÓN!$T92=Lists!$S$4,AVERAGE(FORMULACIÓN!V92:W92),IF(FORMULACIÓN!$T92=Lists!$S$5,OFFSET(U92,0,COUNTA(V92:W92)),IF(FORMULACIÓN!$T92=Lists!$S$6,AVERAGE(V92:W92),""))))),"") -> 1 | Y92: =IF($R92=Lists!$R$3,TEXT(FORMULACIÓN!X92,"00,00%"),IF(FORMULACIÓN!X92=0,0,TEXT(FORMULACIÓN!X92,"##.###"))) -> 1
A93: =IF(C93<>"",+A92+1,"") -> 84 | B93: 2026 | C93: L2 - Investigación y Redes de conocimiento para el desarrollo de la sociedad | D93: =IFERROR(VLOOKUP(FORMULACIÓN!C93,Lists!$A$2:$B$6,2,FALSE),"") -> Fortalecer y consolidar los procesos de investigación, creación e innovación al servicio del progreso científico, tecnológico, ambiental, cultural, social y humano, en el contexto regional, nacional e internacional. | E93: 6. Fomentar actividades para el desarrollo científico, tecnológico, ambiental, cultural, social y humano con impacto positivo hacia el entorno regional, nacional e internacional. | F93: M3 - Innovación y desarrollo tecnológico. | G93: Fomentar los servicios científicos y tecnológicos del CICIT | H93: P2 - Consolidación del Centro de Investigaciones Científicas y Tecnológicas de la Universidad del Atlántico | I93: 0.16 | J93: Promover los servicios del CICIT. | K93: 0.2 | L93: Jefe del Departamento de Fomento y Apoyo a la Investigación | M93: PA | O93: Servicios científicos y tecnológicos prestados por laboratorios institucionales (convenios, alianzas, contratos). | P93: N° de servicios científicos y tecnológicos prestados por laboratorios institucionales. | Q93: Anual | R93: Unidad | T93: Nuevo gestionado durante la vigencia | U93: 10 | V93: 0 | W93: 10 | X93: =IFERROR(IF($T93=Lists!$S$2,SUM(FORMULACIÓN!U93:W93),IF(FORMULACIÓN!$T93=Lists!$S$3,SUM(FORMULACIÓN!V93:W93),IF(FORMULACIÓN!$T93=Lists!$S$4,AVERAGE(FORMULACIÓN!V93:W93),IF(FORMULACIÓN!$T93=Lists!$S$5,OFFSET(U93,0,COUNTA(V93:W93)),IF(FORMULACIÓN!$T93=Lists!$S$6,AVERAGE(V93:W93),""))))),"") -> 10 | Y93: =IF($R93=Lists!$R$3,TEXT(FORMULACIÓN!X93,"00,00%"),IF(FORMULACIÓN!X93=0,0,TEXT(FORMULACIÓN!X93,"##.###"))) -> 10
A94: =IF(C94<>"",+A93+1,"") -> 85 | B94: 2026 | C94: L3 - Impacto regional, nacional e internacional desde la extensión y proyección social | D94: =IFERROR(VLOOKUP(FORMULACIÓN!C94,Lists!$A$2:$B$6,2,FALSE),"") -> Coadyuvar con el desarrollo económico, social, cultural y ambiental a nivel regional, nacional e internacional; mediante la extensión y proyección social articulada con la investigación, creación, formación, innovación y transferencia tecnológica, que permita una interacción e integración permanente, amplia y diversa con el estado, la empresa y la sociedad. | E94: 3. Contribuir desde lo académico, investigativo, extensión y proyección social en el tratamiento y resolución de temáticas de interés mediante el asesoramiento, análisis, formación de factores claves para la sociedad. | F94: M1 - Educación continua y formación avanzada con enfoque global. | G94: Mejoramiento de la oferta de programas de educación continua, con 1 Centro de Lenguas extranjeras, 5 ambientes de aprendizaje innovadores implementados, 2.300 programas de educación continua ejecutadas en distintas modalidalidades (presencial, semipresencial, virtual y a distancia), 35 con enfoque diferencial, 12 con componente internacional y 130 convenios con entidades del sector público y privado | H94: P1 - Fortalecimiento de los programas de educación contínua con pertinencia regional, nacional e internacional a través de la modernización de los procesos. | I94: 0.18 | J94: Constituir el centro de lenguas nativas y extranjeras | K94: 0.2 | L94: Jefe del Departamento Extensión y Proyección Social | M94: PDI | O94: Centro de Lenguas Extranjeras constituido | P94: Centro de Lenguas Extranjeras constituido | Q94: Anual | R94: Porcentaje | S94: Para el 2026 seria la radicación, (Diseño, retroalimentación y ajustes), pendiente por revisión interna (jefe Dpto) | T94: Último valor reportado | U94: 0.33 | V94: 0 | W94: 0.33 | X94: =IFERROR(IF($T94=Lists!$S$2,SUM(FORMULACIÓN!U94:W94),IF(FORMULACIÓN!$T94=Lists!$S$3,SUM(FORMULACIÓN!V94:W94),IF(FORMULACIÓN!$T94=Lists!$S$4,AVERAGE(FORMULACIÓN!V94:W94),IF(FORMULACIÓN!$T94=Lists!$S$5,OFFSET(U94,0,COUNTA(V94:W94)),IF(FORMULACIÓN!$T94=Lists!$S$6,AVERAGE(V94:W94),""))))),"") -> 0.33 | Y94: =IF($R94=Lists!$R$3,TEXT(FORMULACIÓN!X94,"00,00%"),IF(FORMULACIÓN!X94=0,0,TEXT(FORMULACIÓN!X94,"##.###"))) -> 33,00%
A95: =IF(C95<>"",+A94+1,"") -> 86 | B95: 2026 | C95: L3 - Impacto regional, nacional e internacional desde la extensión y proyección social | D95: =IFERROR(VLOOKUP(FORMULACIÓN!C95,Lists!$A$2:$B$6,2,FALSE),"") -> Coadyuvar con el desarrollo económico, social, cultural y ambiental a nivel regional, nacional e internacional; mediante la extensión y proyección social articulada con la investigación, creación, formación, innovación y transferencia tecnológica, que permita una interacción e integración permanente, amplia y diversa con el estado, la empresa y la sociedad. | E95: 6. Favorecer la proyección laboral de los egresados mediante el fortalecimiento de conocimientos y competencias requeridas para el contexto global. | F95: M1 - Educación continua y formación avanzada con enfoque global. | G95: Mejoramiento de la oferta de programas de educación continua, con 1 Centro de Lenguas extranjeras, 5 ambientes de aprendizaje innovadores implementados, 2.300 programas de educación continua ejecutadas en distintas modalidalidades (presencial, semipresencial, virtual y a distancia), 35 con enfoque diferencial, 12 con componente internacional y 130 convenios con entidades del sector público y privado | H95: P1 - Fortalecimiento de los programas de educación contínua con pertinencia regional, nacional e internacional a través de la modernización de los procesos. | I95: 0.18 | J95: Impulsar la oferta de programas de educación continua en modalidad presencial ejecutadas | K95: 0.2 | L95: Jefe del Departamento Extensión y Proyección Social | M95: PDI | N95: X | O95: Oferta de programas de educación continua en modalidades (presencial, semipresencial, virtual y a distancia) | P95: N° de programas de educación continua ejecutadas en distintas modalidades (presencial, semipresencial, virtual y a distancia) | Q95: Semestral | R95: Unidad | S95: Programas de educacion continua desarrollados en distintas modalidades. | T95: Nuevo gestionado durante la vigencia | U95: 97 | V95: 0 | W95: 60 | X95: =IFERROR(IF($T95=Lists!$S$2,SUM(FORMULACIÓN!U95:W95),IF(FORMULACIÓN!$T95=Lists!$S$3,SUM(FORMULACIÓN!V95:W95),IF(FORMULACIÓN!$T95=Lists!$S$4,AVERAGE(FORMULACIÓN!V95:W95),IF(FORMULACIÓN!$T95=Lists!$S$5,OFFSET(U95,0,COUNTA(V95:W95)),IF(FORMULACIÓN!$T95=Lists!$S$6,AVERAGE(V95:W95),""))))),"") -> 60 | Y95: =IF($R95=Lists!$R$3,TEXT(FORMULACIÓN!X95,"00,00%"),IF(FORMULACIÓN!X95=0,0,TEXT(FORMULACIÓN!X95,"##.###"))) -> 60
A96: =IF(C96<>"",+A95+1,"") -> 87 | B96: 2026 | C96: L3 - Impacto regional, nacional e internacional desde la extensión y proyección social | D96: =IFERROR(VLOOKUP(FORMULACIÓN!C96,Lists!$A$2:$B$6,2,FALSE),"") -> Coadyuvar con el desarrollo económico, social, cultural y ambiental a nivel regional, nacional e internacional; mediante la extensión y proyección social articulada con la investigación, creación, formación, innovación y transferencia tecnológica, que permita una interacción e integración permanente, amplia y diversa con el estado, la empresa y la sociedad. | E96: 6. Favorecer la proyección laboral de los egresados mediante el fortalecimiento de conocimientos y competencias requeridas para el contexto global. | F96: M1 - Educación continua y formación avanzada con enfoque global. | G96: Mejoramiento de la oferta de programas de educación continua, con 1 Centro de Lenguas extranjeras, 5 ambientes de aprendizaje innovadores implementados, 2.300 programas de educación continua ejecutadas en distintas modalidalidades (presencial, semipresencial, virtual y a distancia), 35 con enfoque diferencial, 12 con componente internacional y 130 convenios con entidades del sector público y privado | H96: P1 - Fortalecimiento de los programas de educación contínua con pertinencia regional, nacional e internacional a través de la modernización de los procesos. | I96: 0.18 | J96: Impulsar la oferta de programas de educación continua con componente internacional | K96: 0.15 | L96: Jefe del Departamento Extensión y Proyección Social | M96: PDI | N96: X | O96: Oferta de programas de educación continua con componente internacional | P96: N° de programas con componente internacional | Q96: Anual | R96: Unidad | S96: Programas de educacion continua que se caracterizan por contenido con componente internacional o docente/estudiante de talla internacional. (Justificado en formato correspondiente) | T96: Nuevo gestionado durante la vigencia | U96: 11 | V96: 0 | W96: 3 | X96: =IFERROR(IF($T96=Lists!$S$2,SUM(FORMULACIÓN!U96:W96),IF(FORMULACIÓN!$T96=Lists!$S$3,SUM(FORMULACIÓN!V96:W96),IF(FORMULACIÓN!$T96=Lists!$S$4,AVERAGE(FORMULACIÓN!V96:W96),IF(FORMULACIÓN!$T96=Lists!$S$5,OFFSET(U96,0,COUNTA(V96:W96)),IF(FORMULACIÓN!$T96=Lists!$S$6,AVERAGE(V96:W96),""))))),"") -> 3 | Y96: =IF($R96=Lists!$R$3,TEXT(FORMULACIÓN!X96,"00,00%"),IF(FORMULACIÓN!X96=0,0,TEXT(FORMULACIÓN!X96,"##.###"))) -> 3
A97: =IF(C97<>"",+A96+1,"") -> 88 | B97: 2026 | C97: L3 - Impacto regional, nacional e internacional desde la extensión y proyección social | D97: =IFERROR(VLOOKUP(FORMULACIÓN!C97,Lists!$A$2:$B$6,2,FALSE),"") -> Coadyuvar con el desarrollo económico, social, cultural y ambiental a nivel regional, nacional e internacional; mediante la extensión y proyección social articulada con la investigación, creación, formación, innovación y transferencia tecnológica, que permita una interacción e integración permanente, amplia y diversa con el estado, la empresa y la sociedad. | E97: 6. Favorecer la proyección laboral de los egresados mediante el fortalecimiento de conocimientos y competencias requeridas para el contexto global. | F97: M1 - Educación continua y formación avanzada con enfoque global. | G97: Mejoramiento de la oferta de programas de educación continua, con 1 Centro de Lenguas extranjeras, 5 ambientes de aprendizaje innovadores implementados, 2.300 programas de educación continua ejecutadas en distintas modalidalidades (presencial, semipresencial, virtual y a distancia), 35 con enfoque diferencial, 12 con componente internacional y 130 convenios con entidades del sector público y privado | H97: P1 - Fortalecimiento de los programas de educación contínua con pertinencia regional, nacional e internacional a través de la modernización de los procesos. | I97: 0.18 | J97: Impulsar la oferta de programas de educación continua con enfoque diferencial y/o capacidades diversas | K97: 0.1 | L97: Jefe del Departamento Extensión y Proyección Social | M97: PDI | N97: X | O97: Oferta de programas de educación continua con enfoque diferencial y/o capacidades diversas | P97: N° de programas de educación continua con enfoque diferencial y/o capacidades diversas implementados | Q97: Anual | R97: Unidad | S97: Programas de educación continua implementados con enfoque diferencial y/o para capacidades diversas. El enfoque diferencial considera las necesidades, características, intereses y contextos específicos de diversos grupos poblacionales, mientras que la atención a capacidades diversas abarca las diferentes habilidades, talentos y ritmos de aprendizaje individuales.(Vinculacion de poblacion con estas caracteristicas y contenido) | T97: Nuevo gestionado durante la vigencia | U97: 7 | V97: 0 | W97: 6 | X97: =IFERROR(IF($T97=Lists!$S$2,SUM(FORMULACIÓN!U97:W97),IF(FORMULACIÓN!$T97=Lists!$S$3,SUM(FORMULACIÓN!V97:W97),IF(FORMULACIÓN!$T97=Lists!$S$4,AVERAGE(FORMULACIÓN!V97:W97),IF(FORMULACIÓN!$T97=Lists!$S$5,OFFSET(U97,0,COUNTA(V97:W97)),IF(FORMULACIÓN!$T97=Lists!$S$6,AVERAGE(V97:W97),""))))),"") -> 6 | Y97: =IF($R97=Lists!$R$3,TEXT(FORMULACIÓN!X97,"00,00%"),IF(FORMULACIÓN!X97=0,0,TEXT(FORMULACIÓN!X97,"##.###"))) -> 6
A98: =IF(C98<>"",+A97+1,"") -> 89 | B98: 2026 | C98: L3 - Impacto regional, nacional e internacional desde la extensión y proyección social | D98: =IFERROR(VLOOKUP(FORMULACIÓN!C98,Lists!$A$2:$B$6,2,FALSE),"") -> Coadyuvar con el desarrollo económico, social, cultural y ambiental a nivel regional, nacional e internacional; mediante la extensión y proyección social articulada con la investigación, creación, formación, innovación y transferencia tecnológica, que permita una interacción e integración permanente, amplia y diversa con el estado, la empresa y la sociedad. | E98: 6. Favorecer la proyección laboral de los egresados mediante el fortalecimiento de conocimientos y competencias requeridas para el contexto global. | F98: M1 - Educación continua y formación avanzada con enfoque global. | G98: Mejoramiento de la oferta de programas de educación continua, con 1 Centro de Lenguas extranjeras, 5 ambientes de aprendizaje innovadores implementados, 2.300 programas de educación continua ejecutadas en distintas modalidalidades (presencial, semipresencial, virtual y a distancia), 35 con enfoque diferencial, 12 con componente internacional y 130 convenios con entidades del sector público y privado | H98: P1 - Fortalecimiento de los programas de educación contínua con pertinencia regional, nacional e internacional a través de la modernización de los procesos. | I98: 0.18 | J98: Impulsar la oferta de programas de educación continua en convenio con entidades del sector público y/o privado | K98: 0.1 | L98: Jefe del Departamento Extensión y Proyección Social | M98: PDI | N98: X | O98: Oferta de programas de educación continua basado en las necesidades específicas de entidades del sector público y/o privado | P98: N° de programas de educación continua realizados en convenio con entidades del sector público y/o privado | Q98: Semestral | R98: Unidad | S98: Programas de educacion continua realizado en convenios con entidades de sector publico y privado, incluye los programas de Cursos de Lenguas extranjeras a nivel regional (Kids, Juniors, Young y Adults) | T98: Nuevo gestionado durante la vigencia | U98: 11 | V98: 0 | W98: 5 | X98: =IFERROR(IF($T98=Lists!$S$2,SUM(FORMULACIÓN!U98:W98),IF(FORMULACIÓN!$T98=Lists!$S$3,SUM(FORMULACIÓN!V98:W98),IF(FORMULACIÓN!$T98=Lists!$S$4,AVERAGE(FORMULACIÓN!V98:W98),IF(FORMULACIÓN!$T98=Lists!$S$5,OFFSET(U98,0,COUNTA(V98:W98)),IF(FORMULACIÓN!$T98=Lists!$S$6,AVERAGE(V98:W98),""))))),"") -> 5 | Y98: =IF($R98=Lists!$R$3,TEXT(FORMULACIÓN!X98,"00,00%"),IF(FORMULACIÓN!X98=0,0,TEXT(FORMULACIÓN!X98,"##.###"))) -> 5
A99: =IF(C99<>"",+A98+1,"") -> 90 | B99: 2026 | C99: L3 - Impacto regional, nacional e internacional desde la extensión y proyección social | D99: =IFERROR(VLOOKUP(FORMULACIÓN!C99,Lists!$A$2:$B$6,2,FALSE),"") -> Coadyuvar con el desarrollo económico, social, cultural y ambiental a nivel regional, nacional e internacional; mediante la extensión y proyección social articulada con la investigación, creación, formación, innovación y transferencia tecnológica, que permita una interacción e integración permanente, amplia y diversa con el estado, la empresa y la sociedad. | E99: 6. Favorecer la proyección laboral de los egresados mediante el fortalecimiento de conocimientos y competencias requeridas para el contexto global. | F99: M1 - Educación continua y formación avanzada con enfoque global. | G99: Mejoramiento de la oferta de programas de educación continua, con 1 Centro de Lenguas extranjeras, 5 ambientes de aprendizaje innovadores implementados, 2.300 programas de educación continua ejecutadas en distintas modalidalidades (presencial, semipresencial, virtual y a distancia), 35 con enfoque diferencial, 12 con componente internacional y 130 convenios con entidades del sector público y privado | H99: P1 - Fortalecimiento de los programas de educación contínua con pertinencia regional, nacional e internacional a través de la modernización de los procesos. | I99: 0.18 | J99: Impulsar la oferta de programas de educación continua en convenio con entidades del sector público y/o privado | K99: 0.1 | L99: Jefe del Departamento Extensión y Proyección Social | M99: PA | O99: Oferta de cursos de CLE en modalidad (Presencial, semipresencial, virtual y a distancia) | P99: N° de cursos CLE en distintas modalidades | Q99: Anual | R99: Unidad | S99: Numero de cursos CLE, los cuales incluyen los numeros de grupos existentes por curso en distintas modalidades. | T99: Nuevo gestionado durante la vigencia | U99: 717 | V99: 0 | W99: 450 | X99: =IFERROR(IF($T99=Lists!$S$2,SUM(FORMULACIÓN!U99:W99),IF(FORMULACIÓN!$T99=Lists!$S$3,SUM(FORMULACIÓN!V99:W99),IF(FORMULACIÓN!$T99=Lists!$S$4,AVERAGE(FORMULACIÓN!V99:W99),IF(FORMULACIÓN!$T99=Lists!$S$5,OFFSET(U99,0,COUNTA(V99:W99)),IF(FORMULACIÓN!$T99=Lists!$S$6,AVERAGE(V99:W99),""))))),"") -> 450 | Y99: =IF($R99=Lists!$R$3,TEXT(FORMULACIÓN!X99,"00,00%"),IF(FORMULACIÓN!X99=0,0,TEXT(FORMULACIÓN!X99,"##.###"))) -> 450
A100: =IF(C100<>"",+A99+1,"") -> 91 | B100: 2026 | C100: L3 - Impacto regional, nacional e internacional desde la extensión y proyección social | D100: =IFERROR(VLOOKUP(FORMULACIÓN!C100,Lists!$A$2:$B$6,2,FALSE),"") -> Coadyuvar con el desarrollo económico, social, cultural y ambiental a nivel regional, nacional e internacional; mediante la extensión y proyección social articulada con la investigación, creación, formación, innovación y transferencia tecnológica, que permita una interacción e integración permanente, amplia y diversa con el estado, la empresa y la sociedad. | E100: 1. Promover la extensión y la proyección social como medio de vinculación de la universidad con la sociedad, en sinergia con el sector productivo para responder a sus demandas. | F100: M2 - Articulación con el sector productivo y sociedad. | G100: Concretar al menos 150 proyectos de extensión y proyección social remunerados con el sector público y/o privado a través de la gestión de alianzas y convenios a nivel nacional e internacional. | H100: P1 - Gestión de alianzas, convenios y proyectos para el fomento del desarrollo sostenible según la agenda (ODS), regional, nacional e internacional | I100: 0.15 | J100: Promover la oferta institucional para la prestación de bienes y servicios al sector público y/o privado e impactar de manera pertinente el entorno | K100: 0.2 | L100: Jefe del Departamento Extensión y Proyección Social | M100: PDI | O100: Proyectos de extensión y proyección social remunerados en alianza con el sector público y/o privado | P100: N° de proyectos de extensión y proyección social suscritos con el sector público y/o privado | Q100: Anual | R100: Unidad | S100: Proyectos de extensión y proyección social remunerados en alianza con el sector público y/o privado, muy orientados a los de consultoria | T100: Nuevo gestionado durante la vigencia | U100: 8 | V100: 0 | W100: 1 | X100: =IFERROR(IF($T100=Lists!$S$2,SUM(FORMULACIÓN!U100:W100),IF(FORMULACIÓN!$T100=Lists!$S$3,SUM(FORMULACIÓN!V100:W100),IF(FORMULACIÓN!$T100=Lists!$S$4,AVERAGE(FORMULACIÓN!V100:W100),IF(FORMULACIÓN!$T100=Lists!$S$5,OFFSET(U100,0,COUNTA(V100:W100)),IF(FORMULACIÓN!$T100=Lists!$S$6,AVERAGE(V100:W100),""))))),"") -> 1 | Y100: =IF($R100=Lists!$R$3,TEXT(FORMULACIÓN!X100,"00,00%"),IF(FORMULACIÓN!X100=0,0,TEXT(FORMULACIÓN!X100,"##.###"))) -> 1
A101: =IF(C101<>"",+A100+1,"") -> 92 | B101: 2026 | C101: L3 - Impacto regional, nacional e internacional desde la extensión y proyección social | D101: =IFERROR(VLOOKUP(FORMULACIÓN!C101,Lists!$A$2:$B$6,2,FALSE),"") -> Coadyuvar con el desarrollo económico, social, cultural y ambiental a nivel regional, nacional e internacional; mediante la extensión y proyección social articulada con la investigación, creación, formación, innovación y transferencia tecnológica, que permita una interacción e integración permanente, amplia y diversa con el estado, la empresa y la sociedad. | E101: 5. Innovación en los procesos de Extensión y Proyección social aplicando metodologías con enfoque hacia la cooperación entre disciplinas, uso de nuevas tecnologías, en concordancia con la naturaleza de las distintas áreas de conocimiento. | F101: M2 - Articulación con el sector productivo y sociedad. | G101: Incrementar en un 20% los ingresos del Centro de Investigaciones Científicas y Tecnológicas (CICIT) y Parque Tecnológico del Caribe (PTC) por servicios científicos y tecnológicos | H101: P1 - Gestión de alianzas, convenios y proyectos para el fomento del desarrollo sostenible según la agenda (ODS), regional, nacional e internacional | I101: 0.15 | J101: Impulsar la venta de servicios científicos y tecnológicos a través del CICIT | K101: 0.2 | L101: Jefe del Departamento Extensión y Proyección Social | M101: PDI | O101: Tasa de variación de ingresos del CICIT y PTC para la vigencia de 10 años | P101: [(Ingresos por servicios científicos y tecnológicos del CICIT año 1 - Ingresos por servicios científicos y tecnológicos del CICIT año 0) / Ingresos por servicios científicos y tecnológicos del CICIT año 0) ] * 100 | Q101: Anual | R101: Porcentaje | T101: Último valor reportado | U101: 0.02 | V101: 0 | W101: 0.02 | X101: =IFERROR(IF($T101=Lists!$S$2,SUM(FORMULACIÓN!U101:W101),IF(FORMULACIÓN!$T101=Lists!$S$3,SUM(FORMULACIÓN!V101:W101),IF(FORMULACIÓN!$T101=Lists!$S$4,AVERAGE(FORMULACIÓN!V101:W101),IF(FORMULACIÓN!$T101=Lists!$S$5,OFFSET(U101,0,COUNTA(V101:W101)),IF(FORMULACIÓN!$T101=Lists!$S$6,AVERAGE(V101:W101),""))))),"") -> 0.02 | Y101: =IF($R101=Lists!$R$3,TEXT(FORMULACIÓN!X101,"00,00%"),IF(FORMULACIÓN!X101=0,0,TEXT(FORMULACIÓN!X101,"##.###"))) -> 02,00%
